Workbook

Sheet Dashboard
A1: Case manager | B1: Malak | H1: Row Labels | I1: Count of Joining Date
A2: Claims Status | B2: Claimable | H2: Dina | I2: 16
A3: Dispute | B3: (All) | H3: Meaad | I3: 25
H4: Malak | I4: 9
A5: Row Labels | H5: Husain | I5: 38
A6: JCP/26/286008 | H6: Zainab Mattar | I6: 11
A7: JCP/25/167732 | H7: Mahdi | I7: 3
A8: JCP/24/095374 | H8: Grand Total | I8: 102
A9: JCP/25/183265
A10: JCP/24/146053
A11: JCP/24/098208
A12: Grand Total

Sheet Placements 25
A1: SL No. | B1: Case manager | C1: Ref No | D1: Name | E1: CPR | F1: Joining Date | G1: MoL | H1: Long MoL +3 Years | I1: Gender | J1: Education | K1: Salary | L1: Position | M1: Company | N1: Employer CR No. | O1: Employement Type | P1: Comments
A2: 14 | B2: Husain | C2: JCP/25/219615 | D2: HUSAIN ABDULMONEM HU MOTHANNA | E2: 010207910 | F2: 46005 | G2: Yes | I2: Male | J2: High School | K2: 450 | L2: Office Assistant | M2: ALMOAYYED CLEANING & MAINTENANCE W.L.L. | N2: 47533-1 | O2: Full time Direct Employment | P2: Payment without VAT
A3: 15 | B3: Husain | C3: JCP/25/232927 | D3: SAYED MOHAMED SAEED HASAN ALAWI | E3: 920401961 | F3: 46005 | G3: Yes | I3: Male | J3: Bachelors + | K3: 500 | L3: Sales Executive | M3: ALMOAYYED CONTRACTING GROUP W.L.L. | N3: 43090-1 | O3: Full time Direct Employment
A4: 16 | B4: Husain | C4: JCP/25/214227 | D4: FATEMA WALEED HASAN SHOWIATER | E4: 020905904 | F4: 46006 | G4: Yes | I4: Female | J4: Bachelors + | K4: 500 | L4: Trainee Mechanical engineer | M4: ALMOAYYED AIR CONDITIONING W.L.L. | N4: 76980-1 | O4: Full time Direct Employment | P4: Payment without VAT
A5: 17 | B5: Husain | C5: JCP/25/212208 | D5: WALAA ISA A. HASAN | E5: 990900045 | F5: 45865 | G5: Yes | I5: Female | J5: Bachelors + | K5: 700 | L5: Account Manager Specialist | M5: Student Plaform | N5: 127080-1 | O5: Full time Direct Employment | P5: Payment without VAT
A6: 18 | B6: Meaad | C6: JCP/25/223039 | D6: SAYED ALI HASHEM E. ALQASSAB | E6: 70809119 | F6: 45956 | G6: Yes | I6: Male | J6: High School | K6: 350 | L6: Driver | M6: SIMPLEX AL MOAYYED W.L.L | N6: 58313-1 | O6: Full time Direct Employment | P6: Payment without VAT
A7: 20 | B7: Dina | C7: JCP/25/233782 | D7: FATEMA JAAFAR MOHAMED FARHAN | E7: 040601854 | F7: 45939 | G7: Yes | I7: Female | J7: High School | K7: 350 | L7: Sales Lady | M7: Femi 9 | N7: 49089-3 | O7: Full time Direct Employment
A8: 29 | B8: Husain | C8: JCP/25/170479 | D8: Ali hasan Alaswami | E8: 930904079 | F8: 45692 | G8: Yes | H8: Yes | I8: Male | J8: High School | K8: 450 | L8: Safety officer | M8: Rafco | N8: 1856-1 | O8: Full time Direct Employment | P8: Payment without VAT
A9: 30 | B9: Husain | C9: JCP/25/213845 | D9: Sara Jamal Ahmed | E9: 970303629 | F9: 45874 | I9: Female | J9: Bachelors + | K9: 500 | L9: Consultant | M9: Propel Consult | N9: 75091-1 | O9: Insourced to Service Provider | P9: Payment without VAT
A10: 32 | B10: Husain | C10: JCP/25/170060 | D10: SALMAN ADEL OUN JASIM | E10: 050201182 | F10: 45697 | G10: Yes | I10: Male | J10: High School | K10: 350 | L10: Driver | M10: DRAGON BEACH HOTEL W.L.L | N10: 170835-2 | O10: Full time Direct Employment | P10: Payment without VAT
A11: 42 | B11: Husain | C11: JCP/25/213261 | D11: AMMAR SALEH HASAN AHMED ALI | E11: 000305910 | F11: 45893 | G11: Yes | I11: Male | J11: Diploma | K11: 450 | L11: Machine operator | M11: ARLA FOODS W.L.L | N11: 127867-1 | O11: Full time Direct Employment | P11: Payment without VAT
A12: 43 | B12: Husain | C12: JCP/25/217089 | D12: ALI HUSAIN ABDULLA KAD FARDAN | E12: 030400686 | F12: 45886 | G12: Yes | I12: Male | J12: High School | K12: 350 | L12: Security Cum Bell Boy | M12: Almanzil hotel | N12: 186174-1 | O12: Full time Direct Employment | P12: Payment without VAT
A13: 47 | B13: Husain | C13: JCP/25/171258 | D13: Noora Faqir | E13: 930911571 | F13: 45721 | I13: Female | J13: High School | K13: 350 | L13: Cashier/ Sales consultant | M13: BAHRAIN FINANCING COMPANY | N13: 35-10 | O13: Full time Direct Employment | P13: Payment without VAT
A14: 49 | B14: Husain | C14: JCP/25/153757 | D14: Sayed Moosa Mahdi Alawi Mohsen Ahmed | E14: 020100868 | F14: 45725 | I14: Male | J14: High School | K14: 350 | L14: Electrical technician | M14: IOT BAHRAIN TRADING | N14: 148642-1 | O14: Full time Direct Employment | P14: Payment without VAT
A15: 50 | B15: Husain | C15: JCP/24/096845 | D15: KARAR HUSAM ALI YATEEM | E15: 980405866 | F15: 45911 | G15: Yes | H15: Yes | I15: Male | J15: High School | K15: 500 | L15: Partner Care agent | M15: NINJA SUPPORT W.L.L | N15: 184823-1 | O15: Full time Direct Employment | P15: Payment without VAT
A16: 51 | B16: Husain | C16: JCP/25/225850 | D16: HASAN FADHEL HASAN ISMAEEL ALI | E16: 970102917 | F16: 45914 | I16: Male | J16: Bachelors + | K16: 500 | L16: Electronic engineer | M16: IOT BAHRAIN TRADING | N16: 148642-1 | O16: Full time Direct Employment | P16: Payment without VAT
A17: 52 | B17: Husain | C17: JCP/25/173504 | D17: Shuaib hasan Rustam | E17: 940205432 | F17: 45739 | G17: Yes | H17: Yes | I17: Male | J17: High School | K17: 400 | L17: Coordinator | M17: RAFFA INDUSTRIAL SERVICES W.L.L | N17: 1856-2 | O17: Full time Direct Employment | P17: Payment without VAT
A18: 53 | B18: Husain | C18: JCP/25/217425 | D18: ALI SALMAN HASAN ALI | E18: 960800360 | F18: 45922 | G18: Yes | H18: Yes | I18: Male | J18: High School | K18: 400 | L18: Forklift operator | M18: KONEXUS ALUMINIUM INTERNATIONAL CO. W.L.L | N18: 116589-1 | O18: Full time Direct Employment | P18: Payment without VAT
A19: 54 | B19: Husain | C19: JCP/24/047875 | D19: AMMAR SAYED YASER SAEED MOHAMED | E19: 960507680 | F19: 45922 | G19: Yes | H19: Yes | I19: Male | J19: Bachelors + | K19: 600 | L19: Partnership Specialist | M19: STUDENT PLATFORM W.L.L. | N19: 127080-1 | O19: Full time Direct Employment | P19: Payment without VAT
A20: 55 | B20: Meaad | C20: JCP/25/229307 | D20: Bader Abdulnabi Ebrahim | E20: 10306587 | F20: 45921 | G20: Yes | H20: Yes | I20: Male | J20: Bachelors + | K20: 378 | L20: Sales Executive | M20: BAHRAIN DUTY FREE CO. WLL | N20: 119146-1 | O20: Full time Direct Employment
A21: 56 | B21: Meaad | C21: JCP/25/174221 | D21: فاطمه حسن الليث | E21: 920300600 | F21: 45921 | I21: Female | J21: Bachelors + | K21: 500 | L21: Consultant | M21: GIG | N21: 75091-1
A22: 57 | B22: Husain | C22: JCP/25/180485 | D22: ساره ساتر | E22: 010306420 | F22: 45740 | G22: Yes | H22: Yes | I22: Female | J22: Bachelors + | K22: 500 | L22: Accountant | M22: KONEXUS ALUMINIUM INTERNATIONAL CO. W.L.L | N22: 116589-1 | O22: Full time Direct Employment | P22: Payment without VAT
A23: 58 | B23: Meaad | C23: JCP/25/194119 | D23: MAHDI MOHAMED MAHDI ALI | E23: 891103503 | F23: 45792 | I23: Male | M23: DRAGON BEACH HOTEL W.L.L | N23: 170835-2 | O23: Full time Direct Employment
A24: 59 | B24: Malak | C24: JCP/25/178761 | D24: MAJED MOHAMED ALI MOHSEN ZABAR | E24: 840201451 | F24: 45922 | G24: Yes | I24: Male | J24: Diploma | K24: 1200 | L24: Business Development Manager | M24: HAAND SOLUTIONS LTDA W.L.L | N24: 167652-01 | O24: Full time Direct Employment | P24: 6 Months Payment
A25: 60 | B25: Zainab Mattar | C25: JCP/25/231016 | D25: KHADIJA FAISAL ALIJASI AHMED | E25: 020608268 | F25: 45927 | G25: No | H25: No | I25: Female | J25: High School | K25: 350 | L25: Sales Lady | M25: FEMI 9 | N25: 49089-3 | O25: Full time Direct Employment
A26: 61 | B26: Meaad | C26: JCP/25/190585 | D26: ZAINAB MOHAMED GHULOOM ALI | E26: 1203282 | F26: 45811 | G26: Yes | I26: Female | J26: Bachelors + | K26: 500 | L26: sales designer | M26: ALMA KITCHENS FACTORY W.L.L | N26: 11017-10 | O26: Full time Direct Employment
A27: 64 | B27: Meaad | C27: JCP/25/195286 | D27: HASAN AQEEL ALI HASAN ALJESHI | E27: 950405051 | F27: 45819 | G27: Yes | I27: Male | J27: High School | M27: AHMED MANSOOR ALAALI | N27: 571-2 | O27: Full time Direct Employment
A28: 65 | B28: Dina | C28: JCP/24/094062 | D28: sayed ali noordeen ali | E28: 970303335 | F28: 46012 | G28: Yes | H28: Yes | I28: Male | J28: Diploma | K28: 700 | L28: Safety officer | M28: GULF TOBACCO COMPANY. W.L.L | N28: 145777-1 | O28: Full time Direct Employment
A29: 97 | B29: Husain | C29: JCP/24/142442 | D29: SAYED ALAA MOOSA MOHAMED FADHEL | E29: 890704791 | F29: 45931 | I29: Male | J29: Bachelors + | K29: 500 | L29: Sales officer | M29: MENWIN BUSINESS CONSULTANTS W.L.L | N29: 163331-1 | O29: Full time Direct Employment | P29: Payment without VAT, payment done for 6 months
A30: 98 | B30: Husain | C30: JCP/25/233173 | D30: KHALIFA EBRAHIM K. SAAD | E30: 890201641 | F30: 45935 | G30: Yes | I30: Male | J30: High School | K30: 350 | L30: Security officer | M30: THE K - HOTEL W.L.L | N30: 74418-1 | O30: Full time Direct Employment | P30: Payment without VAT, payment done for 6 months
A31: 99 | B31: Husain | C31: JCP/25/244587 | D31: EBRAHIM NAEEM A. MARHOON | E31: 920801471 | F31: 45939 | G31: Yes | I31: Male | J31: High School | K31: 420 | L31: Trainee- HSE officer | M31: ALMOAYYED CONTRACTING GROUP W.L.L. | N31: 43090-1 | O31: Full time Direct Employment | P31: payment done for 6 months
A32: 100 | B32: Husain | C32: JCP/24/147404 | D32: ALI HAFEDH ALI BUKAMAL | E32: 961204559 | F32: 45942 | G32: Yes | I32: Male | J32: Bachelors + | K32: 500 | L32: Admin officer | M32: BAHRAIN INSTITUTE FOR PEARLS AND GEMSTONES (DANAT) W.L.L | N32: 112090-1 | O32: Full time Direct Employment | P32: Payment without VAT, payment done for 6 months
A33: 101 | B33: Husain | C33: JCP/25/244921 | D33: Firas Ali Abdulla | E33: 990102378 | F33: 45942 | I33: Male | J33: Bachelors + | K33: 850 | L33: Marketing Manager | M33: STUDENT PLATFORM W.L.L. | N33: 127080-1 | O33: Full time Direct Employment | P33: payment done for 6 months
A34: 102 | B34: Husain | C34: JCP/24/109221 | D34: ALI GHULAM MOHAMED AMEERI | E34: 941113825 | F34: 45931 | G34: Yes | H34: Yes | I34: Male | J34: Bachelors + | K34: 500 | L34: sales executive | M34: MENWIN BUSINESS CONSULTANTS W.L.L | O34: Full time Direct Employment | P34: Payment without VAT, payment done for 6 months
A35: 103 | B35: Husain | C35: JCP/25/184255 | D35: hasan mohamed taqi | E35: 980308771 | F35: 45760 | I35: Male | J35: Bachelors + | K35: 500 | L35: Planning technician | M35: RAFFA INDUSTRIAL SERVICES W.L.L | N35: 1856-01 | O35: Full time Direct Employment | P35: Payment without VAT, payment done for 12 months
A36: 105 | B36: Husain | C36: JCP/25/163920 | D36: MOHAMED ALI NAJIMO ALRAYASHI | E36: 980903750 | F36: 45763 | G36: Yes | I36: Male | J36: Bachelors + | K36: 500 | L36: Engineering Aid | M36: RAFFA INDUSTRIAL SERVICES W.L.L | N36: 1856-01 | O36: Full time Direct Employment | P36: Payment without VAT, payment done for 12 months
A37: 106 | B37: Husain | C37: JCP/25/176279 | D37: AWADH ATEF M. ALATEF | E37: 050915215 | F37: 45741 | I37: Male | J37: High School | K37: 350 | L37: worker | M37: Bahrain pack | N37: 29242-01 | O37: Full time Direct Employment | P37: Payment without VAT, payment done for 12 months
A38: 107 | B38: Husain | C38: JCP/25/181964 | D38: SAMAR AMER HASAN ZAINUDDIN | E38: 951206605 | F38: 45751 | I38: Female | J38: Bachelors + | K38: 820 | L38: SUPERVISOR | M38: CHALHOUB & BUHINDI CO. W.L.L | N38: 39216-1 | O38: Full time Direct Employment | P38: Payment without VAT, payment done for 12 months
A39: 108 | B39: Husain | C39: JCP/24/141182 | D39: SAYED HASAN HAMZA HUSAIN JAAFAR | E39: 920500820 | F39: 45767 | I39: Male | J39: Bachelors + | K39: 700 | L39: Adminstrator | M39: WE GROW CONSULTANCY | N39: 117683-2 | O39: Full time Direct Employment | P39: Payment without VAT, payment done for 12 months
A40: 109 | B40: Malak | C40: JCP/25/229030 | D40: No Placement Recorded | F40: 45931
A41: 110 | B41: Zainab Mattar | C41: JCP/25/174409 | D41: HABIB MOHAMED A. MOHAMED | E41: 060104546 | F41: 45719 | G41: Yes | H41: No | I41: Male | J41: High School | K41: 350 | L41: Worker | M41: UNITED PAPER INDUSTRIES | N41: 29242-1 | O41: Full time Direct Employment
A42: 111 | B42: Zainab Mattar | C42: JCP/25/154261 | D42: HUSAIN ALI KHAMIS HAMMADI | E42: 860602907 | F42: 45735 | G42: Yes | H42: No | I42: Male | J42: Bachelors + | K42: 500 | L42: Bill Collector | M42: ALMOAYYED CONTRACTING W.L.L. | N42: 76979-1 | O42: Full time Direct Employment
A43: 112 | B43: Zainab Mattar | C43: JCP/25/177104 | D43: EBRAHIM NAZAR MANSOOR ALSAGHEER | E43: 010105018 | F43: 45741 | G43: Yes | H43: No | I43: Male | J43: Bachelors + | K43: 500 | L43: Leasing Agent | M43: DAR AL EJAR REAL ESTATE W.L.L | N43: 15879-5 | O43: Full time Direct Employment
A44: 113 | B44: Zainab Mattar | C44: JCP/25/205639 | D44: JASIM JAFFAR AHMEDAB ALBBARI | E44: 020104227 | F44: 45863 | G44: Yes | H44: No | I44: Male | J44: Bachelors + | K44: 500 | L44: Salesman | M44: SYED JUNAID ALAM W.L.L | N44: 52-6 | O44: Full time Direct Employment
A45: 114 | B45: Malak | C45: JCP/24/095374 | D45: No Placement Recorded | F45: 45710
A46: 115 | B46: Malak | C46: JCP/25/183265 | D46: No Placement Recorded | F46: 45760
A47: 116 | B47: Zainab Mattar | C47: JCP/25/217023 | D47: AHMED EBRAHIM KHAMIS AHMED | E47: 060301686 | F47: 45886 | G47: Yes | H47: No | I47: Male | J47: High School | K47: 350 | L47: Store Associate | M47: HOME CENTRE B.S.C CLOSED | N47: 17705-30 | O47: Full time Direct Employment
A48: 117 | B48: Zainab Mattar | C48: JCP/25/167640 | D48: SHUAIB MOHAMED REDHA MOHAMED | E48: 050911430 | F48: 45881 | G48: Yes | H48: No | I48: Male | J48: High School | K48: 400 | L48: Security | M48: RAFFA INDUSTRIAL SERVICES W.L.L | N48: 1856-2 | O48: Full time Direct Employment
A49: 118 | B49: Zainab Mattar | C49: JCP/25/221888 | D49: AHMED BAQER ISA MAHROOS | E49: 941109259 | F49: 45902 | G49: Yes | H49: Yes | I49: Male | J49: Bachelors + | K49: 700 | L49: Project Executive | M49: CLAVIS EVENTS | N49: 128294-1 | O49: Full time Direct Employment
A50: 119 | B50: Malak | C50: JCP/24/146053 | D50: No Placement Recorded | F50: 45761
A51: 120 | B51: Malak | C51: JCP/24/098208 | D51: No Placement Recorded | F51: 45634
A52: 121 | B52: Zainab Mattar | C52: JCP/25/218077 | D52: ZAHID SHARIF KHAN BAGH ABDULREHMAN | E52: 040918890 | F52: 45921 | G52: Yes | H52: No | I52: Male | J52: High School | K52: 350 | L52: Security | M52: AL MANZIL HOTEL W.L.L | N52: 186174-1 | O52: Full time Direct Employment
A53: 122 | B53: Meaad | C53: JCP/25/195286/PMT/001 | D53: Hasan Aqeel Aljeshi | E53: 950405051 | F53: 45819 | G53: Yes | H53: Yes | I53: Male | J53: High School | M53: AHMED MANSOOR ALAALI | N53: 571-2 | O53: Full time Direct Employment
A54: 123 | B54: Meaad | C54: JCP/25/229307 | D54: BADER ABDULNABI K. EBRAHIM | E54: 10306587 | F54: 45921 | G54: Yes | H54: Yes | I54: Male | J54: Bachelors + | K54: 378 | L54: Sales | M54: BAHRAIN DUTY FREE CO. WLL | N54: 119146-1 | O54: Full time Direct Employment
A55: 124 | B55: Meaad | C55: JCP/25/234452 | D55: AYAH SHAFEEQ A. ABDULHUSAIN | E55: 21106398 | F55: 45939 | G55: Yes | H55: Yes | I55: Female | J55: Bachelors + | K55: 500 | M55: IRead | N55: 79663-3 | O55: Full time Direct Employment
A56: 126 | B56: Meaad | C56: JCP/25/207044 | D56: SARA NASER A. ALATTAR | E56: 890300763 | F56: - | G56: Yes | H56: Yes | I56: Male | J56: Bachelors + | K56: 850 | L56: QA/QC | M56: ALMOAYYED CONTRACTING W.L.L. | N56: 76979-1 | O56: Full time Direct Employment
A57: 127 | B57: Meaad | C57: JCP/25/229327 | D57: FATIMA ALTUHAMI BINAASHER ALABSI | E57: 810712660 | F57: 45931 | G57: Yes | H57: Yes | I57: Female | J57: High School | K57: 400 | L57: Administrator | M57: Kangaroo Kids International Preschool | N57: 183468-01 | O57: Full time Direct Employment
A58: 128 | B58: Meaad | C58: JCP/25/245831/PMT/002 | D58: ALI KHALIL BAQER EATMADI | E58: 981100244 | F58: 45942 | G58: yes | H58: yes | I58: Male | J58: Bachelors + | K58: 378 | L58: Sales | M58: BAHRAIN DUTY FREE CO. WLL | N58: 119146-1 | O58: Full time Direct Employment
A59: 131 | B59: Khalifa | E59: 930207041 | F59: - | I59: Male | J59: Bachelors + | L59: Logistics Operation Specialist | M59: NINJA SUPPORT W.L.L | N59: 184823-1
A60: 133 | B60: Husain | C60: JCP/24/106751 | D60: Zia Urrahman Fida | E60: 990505294 | F60: 45769 | G60: Yes | H60: Yes | I60: Male | J60: High School | K60: 356 | L60: Rental Sales agent | M60: BIN HINDI TRANSPORT COMPANY W.L.L | N60: 62548-1 | O60: Full time Direct Employment | P60: Payment without VAT, payment done for 12 months
A61: 134 | B61: Meaad | C61: JCP/25/193738 | D61: AHMED MOHAMMED ABDUL ALSHOALA | E61: 930604547 | F61: - | G61: Yes | H61: Yes | I61: Male | J61: High School | K61: 475 | L61: Logistics Operation Specialist | M61: NINJA SUPPORT W.L.L | N61: 184823-1 | O61: Full time Direct Employment
A62: 135 | F62: -
A63: 136 | F63: -
A64: 137 | B64: Husain | C64: JCP/25/179588 | D64: SALMAN FAISAL SALMAN SALMAN | E64: 011100346 | F64: 45776 | G64: Yes | J64: High School | K64: 350 | L64: Securiry officer | M64: THE K - HOTEL W.L.L | N64: 74418-1 | O64: Full time Direct Employment | P64: Payment without VAT, payment done for 12 months
A65: 138 | B65: Husain | C65: JCP/25/232222 | D65: Ali Hasan AlNoaimi | E65: 941005623 | F65: 45938 | G65: Yes | H65: Yes | I65: Male | J65: Bachelors + | K65: 1400 | M65: ENQUEST GLOBAL SERVICES LTD BRANCH OF A FOREIGN COMPANY | N65: 187741-1 | O65: Full time Direct Employment | P65: payment done for 6 months
A66: 139 | B66: Husain | C66: JCP/25/190379 | D66: HUSAIN ALI MANSOOR ALKOUS | E66: 921100329 | F66: 45782 | J66: High School | K66: 350 | L66: Driver | M66: ALMOAYYED CONTRACTING GROUP W.L.L. | N66: 76979-1 | O66: Full time Direct Employment | P66: Payment without VAT, payment done for 12 months
A67: 140 | B67: Dina | C67: JCP/25/182203 | D67: Ali Faisal Ali | E67: 840704836 | F67: 45779 | G67: Yes | J67: High School | K67: 650 | L67: Housing and Accomdation in charge | M67: ALMOAYYED CONTRACTING GROUP W.L.L. | N67: 76979-1 | O67: Full time Direct Employment | P67: Payment without VAT, payment done for 6 months
A68: 141 | B68: Husain | C68: JCP/25/189869 | D68: SAYED AHMED JUMA MOHAMED HUSAIN | E68: 990200817 | F68: 45785 | G68: Yes | H68: Yes | I68: Male | J68: High School | K68: 350 | L68: Helper | M68: ALMOAYYED AIR CONDENTIONING | N68: 769800-1 | O68: Full time Direct Employment | P68: Payment without VAT, payment done for 12 months
A69: 142 | B69: Husain | C69: JCP/25/253223 | D69: ahmed ali alghazal | E69: 990806782 | F69: 45786 | J69: High School | K69: 435 | L69: Healthclub supervisor | M69: THE K - HOTEL W.L.L | N69: 74418-1 | O69: Full time Direct Employment | P69: Payment with VAT, payment done for 6 months
A70: 143 | B70: Husain | C70: JCP/25/188262 | D70: BAYAN YUSUF EBRAHIM ABDULRASOOL | E70: 991209850 | F70: 45782 | G70: Yes | H70: Yes | I70: Male | J70: Bachelors + | K70: 500 | L70: Office coordinator | M70: ALMOAYYED AIR CONDENTIONING | N70: 769800-1 | O70: Full time Direct Employment | P70: Payment without VAT, payment done for 12 months
A71: 144 | B71: Husain | C71: JCP/24/094433 | D71: BASMA AHMED ALI ALSHEHABI | E71: 890701989 | F71: 45972 | G71: Yes | I71: Female | J71: Bachelors + | K71: 680 | L71: Officer- client services | M71: BAHRAIN INSTITUTE OF PEARLS AND GEMSTONES (DANAT) W.L.L | O71: Full time Direct Employment | P71: Payment with VAT, payment done for 6 months
A72: 145 | B72: Husain | C72: JCP/25/254396 | D72: AQEELA MOHAMED JAAFAR AHMED ABDULLA | E72: 950208574 | F72: 45974 | I72: Female | J72: Bachelors + | K72: 600 | L72: Marketing and Public relation execuitve | M72: ALMOAYYED CONTRACTING GROUP W.L.L. | N72: 43090-1 | O72: Full time Direct Employment | P72: Payment with VAT, payment done for 6 months
A73: 146 | B73: Husain | C73: JCP/25/254252 | D73: FADHEL ABBAS SALMAN ALGHANEM | E73: 741103958 | F73: 45979 | I73: Male | J73: High School | K73: 350 | L73: Light Driver | M73: ALMOAYYED TRANSPORT | N73: 798440-1 | O73: Full time Direct Employment | P73: Payment with VAT, payment done for 6 months
A74: 147 | B74: Husain | C74: JCP/25/256699 | D74: HASAN AHMED MOHAMED FARDAN | E74: 890807655 | F74: 45979 | I74: Male | J74: High School | K74: 350 | L74: Light Driver | M74: ALMOAYYED TRANSPORT | N74: 798440-1 | O74: Full time Direct Employment | P74: Payment with VAT, payment done for 6 months
A75: 148 | B75: Husain | C75: JCP/25/194678 | D75: MASOOMA ABDULNABI SALMAN SALMAN | E75: 920406467 | F75: 45796 | I75: Male | J75: Bachelors + | K75: 600 | L75: Sales executive | M75: DAR AL EJAR REAL ESTATE W.L.L | N75: 15879-5 | O75: Full time Direct Employment | P75: Payment without VAT, payment done for 12 months
A76: 149 | B76: Husain | C76: JCP/25/195337 | D76: Sayed Hasan Moos Mahdi Kadhem Salman | E76: 020909063 | F76: 45797 | I76: Male | J76: High School | K76: 400 | L76: Sales executive | M76: MATROOK INTERCONTINENTAL BUILDING SOLUTIONS W.L.L | N76: 117877-1 | O76: Full time Direct Employment | P76: Payment without VAT, payment done for 12 months
A77: 150 | B77: Husain | C77: JCP/25/258923 | D77: ALI HASANAIN SALMAN ALI EBRAHIM | E77: 020708769 | F77: 45804 | I77: Male | J77: Bachelors + | K77: 600 | L77: Trainee engineer | M77: ALMOAYYED CONTRACTING GROUP W.L.L. | N77: 43090-1 | O77: Full time Direct Employment | P77: Payment with VAT, payment done for 6 months
A78: 151 | B78: Husain | C78: JCP/25/164337 | D78: ALYA JAMAL ATEYA ALSAKRAN | E78: 020409923 | F78: 45983 | I78: Female | J78: High School | K78: 350 | L78: Sales associate | M78: HOME CENTRE B.S.C CLOSED | N78: 17705-30 | O78: Full time Direct Employment | P78: Payment without VAT, payment done for 6 months
A79: 152 | B79: Husain | C79: JCP/25/163851 | D79: SAYED MUNTADHER OMRAN A. jaafar | E79: 050507478 | F79: 45983 | I79: Male | J79: High School | K79: 350 | L79: Sales associate | M79: SHOE MART B.S.C. - CLOSED | N79: 17705-5 | O79: Full time Direct Employment | P79: Payment without VAT, payment done for 6 months
A80: 153 | B80: Husain | C80: JCP/25/261206 | D80: KHALED WALEED ABDULHAMEED ALALAWI | E80: 970802757 | F80: 45999 | I80: Male | J80: Bachelors + | K80: 600 | L80: Guest Service agent | M80: DRAGON BEACH HOTEL W.L.L | N80: 170835-2 | O80: Full time Direct Employment | P80: Payment with VAT, payment done for 6 months
A81: 154 | B81: Husain | D81: MUSTAFA ALI S. ALGHAZAL | E81: 060410582 | F81: 45984 | I81: Male | J81: High School | K81: 350 | L81: Sales associate | M81: HOME CENTRE B.S.C CLOSED | N81: 17705-30 | O81: Full time Direct Employment | P81: Payment without VAT, payment done for 6 months
A82: 155 | D82: AYMAN ABDULADHEEM ALI ALI | E82: 020802056 | F82: 45987 | I82: Male | J82: High School | K82: 350 | L82: Worker | M82: AHMED MANSOOR ALAALI | N82: 571-2 | O82: Full time Direct Employment | P82: Payment without VAT, payment done for 12 months
A83: 156 | B83: Husain | C83: JCP/25/219615 | D83: HUSAIN ABDULMONEM H. AHMED | E83: 010207910 | F83: 46005 | I83: Male | J83: High School | K83: 450 | L83: Office assistant | M83: ALMOAYYED CLEANING & MAINTENANCE W.L.L. | N83: 47533-1 | O83: Full time Direct Employment | P83: Payment without VAT, payment done for 6 months
A84: 157 | B84: Husain | C84: JCP/25/232927 | D84: SAYED MOHAMED SAEED HASAN ALAWI | E84: 920401961 | F84: 46005 | I84: Male | J84: Bachelors + | K84: 500 | L84: sales executive | M84: ALMOAYYED CONTRACTING GROUP W.L.L. | N84: 43090-1 | O84: Full time Direct Employment | P84: Payment with VAT, payment done for 6 months
A85: 158 | B85: Husain | C85: JCP/25/214227 | D85: FATEMA WALEED HASAN SHOWIATER | E85: 020905904 | F85: 46006 | I85: Female | J85: Bachelors + | K85: 500 | L85: Trainee Mechanical engineer | M85: ALMOAYYED AIR CONDITIONING W.L.L. | N85: 76980-1 | O85: Full time Direct Employment | P85: Payment without VAT, payment done for 6 months
A86: 159 | B86: Husain | C86: JCP/25/181682 | D86: SALEH EBRAHIM NAJI ABDULKARIM | E86: 020502141 | F86: 45823 | I86: Male | J86: Bachelors + | K86: 500 | L86: Training Operations and Adminstrative specialist | M86: SIGMA EXPERTS FOR TRAINING AND CONSULTANCY COMPANY W.L.L | N86: 81666-1 | O86: Full time Direct Employment | P86: Payment without VAT, payment done for 12 months
A87: 160 | B87: Husain | C87: JCP/25/206635 | D87: HUSAIN ABDULNABI HASAN NASER | E87: 040303233 | F87: 45860 | I87: Male | J87: High School | K87: 350 | L87: worker | M87: Bahrain pack | N87: 29242-01 | O87: Full time Direct Employment | P87: Payment without VAT, payment done for 6 months
A88: 161 | B88: Husain | C88: JCP/25/206635 | D88: HUSAIN ABDULNABI HASAN NASER | E88: 040303233 | F88: 45860 | I88: Male | J88: High School | K88: 350 | L88: worker | M88: Bahrain pack | N88: 29242-01 | O88: Full time Direct Employment | P88: Payment without VAT, payment done for 12 months
A89: 162 | B89: Husain | C89: JCP/25/213845 | D89: No Placement Recorded | F89: - | P89: Payment without VAT, payment done for 6 months
A90: 163 | C90: JCP/25/221932 | D90: ZAHRA ABDULGHANI I. ALMARZOOQ | E90: 000500623 | F90: 45902 | I90: Male | J90: Bachelors + | K90: 510 | L90: Interior design | M90: CLAVIS EVENTS | N90: 128294-1 | O90: Full time Direct Employment | P90: Payment without VAT, payment done for 6 months and 12 months
A91: 164 | C91: JCP/25/219675 | D91: NOOR AHMED J. ALDOY | E91: 050210696 | F91: 45902 | I91: Male | J91: Bachelors + | K91: 500 | L91: sales | M91: SYED JUNAID ALAM W.L.L | N91: 52-6 | O91: Full time Direct Employment | P91: Payment without VAT, payment done for 6 months and 12 months
A92: 165 | B92: Husain | C92: JCP/24/096845 | D92: KARRAR HUSAM ALI YATEEM | E92: 980405866 | F92: 45911 | I92: Male | J92: Bachelors + | K92: 500 | M92: NINJA SUPPORT W.L.L | N92: 184823-1 | O92: Full time Direct Employment | P92: Payment without VAT, payment done for 12 months
A93: 166 | B93: Husain | C93: JCP/25/225850 | D93: HASAN FADHEL HASAN ALI | E93: 970102917 | F93: 14-9-2025 | I93: Male | J93: Bachelors + | K93: 500 | M93: IOT BAHRAIN TRADING | N93: 148642-1 | O93: Full time Direct Employment | P93: Payment without VAT, payment done for 12 months
A94: 167 | B94: Husain | C94: JCP/25/217425 | D94: ALI SALMAN HASAN ALI | E94: 960800360 | F94: 21-9-25 | I94: Male | J94: Bachelors + | K94: 500 | M94: KONEXUS ALUMINIUM INTERNATIONAL CO. W.L.L | N94: 116589-1 | O94: Full time Direct Employment | P94: Payment without VAT, payment done for 12 months
A95: 168 | F95: -
A96: 169 | F96: -
A97: 170 | F97: -
A98: 171 | F98: -
A99: 172 | F99: -
A100: 173 | F100: -
...

Sheet Placements 26
A1: SL No. | B1: Case manager | C1: Ref No | D1: Name | E1: CPR | F1: Joining Date | G1: MoL | H1: Long MoL +3 Years | I1: Gender | J1: Education | K1: Salary | L1: Position | M1: Company | N1: Employer CR No. | O1: Employement Type | P1: Comments
A2: =ROW() - ROW(Table1[[#Headers],[SL No.]]) -> 1 | B2: Husain | C2: JCP/25/172042 | D2: WALEED ABDULWAHID J ABDULAZIZ | E2: 040710890 | F2: 46028 | G2: Yes | K2: 350 | L2: Sales | M2: CENTRE POINT COLOUR | N2: 17705-34 | O2: Full time Direct Employment | P2: Payment without VAT
A3: =ROW() - ROW(Table1[[#Headers],[SL No.]]) -> 2 | B3: Meaad | C3: JCP/24/057296 | D3: ASMA MOHAMMAD ASHFAQMO DIN | E3: 010706941 | F3: 46035 | G3: Yes | I3: Female | J3: Bachelors + | K3: 500 | L3: Quality assurance specialist | M3: Konexus | N3: 116589-1 | O3: Full time Direct Employment
A4: =ROW() - ROW(Table1[[#Headers],[SL No.]]) -> 3 | B4: Malak | C4: JCP/25/218398 | D4: ZIYAD TAREQ MAJEDA ALTHAWADI | E4: 980309620 | F4: 46033 | G4: Yes | I4: Male | J4: Bachelors + | K4: 508 | L4: Sales Executive | M4: Bahrain Duty Free | N4: 119146-1 | O4: Full time Direct Employment
A5: =ROW() - ROW(Table1[[#Headers],[SL No.]]) -> 4 | B5: Zainab Mattar | C5: JCP/25/183340 | D5: AYSHA OMAR SALEH AL ALYAZEEDI | E5: 031103103 | F5: 46033 | G5: Yes | I5: Female | J5: Diploma | K5: 482 | L5: Sales Executive | M5: Bahrain Duty Free | N5: 119146-1 | O5: Full time Direct Employment
A6: =ROW() - ROW(Table1[[#Headers],[SL No.]]) -> 5 | B6: Meaad | C6: JCP/25/210558 | D6: ali abdulameer ali ali mohamed | E6: 990805476 | F6: 46041 | G6: Yes | H6: Yes | I6: Male | J6: High School | K6: 350 | L6: Cashier | M6: GRILL LAND RESTAURANT W.L.L | N6: 121532-1 | O6: Full time Direct Employment | P6: Payment without VAT
A7: =ROW() - ROW(Table1[[#Headers],[SL No.]]) -> 6 | B7: Meaad | C7: JCP/25/267702 | D7: ABBAS AHMED A ALHANNAN | E7: 920305890 | F7: 46033 | G7: Yes | I7: Male | J7: High School | K7: 350 | L7: Dispatcher | M7: Manama Steels | N7: 103226-1 | O7: Full time Direct Employment
A8: =ROW() - ROW(Table1[[#Headers],[SL No.]]) -> 7 | B8: Meaad | C8: JCP/25/267727 | D8: MAYTHAM MOHAMED JAAFAR A. MOHAMED ALI | E8: 910601313 | F8: 46033 | I8: Male | J8: High School | K8: 350 | L8: Driver | M8: Manama Steels | N8: 103226-1 | O8: Full time Direct Employment
A9: =ROW() - ROW(Table1[[#Headers],[SL No.]]) -> 8 | B9: Zainab Mattar | C9: JCP/25/204298 | D9: ABDULLA MOHAMED HOORAN MOHAMED AWAD ALENEZI | E9: 000811084 | F9: 46033 | G9: Yes | I9: Male | J9: Bachelors + | K9: 508 | L9: Sales Executive | M9: Bahrain Duty Free | N9: 119146-1 | O9: Full time Direct Employment | P9: Payment without VAT
A10: =ROW() - ROW(Table1[[#Headers],[SL No.]]) -> 9 | B10: Meaad | C10: JCP/26/268524 | D10: LULWA EZZ EBRAHIM ABDULAZIZ RASHED ALBANKI | E10: 970409397 | F10: 46033 | G10: Yes | I10: Female | J10: Bachelors + | K10: 508 | L10: Sales Executive | M10: Bahrain Duty Free | N10: 119146-1
A11: =ROW() - ROW(Table1[[#Headers],[SL No.]]) -> 10 | B11: Mahdi | C11: JCP/26/268505 | D11: YUSUF ALI YUSUF HABIB DAGHER | E11: 041001389 | F11: 46033 | I11: Male | J11: High School | K11: 482 | L11: Sales Executive | M11: Bahrain Duty Free | N11: 119146-1
A12: =ROW() - ROW(Table1[[#Headers],[SL No.]]) -> 11 | B12: Meaad | C12: JCP/26/268879 | D12: MERZA JAMEEL MIRZA ALARADI | E12: 961006579 | F12: 46033 | G12: Yes | H12: Yes | I12: Male | J12: Bachelors + | K12: 508 | L12: Sales Executive | M12: Bahrain Duty Free | N12: 119146-1 | O12: Full time Direct Employment
A13: =ROW() - ROW(Table1[[#Headers],[SL No.]]) -> 12 | B13: Mahdi | C13: JCP/26/268526 | D13: AHMED WAHEED AKHTAR M. ALI | E13: 020302720 | F13: 46033 | G13: Yes | H13: Yes | I13: Male | J13: High School | K13: 508 | L13: Sales Executive | M13: Bahrain Duty Free | N13: 119146-1 | O13: Full time Direct Employment
A14: =ROW() - ROW(Table1[[#Headers],[SL No.]]) -> 13 | B14: Malak | C14: JCP/25/219711 | D14: FATIMA HASAN ABDULLA BUHMAID | E14: 990701140 | F14: 46033 | G14: Yes | H14: Yes | I14: Female | J14: Diploma | K14: 482 | L14: Sales Executive | M14: Bahrain Duty Free | N14: 119146-1 | O14: Full time Direct Employment | P14: Payment without VAT
A15: =ROW() - ROW(Table1[[#Headers],[SL No.]]) -> 14 | B15: Husain | C15: JCP/25/219615 | D15: HUSAIN ABDULMONEM HU MOTHANNA | E15: 010207910 | F15: 46005 | G15: Yes | I15: Male | J15: High School | K15: 450 | L15: Office Assistant | M15: ALMOAYYED CLEANING & MAINTENANCE W.L.L. | N15: 47533-1 | O15: Full time Direct Employment | P15: Payment without VAT
A16: =ROW() - ROW(Table1[[#Headers],[SL No.]]) -> 15 | B16: Husain | C16: JCP/25/232927 | D16: SAYED MOHAMED SAEED HASAN ALAWI | E16: 920401961 | F16: 46005 | G16: Yes | I16: Male | J16: Bachelors + | K16: 500 | L16: Sales Executive | M16: ALMOAYYED CONTRACTING GROUP W.L.L. | N16: 43090-1 | O16: Full time Direct Employment
A17: =ROW() - ROW(Table1[[#Headers],[SL No.]]) -> 16 | B17: Husain | C17: JCP/25/214227 | D17: FATEMA WALEED HASAN SHOWIATER | E17: 020905904 | F17: 46006 | G17: Yes | I17: Female | J17: Bachelors + | K17: 500 | L17: Trainee Mechanical engineer | M17: ALMOAYYED AIR CONDITIONING W.L.L. | N17: 76980-1 | O17: Full time Direct Employment | P17: Payment without VAT
A18: =ROW() - ROW(Table1[[#Headers],[SL No.]]) -> 17 | B18: Husain | C18: JCP/25/212208 | D18: WALAA ISA A. HASAN | E18: 990900045 | F18: 45865 | G18: Yes | I18: Female | J18: Bachelors + | K18: 700 | L18: Account Manager Specialist | M18: Student Plaform | N18: 127080-1 | O18: Full time Direct Employment | P18: Payment without VAT
A19: =ROW() - ROW(Table1[[#Headers],[SL No.]]) -> 18 | B19: Meaad | C19: JCP/25/223039 | D19: SAYED ALI HASHEM E. ALQASSAB | E19: 70809119 | F19: 45956 | G19: Yes | I19: Male | J19: High School | K19: 350 | L19: Driver | M19: SIMPLEX AL MOAYYED W.L.L | N19: 58313-1 | O19: Full time Direct Employment | P19: Payment without VAT
A20: =ROW() - ROW(Table1[[#Headers],[SL No.]]) -> 19 | B20: Malak | C20: JCP/25/233228 | D20: SYED HAMID NAZIR HUSSAIN SHAH PIRZAMAN SHAH | E20: 020515189 | F20: 46054 | G20: Yes | I20: Male | J20: Diploma | K20: 430 | L20: Accountant | M20: Harmony Music Gate | N20: 50358-1 | O20: Full time Direct Employment
A21: =ROW() - ROW(Table1[[#Headers],[SL No.]]) -> 20 | B21: Dina | C21: JCP/25/233782 | D21: FATEMA JAAFAR MOHAMED FARHAN | E21: 040601854 | F21: 45939 | G21: Yes | I21: Female | J21: High School | K21: 350 | L21: Sales Lady | M21: Femi 9 | N21: 49089-3 | O21: Full time Direct Employment
A22: =ROW() - ROW(Table1[[#Headers],[SL No.]]) -> 21 | B22: Zainab Mattar | C22: JCP/25/262810 | D22: GHASSAN ABDULLA MAHDI MAHDI | E22: 861203992 | F22: 46040 | G22: Yes | H22: Yes | I22: Male | J22: Bachelors + | K22: 800 | L22: Senior Accountant | M22: Naseef | N22: 22729-5 | O22: Full time Direct Employment
A23: =ROW() - ROW(Table1[[#Headers],[SL No.]]) -> 22 | B23: Husain | C23: JCP/26/283826 | D23: Ali Husain Seroor | E23: 941100049 | F23: 46050 | G23: Yes | H23: Yes | I23: Male | J23: High School | K23: 400 | L23: Technician | M23: Old School Garage | N23: 94591-1 | O23: Full time Direct Employment | P23: Payment with VAT
A24: =ROW() - ROW(Table1[[#Headers],[SL No.]]) -> 23 | B24: Husain | C24: JCP/25/171059 | D24: ZAINAB NASER MOHAMED MAHMOOD ALALWAANI | E24: 980602564 | F24: 46055 | G24: No | H24: No | I24: Female | J24: High School | K24: 520 | L24: Sales Executive | M24: CHALHOUS & BI,,HINDI W.L.L. | N24: 39216-1 | O24: Full time Direct Employment | P24: Payment without VAT
A25: =ROW() - ROW(Table1[[#Headers],[SL No.]]) -> 24 | B25: Husain | C25: JCP/25/171458 | D25: HUSAIN MUSTAFA ALI ALMAJED | E25: 940101645 | F25: 46055 | G25: Yes | I25: Male | J25: High School | K25: 350 | L25: STOREKEEPER | M25: CHALHOUS & BI,,HINDI W.L.L. | N25: 39216-1 | O25: Full time Direct Employment | P25: Payment without VAT
A26: =ROW() - ROW(Table1[[#Headers],[SL No.]]) -> 25 | B26: Meaad | C26: JCP/25/223860 | D26: duaa ahmedhisham t bintin | E26: 880545151 | F26: 46050 | G26: No | H26: No | I26: Female | J26: Bachelors + | K26: 580 | L26: Marketing Execituve | M26: AHMED MANSOOR AL-ALI BSC | N26: 571-2 | O26: Full time Direct Employment | P26: Payment without VAT
A27: =ROW() - ROW(Table1[[#Headers],[SL No.]]) -> 26 | B27: Meaad | C27: JCP/25/258736 | D27: Hasan Abdulnabi Tarada | E27: 991209095 | F27: 46047 | K27: 600 | L27: Auditor | M27: Sayed Junaid Alam | N27: 52-1 | O27: Full time Direct Employment
A28: =ROW() - ROW(Table1[[#Headers],[SL No.]]) -> 27 | B28: Zainab Mattar | C28: JCP/24/120499 | D28: MUSTAFA ABDULHAMEED QA HUSAIN | E28: 990200094 | F28: 46033 | G28: Yes | I28: Male | J28: Bachelors + | K28: 500 | L28: ICT Specialist | M28: Total Reliance for Construction, Trade and Consultancy | N28: 170032-1 | O28: Full time Direct Employment
A29: =ROW() - ROW(Table1[[#Headers],[SL No.]]) -> 28 | B29: Zainab Almaroom | C29: JCP/25/262077 | D29: MAHMOOD JAAFAR ABDULLA JASIM MOHAMED | E29: 891104186 | F29: 46028 | J29: Bachelors + | K29: 550 | L29: Front DEsk | M29: WPA BAHRAIN SPORTS W.L.L | N29: 175641-1 | O29: Full time Direct Employment | P29: Payment without VAT
A30: =ROW() - ROW(Table1[[#Headers],[SL No.]]) -> 29 | B30: Husain | C30: JCP/25/170479 | D30: Ali hasan Alaswami | E30: 930904079 | F30: 45692 | G30: Yes | H30: Yes | I30: Male | J30: High School | K30: 450 | L30: Safety officer | M30: Rafco | N30: 1856-1 | O30: Full time Direct Employment | P30: Payment without VAT
A31: =ROW() - ROW(Table1[[#Headers],[SL No.]]) -> 30 | B31: Husain | C31: JCP/25/213845 | D31: Sara Jamal Ahmed | E31: 970303629 | F31: 45874 | I31: Female | J31: Bachelors + | K31: 500 | L31: Consultant | M31: Propel Consult | N31: 75091-1 | O31: Insourced to Service Provider | P31: Payment without VAT
A32: =ROW() - ROW(Table1[[#Headers],[SL No.]]) -> 31 | B32: Husain | C32: JCP/26/283681 | D32: Shooq Muneer Maaroof | E32: 950401706 | F32: 46057 | G32: Yes | H32: Yes | I32: Female | J32: Bachelors + | K32: 550 | L32: Secertary | M32: ALMOAYYED CONTRACTING GROUP W.L.L. | N32: 43090-1 | O32: Full time Direct Employment
A33: =ROW() - ROW(Table1[[#Headers],[SL No.]]) -> 32 | B33: Husain | C33: JCP/25/170060 | D33: SALMAN ADEL OUN JASIM | E33: 050201182 | F33: 45697 | G33: Yes | I33: Male | J33: High School | K33: 350 | L33: Driver | M33: DRAGON BEACH HOTEL W.L.L | N33: 170835-2 | O33: Full time Direct Employment | P33: Payment without VAT
A34: =ROW() - ROW(Table1[[#Headers],[SL No.]]) -> 33 | B34: Khalifa | C34: JCP/26/271188 | D34: AMINA AYMAN S. NAJEM | E34: 010206191 | F34: 46041 | G34: Yes | I34: Female | J34: Bachelors + | K34: 600 | L34: Marketing Specialist | M34: Serious Duck | N34: 160782-1 | O34: Full time Direct Employment
A35: =ROW() - ROW(Table1[[#Headers],[SL No.]]) -> 34 | B35: Zainab Almaroom | C35: JCP/25/229821 | D35: BAYAN ADEL J. ALARAYEDH | E35: 010500308 | F35: 46041 | G35: Yes | I35: Female | J35: Bachelors + | K35: 600 | L35: Marketing Specialist | M35: Serious Duck | N35: 160782-1 | O35: Full time Direct Employment
A36: =ROW() - ROW(Table1[[#Headers],[SL No.]]) -> 35 | B36: Husain | C36: JCP/25/208891 | D36: SAYED JAAFAR EBRAHIM JAAFAR NEMAA | E36: 000804800 | F36: 46061 | I36: Male | J36: Bachelors + | K36: 530 | L36: Junior Electrical engineer | M36: ALMOAYYED CONTRACTING GROUP W.L.L. | N36: 76980-1 | O36: Full time Direct Employment
A37: =ROW() - ROW(Table1[[#Headers],[SL No.]]) -> 36 | B37: Husain | C37: JCP/25/169005 | D37: YASER SALMAN EBRAHIM MAHDI | E37: 910401390 | F37: 46070 | G37: Yes | I37: Male | J37: High School | K37: 370 | L37: Forklift driver | M37: Bahrain pack | N37: 29242-01 | O37: Full time Direct Employment | P37: Payment without VAT
A38: =ROW() - ROW(Table1[[#Headers],[SL No.]]) -> 37 | B38: Meaad | C38: JCP/26/284939 | D38: Mariam Samir Ali | E38: 931200571 | F38: 46062 | K38: 670 | L38: Business Development Manager | N38: 160782-1 | O38: Full time Direct Employment
A39: =ROW() - ROW(Table1[[#Headers],[SL No.]]) -> 38 | B39: Zainab Mattar | C39: JCP/26/269393 | D39: FATEMA HASAN JASIM HASAN AHMED | E39: 990509540 | F39: 46075 | G39: Yes | I39: Female | J39: Bachelors + | K39: 500 | L39: Coordinator | M39: ALMOAYYED CONTRACTING GROUP W.L.L. | N39: 43090-1 | O39: Full time Direct Employment
A40: =ROW() - ROW(Table1[[#Headers],[SL No.]]) -> 39 | B40: Mahdi | C40: JCP/25/181038 | D40: Hessa al doserri | E40: 001004310 | F40: 46071 | G40: Yes | I40: Female | J40: Bachelors + | K40: 600 | L40: HR officer | M40: Braxtone insurance | N40: 169147-1 | O40: Full time Direct Employment
A41: =ROW() - ROW(Table1[[#Headers],[SL No.]]) -> 40 | B41: Meaad | C41: JCP/26/284947 | D41: MARYAM MOHAMED A. ALMUQAHWI | E41: 031110681 | F41: 46061 | K41: 500 | L41: Computer Systems Analyst | M41: BLOX COMPUTER CONSULTENCIES W.L.L | N41: 37278-3 | O41: Full time Direct Employment
A42: =ROW() - ROW(Table1[[#Headers],[SL No.]]) -> 41 | B42: Meaad | C42: JCP/26/286460 | D42: Sharifa Abdulrazzaq Hasan | E42: 971000689 | F42: 46071 | G42: Yes | I42: Female | J42: Bachelors + | K42: 800 | L42: veterinarian | M42: Animalia by Yara | N42: 166663-1 | O42: Full time Direct Employment
A43: =ROW() - ROW(Table1[[#Headers],[SL No.]]) -> 42 | B43: Husain | C43: JCP/25/213261 | D43: AMMAR SALEH HASAN AHMED ALI | E43: 000305910 | F43: 45893 | G43: Yes | I43: Male | J43: Diploma | K43: 450 | L43: Machine operator | M43: ARLA FOODS W.L.L | N43: 127867-1 | O43: Full time Direct Employment | P43: Payment without VAT
A44: =ROW() - ROW(Table1[[#Headers],[SL No.]]) -> 43 | B44: Husain | C44: JCP/25/217089 | D44: ALI HUSAIN ABDULLA KAD FARDAN | E44: 030400686 | F44: 45886 | G44: Yes | I44: Male | J44: High School | K44: 350 | L44: Security Cum Bell Boy | M44: Almanzil hotel | N44: 186174-1 | O44: Full time Direct Employment | P44: Payment without VAT
A45: =ROW() - ROW(Table1[[#Headers],[SL No.]]) -> 44 | B45: Meaad | C45: JCP/26/286051 | D45: Fatima Mukhtar | E45: 981206620 | F45: 46068 | I45: Female | J45: Bachelors + | K45: 500 | L45: Teacher | M45: New Vision School, | N45: 710474-1 | O45: Full time Direct Employment
A46: =ROW() - ROW(Table1[[#Headers],[SL No.]]) -> 45 | B46: Meaad | C46: JCP/26/286053 | D46: MARYAM A.JALIL ABDULLA HASAN ABDULLA SARHAN | E46: 20203896 | F46: 46068 | I46: Female | J46: Bachelors + | K46: 500 | L46: Teacher | M46: New Vision School, | N46: 710474-1 | O46: Full time Direct Employment
A47: =ROW() - ROW(Table1[[#Headers],[SL No.]]) -> 46 | B47: Meaad | C47: JCP/26/286885 | D47: Naba Zuhair AlElaiwat | E47: 981003133 | F47: 46076 | K47: 500 | L47: Receptionist | M47: YARA MEDICAL HOSPITALIA W.L.L | O47: Full time Direct Employment
A48: =ROW() - ROW(Table1[[#Headers],[SL No.]]) -> 47 | B48: Husain | C48: JCP/25/171258 | D48: Noora Faqir | E48: 930911571 | F48: 45721 | I48: Female | J48: High School | K48: 350 | L48: Cashier/ Sales consultant | M48: BAHRAIN FINANCING COMPANY | N48: 35-10 | O48: Full time Direct Employment | P48: Payment without VAT
A49: =ROW() - ROW(Table1[[#Headers],[SL No.]]) -> 48 | B49: Meaad | C49: JCP/26/286809 | D49: Ameera Husain Hamad | E49: 950704415 | F49: 46082 | I49: Female | J49: Bachelors + | K49: 600 | L49: Recruitment Specialist | M49: Hire Fellows | N49: 189727-1 | O49: Full time Direct Employment
A50: =ROW() - ROW(Table1[[#Headers],[SL No.]]) -> 49 | B50: Husain | C50: JCP/25/153757 | D50: Sayed Moosa Mahdi Alawi Mohsen Ahmed | E50: 020100868 | F50: 45725 | I50: Male | J50: High School | K50: 350 | L50: Electrical technician | M50: IOT BAHRAIN TRADING | N50: 148642-1 | O50: Full time Direct Employment | P50: Payment without VAT
A51: =ROW() - ROW(Table1[[#Headers],[SL No.]]) -> 50 | B51: Husain | C51: JCP/24/096845 | D51: KARAR HUSAM ALI YATEEM | E51: 980405866 | F51: 45911 | G51: Yes | H51: Yes | I51: Male | J51: High School | K51: 500 | L51: Partner Care agent | M51: NINJA SUPPORT W.L.L | N51: 184823-1 | O51: Full time Direct Employment | P51: Payment without VAT
A52: =ROW() - ROW(Table1[[#Headers],[SL No.]]) -> 51 | B52: Husain | C52: JCP/25/225850 | D52: HASAN FADHEL HASAN ISMAEEL ALI | E52: 970102917 | F52: 45914 | I52: Male | J52: Bachelors + | K52: 500 | L52: Electronic engineer | M52: IOT BAHRAIN TRADING | N52: 148642-1 | O52: Full time Direct Employment | P52: Payment without VAT
A53: =ROW() - ROW(Table1[[#Headers],[SL No.]]) -> 52 | B53: Husain | C53: JCP/25/173504 | D53: Shuaib hasan Rustam | E53: 940205432 | F53: 45739 | G53: Yes | H53: Yes | I53: Male | J53: High School | K53: 400 | L53: Coordinator | M53: RAFFA INDUSTRIAL SERVICES W.L.L | N53: 1856-2 | O53: Full time Direct Employment | P53: Payment without VAT
A54: =ROW() - ROW(Table1[[#Headers],[SL No.]]) -> 53 | B54: Husain | C54: JCP/25/217425 | D54: ALI SALMAN HASAN ALI | E54: 960800360 | F54: 45922 | G54: Yes | H54: Yes | I54: Male | J54: High School | K54: 400 | L54: Forklift operator | M54: KONEXUS ALUMINIUM INTERNATIONAL CO. W.L.L | N54: 116589-1 | O54: Full time Direct Employment | P54: Payment without VAT
A55: =ROW() - ROW(Table1[[#Headers],[SL No.]]) -> 54 | B55: Husain | C55: JCP/24/047875 | D55: AMMAR SAYED YASER SAEED MOHAMED | E55: 960507680 | F55: 45922 | G55: Yes | H55: Yes | I55: Male | J55: Bachelors + | K55: 600 | L55: Partnership Specialist | M55: STUDENT PLATFORM W.L.L. | N55: 127080-1 | O55: Full time Direct Employment | P55: Payment without VAT
A56: =ROW() - ROW(Table1[[#Headers],[SL No.]]) -> 55 | B56: Meaad | C56: JCP/25/229307 | D56: Bader Abdulnabi Ebrahim | E56: 10306587 | F56: 45921 | G56: Yes | H56: Yes | I56: Male | J56: Bachelors + | K56: 378 | L56: Sales Executive | M56: BAHRAIN DUTY FREE CO. WLL | N56: 119146-1 | O56: Full time Direct Employment
A57: =ROW() - ROW(Table1[[#Headers],[SL No.]]) -> 56 | B57: Meaad | C57: JCP/25/174221 | D57: فاطمه حسن الليث | E57: 920300600 | F57: 45921 | I57: Female | J57: Bachelors + | K57: 500 | L57: Consultant | M57: GIG | N57: 75091-1
A58: =ROW() - ROW(Table1[[#Headers],[SL No.]]) -> 57 | B58: Husain | C58: JCP/25/180485 | D58: ساره ساتر | E58: 010306420 | F58: 45740 | G58: Yes | H58: Yes | I58: Female | J58: Bachelors + | K58: 500 | L58: Accountant | M58: KONEXUS ALUMINIUM INTERNATIONAL CO. W.L.L | N58: 116589-1 | O58: Full time Direct Employment | P58: Payment without VAT
A59: =ROW() - ROW(Table1[[#Headers],[SL No.]]) -> 58 | B59: Meaad | C59: JCP/25/194119 | D59: MAHDI MOHAMED MAHDI ALI | E59: 891103503 | F59: 45792 | I59: Male | M59: DRAGON BEACH HOTEL W.L.L | N59: 170835-2 | O59: Full time Direct Employment
A60: =ROW() - ROW(Table1[[#Headers],[SL No.]]) -> 59 | B60: Malak | C60: JCP/25/178761 | D60: MAJED MOHAMED ALI MOHSEN ZABAR | E60: 840201451 | F60: 45922 | G60: Yes | I60: Male | J60: Diploma | K60: 1200 | L60: Business Development Manager | M60: HAAND SOLUTIONS LTDA W.L.L | N60: 167652-01 | O60: Full time Direct Employment | P60: 6 Months Payment
A61: =ROW() - ROW(Table1[[#Headers],[SL No.]]) -> 60 | B61: Zainab Mattar | C61: JCP/25/231016 | D61: No Placement Recorded | F61: 45668
A62: =ROW() - ROW(Table1[[#Headers],[SL No.]]) -> 61 | B62: Meaad | C62: JCP/25/190585 | D62: ZAINAB MOHAMED GHULOOM ALI | E62: 1203282 | F62: 45811 | G62: Yes | I62: Female | J62: Bachelors + | K62: 500 | L62: sales designer | M62: ALMA KITCHENS FACTORY W.L.L | N62: 11017-10 | O62: Full time Direct Employment
A63: =ROW() - ROW(Table1[[#Headers],[SL No.]]) -> 62 | B63: Husain | C63: JCP/26/288742 | D63: SAKINA ALI | E63: 041002652 | F63: 46095 | I63: Female | J63: High School | K63: 350 | L63: Sales | M63: M F ABAYAT | N63: 187913-1 | O63: Full time Direct Employment
A64: =ROW() - ROW(Table1[[#Headers],[SL No.]]) -> 63 | B64: Husain | C64: JCP/26/288724 | D64: السيد جعفر ناصر | E64: 920401333 | F64: 46095 | I64: Male | J64: High School | K64: 400 | L64: Sales | M64: BINT AL-SARRAJ JEWELRY | N64: 142007-1 | O64: Full time Direct Employment
A65: =ROW() - ROW(Table1[[#Headers],[SL No.]]) -> 64 | B65: Meaad | C65: JCP/25/195286 | D65: HASAN AQEEL ALI HASAN ALJESHI | E65: 950405051 | F65: 45819 | G65: Yes | I65: Male | J65: High School | M65: AHMED MANSOOR ALAALI | N65: 571-2 | O65: Full time Direct Employment
A66: =ROW() - ROW(Table1[[#Headers],[SL No.]]) -> 65 | B66: Dina | C66: JCP/24/094062 | D66: sayed ali noordeen ali | E66: 970303335 | F66: 46012 | G66: Yes | H66: Yes | I66: Male | J66: Diploma | K66: 700 | L66: Safety officer | M66: GULF TOBACCO COMPANY. W.L.L | N66: 145777-1 | O66: Full time Direct Employment
A67: =ROW() - ROW(Table1[[#Headers],[SL No.]]) -> 66 | B67: Dina | C67: JCP/26/283470 | D67: ALI HUSAIN SAEED ABDULWAHAB ALRADHI | E67: 871001594 | F67: 46047 | G67: Yes | H67: Yes | I67: Male | J67: Bachelors + | K67: 600 | L67: Equipment Operator | M67: GULF TOBACCO COMPANY. W.L.L | N67: 145777-1 | O67: Full time Direct Employment
A68: =ROW() - ROW(Table1[[#Headers],[SL No.]]) -> 67 | B68: Zainab Mattar | C68: JCP/26/283404 | D68: Kadhem Ahmed Kadhem | E68: 030610478 | F68: 46047 | G68: Yes | H68: Yes | I68: Male | J68: High School | K68: 700 | L68: Safety officer | M68: GULF TOBACCO COMPANY. W.L.L | N68: 145777-1 | O68: Full time Direct Employment
A69: =ROW() - ROW(Table1[[#Headers],[SL No.]]) -> 68 | B69: Malak | C69: JCP/26/283447 | D69: ALI ABDULREDHA AHMED KHORRAMI | E69: 960304584 | F69: 46047 | G69: Yes | H69: Yes | I69: Male | J69: Bachelors + | K69: 700 | L69: Shift Lead | M69: GULF TOBACCO COMPANY. W.L.L | N69: 145777-1 | O69: Full time Direct Employment
A70: =ROW() - ROW(Table1[[#Headers],[SL No.]]) -> 69 | B70: Dina | C70: JCP/26/283488 | D70: Ali maki Abbas | E70: 880403390 | F70: 46047 | G70: Yes | I70: Male | J70: Diploma | K70: 600 | L70: Equipment Operator | M70: GULF TOBACCO COMPANY. W.L.L | N70: 145777-1 | O70: Full time Direct Employment
A71: =ROW() - ROW(Table1[[#Headers],[SL No.]]) -> 70 | B71: Zainab Mattar | C71: 26/288849 | D71: FATEMA JASIM AHMED SALEH | E71: 930500199 | F71: 46113 | I71: Female | J71: Bachelors + | K71: 550 | L71: Design Sales Executive | M71: FATIMA ALANSARI DESIGN AND EXECUTION WLL | N71: 101037-1 | O71: Full time Direct Employment
A72: =ROW() - ROW(Table1[[#Headers],[SL No.]]) -> 71 | B72: Meaad | C72: 26/289712 | D72: Maryam Abbas Ahmed Ebrahim Abdulla Almeftah | E72: 011010339 | F72: 46111 | I72: Female | J72: Bachelors + | K72: 500 | L72: Marketing Executive | M72: TOTAL RELIANCE FOR CONSTRUCTION, TRADE AND CONSULTANCY | N72: 170032-1 | O72: Full time Direct Employment
A73: =ROW() - ROW(Table1[[#Headers],[SL No.]]) -> 72 | B73: Husain | C73: JCP/24/145750 | D73: MOHAMED AHMED ALI AHMED HUSAIN | E73: 850201527 | F73: 46106 | G73: Yes | I73: Male | J73: Diploma | K73: 430 | L73: Machine Operator | M73: ARLA FOODS W.L.L | N73: 127867-1 | O73: Full time Direct Employment | P73: Payment without VAT
A74: =ROW() - ROW(Table1[[#Headers],[SL No.]]) -> 73 | B74: Zainab Mattar | C74: JCP/25/217083 | D74: REEMA ARSALAN JASIM ARAYEDH | E74: 030903726 | F74: 46117 | I74: Female | J74: Bachelors + | K74: 550 | L74: HR Adminstrator | M74: ARLA FOODS W.L.L | N74: 127867-1 | O74: Full time Direct Employment
A75: =ROW() - ROW(Table1[[#Headers],[SL No.]]) -> 74 | B75: Husain | C75: 24/049470 | D75: HASAN MAHDI NASER ALKHABBAZ | E75: 960907459 | F75: 46099 | G75: Yes | I75: Male | J75: High School | K75: 350 | L75: Heavy Driver | M75: Almoayyed Transport | N75: 79844-1 | O75: Full time Direct Employment
A76: =ROW() - ROW(Table1[[#Headers],[SL No.]]) -> 75 | B76: Meaad | C76: 26/289720 | D76: ALI MAHROOS | E76: 981100880 | F76: 46113 | I76: Male | J76: High School | K76: 350 | L76: Heavy Driver | M76: Almoayyed Transport | N76: 79844-1 | O76: Full time Direct Employment
A77: =ROW() - ROW(Table1[[#Headers],[SL No.]]) -> 76 | B77: Meaad | C77: 26/288557 | D77: KAWTHAR HUSAIN MAKI A DEKHEEL | E77: 020600844 | F77: 46113 | I77: Female | J77: Bachelors + | K77: 500 | L77: Training Cordenator | M77: PULSE HEALTH TRAINING CENTER W.L.L | N77: 98693-1 | O77: Full time Direct Employment
A78: =ROW() - ROW(Table1[[#Headers],[SL No.]]) -> 77 | B78: Zainab Almaroom | C78: JCP/25/264921 | D78: Maryam Akbar Murad | E78: 000700010 | F78: 46104 | I78: Female | J78: Bachelors + | K78: 700 | L78: Sales Development Representative | M78: AMAN COMPLIANCE SOLUTIONS W.L.L | N78: 172967-1 | O78: Full time Direct Employment
A79: =ROW() - ROW(Table1[[#Headers],[SL No.]]) -> 78 | B79: Dina | C79: JCP/25/180026 | D79: Yusuf Ebrahim Yusuf Ahmed Fulad | E79: 900710381 | F79: 46061 | I79: Male | K79: 400 | L79: Equipment Operator | M79: GULF TOBACCO COMPANY. W.L.L | N79: 145777-1 | O79: Full time Direct Employment
A80: =ROW() - ROW(Table1[[#Headers],[SL No.]]) -> 79 | B80: Dina | C80: JCP/26/285439 | D80: Sayed Mohammed ALI Albahraini | E80: 921205929 | F80: 46061 | G80: Yes | I80: Male | J80: High School | K80: 400 | L80: Equipment Operator | M80: GULF TOBACCO COMPANY. W.L.L | N80: 145777-1 | O80: Full time Direct Employment
A81: =ROW() - ROW(Table1[[#Headers],[SL No.]]) -> 80 | B81: Dina | C81: JCP/24/145581 | D81: JASIM MOHAMED SALEH SALEH | E81: 991106903 | F81: 46054 | I81: Male | K81: 400 | L81: StoreKeeper | M81: GULF TOBACCO COMPANY. W.L.L | N81: 145777-1 | O81: Full time Direct Employment
A82: =ROW() - ROW(Table1[[#Headers],[SL No.]]) -> 81 | B82: Dina | C82: JCP/25/223037 | D82: JAAFAR KADHEM HUSAIN HABIB KADHEM ALJABOORI | E82: 021107238 | F82: 46061 | G82: Yes | I82: Male | J82: High School | K82: 400 | L82: Equipment Operator | M82: GULF TOBACCO COMPANY. W.L.L | N82: 145777-1 | O82: Full time Direct Employment
A83: =ROW() - ROW(Table1[[#Headers],[SL No.]]) -> 82 | B83: Malak | C83: JCP/26/286008 | D83: Husain Hasan Ali | E83: 001209477 | F83: 46068 | I83: Male | K83: 500 | L83: Equipment Operator | M83: GULF TOBACCO COMPANY. W.L.L | N83: 145777-1 | O83: Full time Direct Employment
A84: =ROW() - ROW(Table1[[#Headers],[SL No.]]) -> 83 | B84: Dina | C84: JCP/26/283442 | D84: HUSAIN EBRAHIM JASIM EBRAHIM | E84: 951204181 | F84: 46068 | I84: Male | K84: 450 | L84: Forrklift Operator | M84: GULF TOBACCO COMPANY. W.L.L | N84: 145777-1 | O84: Full time Direct Employment
A85: =ROW() - ROW(Table1[[#Headers],[SL No.]]) -> 84 | B85: Dina | C85: JCP/25/263373 | D85: hasan husain ebrahim | E85: 000303356 | F85: 46075 | I85: Male | K85: 400 | L85: Pallet Truck Operator | M85: GULF TOBACCO COMPANY. W.L.L | N85: 145777-1 | O85: Full time Direct Employment
A86: =ROW() - ROW(Table1[[#Headers],[SL No.]]) -> 85 | B86: Dina | C86: JCP/26/285998 | D86: HASAN ABDULZAHRA ASHO DHABAAN | E86: 010601260 | F86: 46068 | I86: Male | K86: 450 | L86: Equipment Operator | M86: GULF TOBACCO COMPANY. W.L.L | N86: 145777-1 | O86: Full time Direct Employment
A87: =ROW() - ROW(Table1[[#Headers],[SL No.]]) -> 86 | B87: Dina | C87: JCP/25/264214 | D87: FOZAN KHAN MANZOOR Ali MUZAFFAR | E87: 000206326 | F87: 46068 | I87: Male | K87: 750 | L87: Quality Auditor | M87: GULF TOBACCO COMPANY. W.L.L | N87: 145777-1 | O87: Full time Direct Employment
A88: =ROW() - ROW(Table1[[#Headers],[SL No.]]) -> 87 | B88: Zainab Mattar | C88: JCP/25/190581 | D88: faisal ahmed ahmed shah gul salam hashmi | E88: 981011098 | F88: 46054 | G88: Yes | H88: Yes | I88: Male | J88: Bachelors + | K88: 550 | L88: StoreKeeper | M88: GULF TOBACCO COMPANY. W.L.L | N88: 145777-1 | O88: Full time Direct Employment
A89: =ROW() - ROW(Table1[[#Headers],[SL No.]]) -> 88 | B89: Dina | C89: JCP/25/198356 | D89: Faisal Ghulam Mohd | E89: 880911212 | F89: 46098 | I89: Male | K89: 550 | L89: Camera & CCTV Supervisor | M89: GULF TOBACCO COMPANY. W.L.L | N89: 145777-1 | O89: Full time Direct Employment
A90: =ROW() - ROW(Table1[[#Headers],[SL No.]]) -> 89 | B90: Malak | C90: JCP/25/167732 | D90: BASEL SHAKER ALI MANSOOR ALI | E90: 061002798 | F90: 46061 | I90: Male | K90: 400 | L90: Equipment Operator | M90: GULF TOBACCO COMPANY. W.L.L | N90: 145777-1 | O90: Full time Direct Employment
A91: =ROW() - ROW(Table1[[#Headers],[SL No.]]) -> 90 | B91: Meaad | C91: 26/270825 | D91: Ali Mohsin Abdali | E91: 040706842 | F91: 46061 | I91: Male | K91: 400 | L91: Equipment Operator | M91: GULF TOBACCO COMPANY. W.L.L | N91: 145777-1 | O91: Full time Direct Employment
A92: =ROW() - ROW(Table1[[#Headers],[SL No.]]) -> 91 | B92: Dina | C92: JCP/26/285421 | D92: ali abbas abdali | E92: 981003028 | F92: 46061 | I92: Male | J92: High School | K92: 550 | L92: Equipment Operator | M92: GULF TOBACCO COMPANY. W.L.L | N92: 145777-1 | O92: Full time Direct Employment
A93: =ROW() - ROW(Table1[[#Headers],[SL No.]]) -> 92 | B93: Malak | C93: JCP/25/261707 | D93: Abdulla Hussain Abdulla | E93: 030905818 | F93: 46061 | I93: Male | K93: 400 | L93: Equipment Operator | M93: GULF TOBACCO COMPANY. W.L.L | N93: 145777-1 | O93: Full time Direct Employment
A94: =ROW() - ROW(Table1[[#Headers],[SL No.]]) -> 93 | B94: Dina | C94: 26/283501 | D94: AAMER ALI HASAN ALMUTAWA | E94: 871003260 | F94: 46078 | I94: Male | K94: 1000 | L94: IT Specialist | M94: GULF TOBACCO COMPANY. W.L.L | N94: 145777-1 | O94: Full time Direct Employment
A95: =ROW() - ROW(Table1[[#Headers],[SL No.]]) -> 94 | B95: Malak | C95: JCP/26/283428 | D95: mohammed ashoor hasan | E95: 981202241 | F95: 46068 | G95: Yes | H95: Yes | I95: Male | J95: High School | K95: 400 | L95: Pallet Truck Operator | M95: GULF TOBACCO COMPANY. W.L.L | N95: 145777-1 | O95: Full time Direct Employment
A96: =ROW() - ROW(Table1[[#Headers],[SL No.]]) -> 95 | B96: Dina | C96: JCP/26/286399 | D96: HASAN JAAFAR MOHAMED ALAALI | E96: 890304890 | F96: 46070 | G96: Yes | H96: Yes | I96: Male | J96: High School | K96: 450 | L96: Forrklift Operator | M96: GULF TOBACCO COMPANY. W.L.L | N96: 145777-1 | O96: Full time Direct Employment
A97: =ROW() - ROW(Table1[[#Headers],[SL No.]]) -> 96 | B97: Meaad | C97: JCP/26/285972 | D97: ali hassan abdulla | E97: 970604041 | F97: 46124 | I97: Male | K97: 350 | L97: Cashier | M97: BUSAITEEN LAND RESTAURANT W.L.L | N97: 137782-1 | O97: Full time Direct Employment
A98: =ROW() - ROW(Table1[[#Headers],[SL No.]]) -> 97 | B98: Husain | C98: JCP/24/142442 | D98: SAYED ALAA MOOSA MOHAMED FADHEL | E98: 890704791 | F98: 45931 | I98: Male | J98: Bachelors + | K98: 500 | L98: Sales officer | M98: MENWIN BUSINESS CONSULTANTS W.L.L | N98: 163331-1 | O98: Full time Direct Employment | P98: Payment without VAT, payment done for 6 months
A99: =ROW() - ROW(Table1[[#Headers],[SL No.]]) -> 98 | B99: Husain | C99: JCP/25/233173 | D99: KHALIFA EBRAHIM K. SAAD | E99: 890201641 | F99: 45935 | G99: Yes | I99: Male | J99: High School | K99: 350 | L99: Security officer | M99: THE K - HOTEL W.L.L | N99: 74418-1 | O99: Full time Direct Employment | P99: Payment without VAT, payment done for 6 months
A100: =ROW() - ROW(Table1[[#Headers],[SL No.]]) -> 99 | B100: Husain | C100: JCP/25/244587 | D100: EBRAHIM NAEEM A. MARHOON | E100: 920801471 | F100: 45939 | G100: Yes | I100: Male | J100: High School | K100: 420 | L100: Trainee- HSE officer | M100: ALMOAYYED CONTRACTING GROUP W.L.L. | N100: 43090-1 | O100: Full time Direct Employment | P100: payment done for 6 months
...

Sheet Claims 26
A1: SL No. | B1: Case manager | C1: Ref No | D1: Name | E1: Joining Date | F1: Claims Status | G1: Dispute | H1: Disupute Comment | I1: Placement Fee & Variables | J1: Placement claim Highlight | K1: 6 Months | L1: 6M Stat | M1: 6 Months Claim | N1: Highlight rule 6M | O1: 12 Months | P1: 12 Months Claim | Q1: 12 M Stat | R1: Highlight rule 12 M | S1: Total Stat | T1: Total first claim | U1: Placement Fee | V1: MoL | W1: Long MoL | X1: Gender | Y1: Education | Z1: Salary
A2: =Table1[[#This Row],[SL No.]] -> 1 | B2: =Table1[[#This Row],[Case manager]] -> Husain | C2: =Table1[[#This Row],[Ref No]] -> JCP/25/172042 | D2: =Table1[[#This Row],[Name]] -> WALEED ABDULWAHID J ABDULAZIZ | E2: ='Placements 26'!F2 -> 46028 | F2: =IF(S2>=1,"Claimable","Claimed") -> Claimable | G2: No | I2: 46042 | J2: =IF(Table3[[#This Row],[Placement Fee & Variables]]>0,0,1) -> 0 | K2: =Table3[[#This Row],[Joining Date]]+180 -> 46208 | L2: =IF(AND(M2="", K2<=TODAY()), "Claimable", "") -> Claimable | N2: =IF(Table3[[#This Row],[6M Stat]]="Claimable",1,0) -> 1 | O2: =Table3[[#This Row],[Joining Date]]+365 -> 46393 | Q2: =IF(AND(P2="", O2<=TODAY()), "Claimable", "") | R2: =IF(Table3[[#This Row],[12 M Stat]]="Claimable",1,0) -> 0 | S2: =Table3[[#This Row],[Placement claim Highlight]]+Table3[[#This Row],[Highlight rule 6M]]+Table3[[#This Row],[Highlight rule 12 M]] -> 1 | T2: =SUM(Table3[[#This Row],[Placement Fee]:[Salary]]) -> 605 | U2: 550 | V2: =IF(Table1[[#This Row],[MoL]]="Yes",55,0) -> 55 | W2: =IF(Table1[[#This Row],[Long MoL +3 Years]]="Yes",137.5,0) -> 0 | X2: =IF(Table1[[#This Row],[Gender]]="Female",137.5,0) -> 0 | Y2: =IF(Table1[[#This Row],[Education]]="Bachelors +",55,0) -> 0 | Z2: =IF(Table1[[#This Row],[Salary]]>=600,82.5,0) -> 0
A3: =Table1[[#This Row],[SL No.]] -> 2 | B3: =Table1[[#This Row],[Case manager]] -> Meaad | C3: =Table1[[#This Row],[Ref No]] -> JCP/24/057296 | D3: =Table1[[#This Row],[Name]] -> ASMA MOHAMMAD ASHFAQMO DIN | E3: ='Placements 26'!F3 -> 46035 | F3: =IF(S3>=1,"Claimable","Claimed") -> Claimable | G3: No | I3: 46042 | J3: =IF(Table3[[#This Row],[Placement Fee & Variables]]>0,0,1) -> 0 | K3: =Table3[[#This Row],[Joining Date]]+180 -> 46215 | L3: =IF(AND(M3="", K3<=TODAY()), "Claimable", "") -> Claimable | N3: =IF(Table3[[#This Row],[6M Stat]]="Claimable",1,0) -> 1 | O3: =Table3[[#This Row],[Joining Date]]+365 -> 46400 | Q3: =IF(AND(P3="", O3<=TODAY()), "Claimable", "") | R3: =IF(Table3[[#This Row],[12 M Stat]]="Claimable",1,0) -> 0 | S3: =Table3[[#This Row],[Placement claim Highlight]]+Table3[[#This Row],[Highlight rule 6M]]+Table3[[#This Row],[Highlight rule 12 M]] -> 1 | T3: =SUM(Table3[[#This Row],[Placement Fee]:[Salary]]) -> 797.5 | U3: 550 | V3: =IF(Table1[[#This Row],[MoL]]="Yes",55,0) -> 55 | W3: =IF(Table1[[#This Row],[Long MoL +3 Years]]="Yes",137.5,0) -> 0 | X3: =IF(Table1[[#This Row],[Gender]]="Female",137.5,0) -> 137.5 | Y3: =IF(Table1[[#This Row],[Education]]="Bachelors +",55,0) -> 55 | Z3: =IF(Table1[[#This Row],[Salary]]>=600,82.5,0) -> 0
A4: =Table1[[#This Row],[SL No.]] -> 3 | B4: =Table1[[#This Row],[Case manager]] -> Malak | C4: =Table1[[#This Row],[Ref No]] -> JCP/25/218398 | D4: =Table1[[#This Row],[Name]] -> ZIYAD TAREQ MAJEDA ALTHAWADI | E4: ='Placements 26'!F4 -> 46033 | F4: =IF(S4>=1,"Claimable","Claimed") -> Claimed | G4: No | I4: 46042 | J4: =IF(Table3[[#This Row],[Placement Fee & Variables]]>0,0,1) -> 0 | K4: =Table3[[#This Row],[Joining Date]]+180 -> 46213 | L4: =IF(AND(M4="", K4<=TODAY()), "Claimable", "") | M4: 46245 | N4: =IF(Table3[[#This Row],[6M Stat]]="Claimable",1,0) -> 0 | O4: =Table3[[#This Row],[Joining Date]]+365 -> 46398 | Q4: =IF(AND(P4="", O4<=TODAY()), "Claimable", "") | R4: =IF(Table3[[#This Row],[12 M Stat]]="Claimable",1,0) -> 0 | S4: =Table3[[#This Row],[Placement claim Highlight]]+Table3[[#This Row],[Highlight rule 6M]]+Table3[[#This Row],[Highlight rule 12 M]] -> 0 | T4: =SUM(Table3[[#This Row],[Placement Fee]:[Salary]]) -> 110 | V4: =IF(Table1[[#This Row],[MoL]]="Yes",55,0) -> 55 | W4: =IF(Table1[[#This Row],[Long MoL +3 Years]]="Yes",137.5,0) -> 0 | X4: =IF(Table1[[#This Row],[Gender]]="Female",137.5,0) -> 0 | Y4: =IF(Table1[[#This Row],[Education]]="Bachelors +",55,0) -> 55 | Z4: =IF(Table1[[#This Row],[Salary]]>=600,82.5,0) -> 0
A5: =Table1[[#This Row],[SL No.]] -> 4 | B5: =Table1[[#This Row],[Case manager]] -> Zainab Mattar | C5: =Table1[[#This Row],[Ref No]] -> JCP/25/183340 | D5: =Table1[[#This Row],[Name]] -> AYSHA OMAR SALEH AL ALYAZEEDI | E5: 46033 | F5: =IF(S5>=1,"Claimable","Claimed") -> Claimable | G5: No | I5: 46042 | J5: =IF(Table3[[#This Row],[Placement Fee & Variables]]>0,0,1) -> 0 | K5: =Table3[[#This Row],[Joining Date]]+180 -> 46213 | L5: =IF(AND(M5="", K5<=TODAY()), "Claimable", "") -> Claimable | N5: =IF(Table3[[#This Row],[6M Stat]]="Claimable",1,0) -> 1 | O5: =Table3[[#This Row],[Joining Date]]+365 -> 46398 | Q5: =IF(AND(P5="", O5<=TODAY()), "Claimable", "") | R5: =IF(Table3[[#This Row],[12 M Stat]]="Claimable",1,0) -> 0 | S5: =Table3[[#This Row],[Placement claim Highlight]]+Table3[[#This Row],[Highlight rule 6M]]+Table3[[#This Row],[Highlight rule 12 M]] -> 1 | T5: =SUM(Table3[[#This Row],[Placement Fee]:[Salary]]) -> 192.5 | V5: =IF(Table1[[#This Row],[MoL]]="Yes",55,0) -> 55 | W5: =IF(Table1[[#This Row],[Long MoL +3 Years]]="Yes",137.5,0) -> 0 | X5: =IF(Table1[[#This Row],[Gender]]="Female",137.5,0) -> 137.5 | Y5: =IF(Table1[[#This Row],[Education]]="Bachelors +",55,0) -> 0 | Z5: =IF(Table1[[#This Row],[Salary]]>=600,82.5,0) -> 0
A6: =Table1[[#This Row],[SL No.]] -> 5 | B6: =Table1[[#This Row],[Case manager]] -> Meaad | C6: =Table1[[#This Row],[Ref No]] -> JCP/25/210558 | D6: =Table1[[#This Row],[Name]] -> ali abdulameer ali ali mohamed | E6: 46033 | F6: =IF(S6>=1,"Claimable","Claimed") -> Claimable | G6: No | I6: 46043 | J6: =IF(Table3[[#This Row],[Placement Fee & Variables]]>0,0,1) -> 0 | K6: =Table3[[#This Row],[Joining Date]]+180 -> 46213 | L6: =IF(AND(M6="", K6<=TODAY()), "Claimable", "") -> Claimable | N6: =IF(Table3[[#This Row],[6M Stat]]="Claimable",1,0) -> 1 | O6: =Table3[[#This Row],[Joining Date]]+365 -> 46398 | Q6: =IF(AND(P6="", O6<=TODAY()), "Claimable", "") | R6: =IF(Table3[[#This Row],[12 M Stat]]="Claimable",1,0) -> 0 | S6: =Table3[[#This Row],[Placement claim Highlight]]+Table3[[#This Row],[Highlight rule 6M]]+Table3[[#This Row],[Highlight rule 12 M]] -> 1 | T6: =SUM(Table3[[#This Row],[Placement Fee]:[Salary]]) -> 192.5 | V6: =IF(Table1[[#This Row],[MoL]]="Yes",55,0) -> 55 | W6: =IF(Table1[[#This Row],[Long MoL +3 Years]]="Yes",137.5,0) -> 137.5 | X6: =IF(Table1[[#This Row],[Gender]]="Female",137.5,0) -> 0 | Y6: =IF(Table1[[#This Row],[Education]]="Bachelors +",55,0) -> 0 | Z6: =IF(Table1[[#This Row],[Salary]]>=600,82.5,0) -> 0
A7: =Table1[[#This Row],[SL No.]] -> 6 | B7: =Table1[[#This Row],[Case manager]] -> Meaad | C7: =Table1[[#This Row],[Ref No]] -> JCP/25/267702 | D7: =Table1[[#This Row],[Name]] -> ABBAS AHMED A ALHANNAN | E7: ='Placements 26'!F7 -> 46033 | F7: =IF(S7>=1,"Claimable","Claimed") -> Claimed | G7: No | I7: 46044 | J7: =IF(Table3[[#This Row],[Placement Fee & Variables]]>0,0,1) -> 0 | K7: =Table3[[#This Row],[Joining Date]]+180 -> 46213 | L7: =IF(AND(M7="", K7<=TODAY()), "Claimable", "") | M7: 46216 | N7: =IF(Table3[[#This Row],[6M Stat]]="Claimable",1,0) -> 0 | O7: =Table3[[#This Row],[Joining Date]]+365 -> 46398 | Q7: =IF(AND(P7="", O7<=TODAY()), "Claimable", "") | R7: =IF(Table3[[#This Row],[12 M Stat]]="Claimable",1,0) -> 0 | S7: =Table3[[#This Row],[Placement claim Highlight]]+Table3[[#This Row],[Highlight rule 6M]]+Table3[[#This Row],[Highlight rule 12 M]] -> 0 | T7: =SUM(Table3[[#This Row],[Placement Fee]:[Salary]]) -> 55 | V7: =IF(Table1[[#This Row],[MoL]]="Yes",55,0) -> 55 | W7: =IF(Table1[[#This Row],[Long MoL +3 Years]]="Yes",137.5,0) -> 0 | X7: =IF(Table1[[#This Row],[Gender]]="Female",137.5,0) -> 0 | Y7: =IF(Table1[[#This Row],[Education]]="Bachelors +",55,0) -> 0 | Z7: =IF(Table1[[#This Row],[Salary]]>=600,82.5,0) -> 0
A8: =Table1[[#This Row],[SL No.]] -> 7 | B8: =Table1[[#This Row],[Case manager]] -> Meaad | C8: =Table1[[#This Row],[Ref No]] -> JCP/25/267727 | D8: =Table1[[#This Row],[Name]] -> MAYTHAM MOHAMED JAAFAR A. MOHAMED ALI | E8: ='Placements 26'!F8 -> 46033 | F8: =IF(S8>=1,"Claimable","Claimed") -> Claimed | G8: No | I8: 46044 | J8: =IF(Table3[[#This Row],[Placement Fee & Variables]]>0,0,1) -> 0 | K8: =Table3[[#This Row],[Joining Date]]+180 -> 46213 | L8: =IF(AND(M8="", K8<=TODAY()), "Claimable", "") | M8: 46216 | N8: =IF(Table3[[#This Row],[6M Stat]]="Claimable",1,0) -> 0 | O8: =Table3[[#This Row],[Joining Date]]+365 -> 46398 | Q8: =IF(AND(P8="", O8<=TODAY()), "Claimable", "") | R8: =IF(Table3[[#This Row],[12 M Stat]]="Claimable",1,0) -> 0 | S8: =Table3[[#This Row],[Placement claim Highlight]]+Table3[[#This Row],[Highlight rule 6M]]+Table3[[#This Row],[Highlight rule 12 M]] -> 0 | T8: =SUM(Table3[[#This Row],[Placement Fee]:[Salary]]) -> 0 | V8: =IF(Table1[[#This Row],[MoL]]="Yes",55,0) -> 0 | W8: =IF(Table1[[#This Row],[Long MoL +3 Years]]="Yes",137.5,0) -> 0 | X8: =IF(Table1[[#This Row],[Gender]]="Female",137.5,0) -> 0 | Y8: =IF(Table1[[#This Row],[Education]]="Bachelors +",55,0) -> 0 | Z8: =IF(Table1[[#This Row],[Salary]]>=600,82.5,0) -> 0
A9: =Table1[[#This Row],[SL No.]] -> 8 | B9: =Table1[[#This Row],[Case manager]] -> Zainab Mattar | C9: =Table1[[#This Row],[Ref No]] -> JCP/25/204298 | D9: =Table1[[#This Row],[Name]] -> ABDULLA MOHAMED HOORAN MOHAMED AWAD ALENEZI | E9: ='Placements 26'!F9 -> 46033 | F9: =IF(S9>=1,"Claimable","Claimed") -> Claimable | G9: No | I9: 46044 | J9: =IF(Table3[[#This Row],[Placement Fee & Variables]]>0,0,1) -> 0 | K9: =Table3[[#This Row],[Joining Date]]+180 -> 46213 | L9: =IF(AND(M9="", K9<=TODAY()), "Claimable", "") -> Claimable | N9: =IF(Table3[[#This Row],[6M Stat]]="Claimable",1,0) -> 1 | O9: =Table3[[#This Row],[Joining Date]]+365 -> 46398 | Q9: =IF(AND(P9="", O9<=TODAY()), "Claimable", "") | R9: =IF(Table3[[#This Row],[12 M Stat]]="Claimable",1,0) -> 0 | S9: =Table3[[#This Row],[Placement claim Highlight]]+Table3[[#This Row],[Highlight rule 6M]]+Table3[[#This Row],[Highlight rule 12 M]] -> 1 | T9: =SUM(Table3[[#This Row],[Placement Fee]:[Salary]]) -> 110 | V9: =IF(Table1[[#This Row],[MoL]]="Yes",55,0) -> 55 | W9: =IF(Table1[[#This Row],[Long MoL +3 Years]]="Yes",137.5,0) -> 0 | X9: =IF(Table1[[#This Row],[Gender]]="Female",137.5,0) -> 0 | Y9: =IF(Table1[[#This Row],[Education]]="Bachelors +",55,0) -> 55 | Z9: =IF(Table1[[#This Row],[Salary]]>=600,82.5,0) -> 0
A10: =Table1[[#This Row],[SL No.]] -> 9 | B10: =Table1[[#This Row],[Case manager]] -> Meaad | C10: =Table1[[#This Row],[Ref No]] -> JCP/26/268524 | D10: =Table1[[#This Row],[Name]] -> LULWA EZZ EBRAHIM ABDULAZIZ RASHED ALBANKI | E10: ='Placements 26'!F10 -> 46033 | F10: =IF(S10>=1,"Claimable","Claimed") -> Claimed | G10: No | I10: 46131 | J10: =IF(Table3[[#This Row],[Placement Fee & Variables]]>0,0,1) -> 0 | K10: =Table3[[#This Row],[Joining Date]]+180 -> 46213 | L10: =IF(AND(M10="", K10<=TODAY()), "Claimable", "") | M10: 46188 | N10: =IF(Table3[[#This Row],[6M Stat]]="Claimable",1,0) -> 0 | O10: =Table3[[#This Row],[Joining Date]]+365 -> 46398 | Q10: =IF(AND(P10="", O10<=TODAY()), "Claimable", "") | R10: =IF(Table3[[#This Row],[12 M Stat]]="Claimable",1,0) -> 0 | S10: =Table3[[#This Row],[Placement claim Highlight]]+Table3[[#This Row],[Highlight rule 6M]]+Table3[[#This Row],[Highlight rule 12 M]] -> 0 | T10: =SUM(Table3[[#This Row],[Placement Fee]:[Salary]]) -> 247.5 | V10: =IF(Table1[[#This Row],[MoL]]="Yes",55,0) -> 55 | W10: =IF(Table1[[#This Row],[Long MoL +3 Years]]="Yes",137.5,0) -> 0 | X10: =IF(Table1[[#This Row],[Gender]]="Female",137.5,0) -> 137.5 | Y10: =IF(Table1[[#This Row],[Education]]="Bachelors +",55,0) -> 55 | Z10: =IF(Table1[[#This Row],[Salary]]>=600,82.5,0) -> 0
A11: =Table1[[#This Row],[SL No.]] -> 10 | B11: =Table1[[#This Row],[Case manager]] -> Mahdi | C11: =Table1[[#This Row],[Ref No]] -> JCP/26/268505 | D11: =Table1[[#This Row],[Name]] -> YUSUF ALI YUSUF HABIB DAGHER | E11: ='Placements 26'!F11 -> 46033 | F11: =IF(S11>=1,"Claimable","Claimed") -> Claimable | G11: No | I11: 46131 | J11: =IF(Table3[[#This Row],[Placement Fee & Variables]]>0,0,1) -> 0 | K11: =Table3[[#This Row],[Joining Date]]+180 -> 46213 | L11: =IF(AND(M11="", K11<=TODAY()), "Claimable", "") -> Claimable | N11: =IF(Table3[[#This Row],[6M Stat]]="Claimable",1,0) -> 1 | O11: =Table3[[#This Row],[Joining Date]]+365 -> 46398 | Q11: =IF(AND(P11="", O11<=TODAY()), "Claimable", "") | R11: =IF(Table3[[#This Row],[12 M Stat]]="Claimable",1,0) -> 0 | S11: =Table3[[#This Row],[Placement claim Highlight]]+Table3[[#This Row],[Highlight rule 6M]]+Table3[[#This Row],[Highlight rule 12 M]] -> 1 | T11: =SUM(Table3[[#This Row],[Placement Fee]:[Salary]]) -> 0 | V11: =IF(Table1[[#This Row],[MoL]]="Yes",55,0) -> 0 | W11: =IF(Table1[[#This Row],[Long MoL +3 Years]]="Yes",137.5,0) -> 0 | X11: =IF(Table1[[#This Row],[Gender]]="Female",137.5,0) -> 0 | Y11: =IF(Table1[[#This Row],[Education]]="Bachelors +",55,0) -> 0 | Z11: =IF(Table1[[#This Row],[Salary]]>=600,82.5,0) -> 0
A12: =Table1[[#This Row],[SL No.]] -> 11 | B12: =Table1[[#This Row],[Case manager]] -> Meaad | C12: =Table1[[#This Row],[Ref No]] -> JCP/26/268879 | D12: =Table1[[#This Row],[Name]] -> MERZA JAMEEL MIRZA ALARADI | E12: ='Placements 26'!F12 -> 46033 | F12: =IF(S12>=1,"Claimable","Claimed") -> Claimed | G12: No | I12: 46044 | J12: =IF(Table3[[#This Row],[Placement Fee & Variables]]>0,0,1) -> 0 | K12: =Table3[[#This Row],[Joining Date]]+180 -> 46213 | L12: =IF(AND(M12="", K12<=TODAY()), "Claimable", "") | M12: 46208 | N12: =IF(Table3[[#This Row],[6M Stat]]="Claimable",1,0) -> 0 | O12: =Table3[[#This Row],[Joining Date]]+365 -> 46398 | Q12: =IF(AND(P12="", O12<=TODAY()), "Claimable", "") | R12: =IF(Table3[[#This Row],[12 M Stat]]="Claimable",1,0) -> 0 | S12: =Table3[[#This Row],[Placement claim Highlight]]+Table3[[#This Row],[Highlight rule 6M]]+Table3[[#This Row],[Highlight rule 12 M]] -> 0 | T12: =SUM(Table3[[#This Row],[Placement Fee]:[Salary]]) -> 247.5 | V12: =IF(Table1[[#This Row],[MoL]]="Yes",55,0) -> 55 | W12: =IF(Table1[[#This Row],[Long MoL +3 Years]]="Yes",137.5,0) -> 137.5 | X12: =IF(Table1[[#This Row],[Gender]]="Female",137.5,0) -> 0 | Y12: =IF(Table1[[#This Row],[Education]]="Bachelors +",55,0) -> 55 | Z12: =IF(Table1[[#This Row],[Salary]]>=600,82.5,0) -> 0
A13: =Table1[[#This Row],[SL No.]] -> 12 | B13: =Table1[[#This Row],[Case manager]] -> Mahdi | C13: =Table1[[#This Row],[Ref No]] -> JCP/26/268526 | D13: =Table1[[#This Row],[Name]] -> AHMED WAHEED AKHTAR M. ALI | E13: ='Placements 26'!F13 -> 46033 | F13: =IF(S13>=1,"Claimable","Claimed") -> Claimable | G13: No | I13: 46043 | J13: =IF(Table3[[#This Row],[Placement Fee & Variables]]>0,0,1) -> 0 | K13: =Table3[[#This Row],[Joining Date]]+180 -> 46213 | L13: =IF(AND(M13="", K13<=TODAY()), "Claimable", "") -> Claimable | N13: =IF(Table3[[#This Row],[6M Stat]]="Claimable",1,0) -> 1 | O13: =Table3[[#This Row],[Joining Date]]+365 -> 46398 | Q13: =IF(AND(P13="", O13<=TODAY()), "Claimable", "") | R13: =IF(Table3[[#This Row],[12 M Stat]]="Claimable",1,0) -> 0 | S13: =Table3[[#This Row],[Placement claim Highlight]]+Table3[[#This Row],[Highlight rule 6M]]+Table3[[#This Row],[Highlight rule 12 M]] -> 1 | T13: =SUM(Table3[[#This Row],[Placement Fee]:[Salary]]) -> 192.5 | V13: =IF(Table1[[#This Row],[MoL]]="Yes",55,0) -> 55 | W13: =IF(Table1[[#This Row],[Long MoL +3 Years]]="Yes",137.5,0) -> 137.5 | X13: =IF(Table1[[#This Row],[Gender]]="Female",137.5,0) -> 0 | Y13: =IF(Table1[[#This Row],[Education]]="Bachelors +",55,0) -> 0 | Z13: =IF(Table1[[#This Row],[Salary]]>=600,82.5,0) -> 0
A14: =Table1[[#This Row],[SL No.]] -> 13 | B14: =Table1[[#This Row],[Case manager]] -> Malak | C14: =Table1[[#This Row],[Ref No]] -> JCP/25/219711 | D14: =Table1[[#This Row],[Name]] -> FATIMA HASAN ABDULLA BUHMAID | E14: ='Placements 26'!F14 -> 46033 | F14: =IF(S14>=1,"Claimable","Claimed") -> Claimed | G14: No | I14: 46044 | J14: =IF(Table3[[#This Row],[Placement Fee & Variables]]>0,0,1) -> 0 | K14: =Table3[[#This Row],[Joining Date]]+180 -> 46213 | L14: =IF(AND(M14="", K14<=TODAY()), "Claimable", "") | M14: 46245 | N14: =IF(Table3[[#This Row],[6M Stat]]="Claimable",1,0) -> 0 | O14: =Table3[[#This Row],[Joining Date]]+365 -> 46398 | Q14: =IF(AND(P14="", O14<=TODAY()), "Claimable", "") | R14: =IF(Table3[[#This Row],[12 M Stat]]="Claimable",1,0) -> 0 | S14: =Table3[[#This Row],[Placement claim Highlight]]+Table3[[#This Row],[Highlight rule 6M]]+Table3[[#This Row],[Highlight rule 12 M]] -> 0 | T14: =SUM(Table3[[#This Row],[Placement Fee]:[Salary]]) -> 330 | V14: =IF(Table1[[#This Row],[MoL]]="Yes",55,0) -> 55 | W14: =IF(Table1[[#This Row],[Long MoL +3 Years]]="Yes",137.5,0) -> 137.5 | X14: =IF(Table1[[#This Row],[Gender]]="Female",137.5,0) -> 137.5 | Y14: =IF(Table1[[#This Row],[Education]]="Bachelors +",55,0) -> 0 | Z14: =IF(Table1[[#This Row],[Salary]]>=600,82.5,0) -> 0
A15: =Table1[[#This Row],[SL No.]] -> 14 | B15: =Table1[[#This Row],[Case manager]] -> Husain | C15: =Table1[[#This Row],[Ref No]] -> JCP/25/219615 | D15: =Table1[[#This Row],[Name]] -> HUSAIN ABDULMONEM HU MOTHANNA | E15: ='Placements 26'!F15 -> 46005 | F15: =IF(S15>=1,"Claimable","Claimed") -> Claimable | G15: No | I15: 46040 | J15: =IF(Table3[[#This Row],[Placement Fee & Variables]]>0,0,1) -> 0 | K15: =Table3[[#This Row],[Joining Date]]+180 -> 46185 | L15: =IF(AND(M15="", K15<=TODAY()), "Claimable", "") -> Claimable | N15: =IF(Table3[[#This Row],[6M Stat]]="Claimable",1,0) -> 1 | O15: =Table3[[#This Row],[Joining Date]]+365 -> 46370 | Q15: =IF(AND(P15="", O15<=TODAY()), "Claimable", "") | R15: =IF(Table3[[#This Row],[12 M Stat]]="Claimable",1,0) -> 0 | S15: =Table3[[#This Row],[Placement claim Highlight]]+Table3[[#This Row],[Highlight rule 6M]]+Table3[[#This Row],[Highlight rule 12 M]] -> 1 | T15: =SUM(Table3[[#This Row],[Placement Fee]:[Salary]]) -> 55 | V15: =IF(Table1[[#This Row],[MoL]]="Yes",55,0) -> 55 | W15: =IF(Table1[[#This Row],[Long MoL +3 Years]]="Yes",137.5,0) -> 0 | X15: =IF(Table1[[#This Row],[Gender]]="Female",137.5,0) -> 0 | Y15: =IF(Table1[[#This Row],[Education]]="Bachelors +",55,0) -> 0 | Z15: =IF(Table1[[#This Row],[Salary]]>=600,82.5,0) -> 0
A16: =Table1[[#This Row],[SL No.]] -> 15 | B16: =Table1[[#This Row],[Case manager]] -> Husain | C16: =Table1[[#This Row],[Ref No]] -> JCP/25/232927 | D16: =Table1[[#This Row],[Name]] -> SAYED MOHAMED SAEED HASAN ALAWI | E16: ='Placements 26'!F16 -> 46005 | F16: =IF(S16>=1,"Claimable","Claimed") -> Claimable | G16: No | I16: 46041 | J16: =IF(Table3[[#This Row],[Placement Fee & Variables]]>0,0,1) -> 0 | K16: =Table3[[#This Row],[Joining Date]]+180 -> 46185 | L16: =IF(AND(M16="", K16<=TODAY()), "Claimable", "") -> Claimable | N16: =IF(Table3[[#This Row],[6M Stat]]="Claimable",1,0) -> 1 | O16: =Table3[[#This Row],[Joining Date]]+365 -> 46370 | Q16: =IF(AND(P16="", O16<=TODAY()), "Claimable", "") | R16: =IF(Table3[[#This Row],[12 M Stat]]="Claimable",1,0) -> 0 | S16: =Table3[[#This Row],[Placement claim Highlight]]+Table3[[#This Row],[Highlight rule 6M]]+Table3[[#This Row],[Highlight rule 12 M]] -> 1 | T16: =SUM(Table3[[#This Row],[Placement Fee]:[Salary]]) -> 110 | V16: =IF(Table1[[#This Row],[MoL]]="Yes",55,0) -> 55 | W16: =IF(Table1[[#This Row],[Long MoL +3 Years]]="Yes",137.5,0) -> 0 | X16: =IF(Table1[[#This Row],[Gender]]="Female",137.5,0) -> 0 | Y16: =IF(Table1[[#This Row],[Education]]="Bachelors +",55,0) -> 55 | Z16: =IF(Table1[[#This Row],[Salary]]>=600,82.5,0) -> 0
A17: =Table1[[#This Row],[SL No.]] -> 16 | B17: =Table1[[#This Row],[Case manager]] -> Husain | C17: =Table1[[#This Row],[Ref No]] -> JCP/25/214227 | D17: =Table1[[#This Row],[Name]] -> FATEMA WALEED HASAN SHOWIATER | E17: ='Placements 26'!F17 -> 46006 | F17: =IF(S17>=1,"Claimable","Claimed") -> Claimable | G17: No | I17: 46042 | J17: 46042 | K17: 46043 | L17: 46044 | N17: =IF(Table3[[#This Row],[6M Stat]]="Claimable",1,0) -> 0 | O17: =Table3[[#This Row],[Joining Date]]+365 -> 46371 | Q17: =IF(AND(P17="", O17<=TODAY()), "Claimable", "") | R17: =IF(Table3[[#This Row],[12 M Stat]]="Claimable",1,0) -> 0 | S17: =Table3[[#This Row],[Placement claim Highlight]]+Table3[[#This Row],[Highlight rule 6M]]+Table3[[#This Row],[Highlight rule 12 M]] -> 46042 | T17: =SUM(Table3[[#This Row],[Placement Fee]:[Salary]]) -> 247.5 | V17: =IF(Table1[[#This Row],[MoL]]="Yes",55,0) -> 55 | W17: =IF(Table1[[#This Row],[Long MoL +3 Years]]="Yes",137.5,0) -> 0 | X17: =IF(Table1[[#This Row],[Gender]]="Female",137.5,0) -> 137.5 | Y17: =IF(Table1[[#This Row],[Education]]="Bachelors +",55,0) -> 55 | Z17: =IF(Table1[[#This Row],[Salary]]>=600,82.5,0) -> 0
A18: =Table1[[#This Row],[SL No.]] -> 17 | B18: =Table1[[#This Row],[Case manager]] -> Husain | C18: =Table1[[#This Row],[Ref No]] -> JCP/25/212208 | D18: =Table1[[#This Row],[Name]] -> WALAA ISA A. HASAN | E18: ='Placements 26'!F18 -> 45865 | F18: =IF(S18>=1,"Claimable","Claimed") -> Claimable | G18: No | H18: this payment is done for 6 months | I18: 45865 | J18: =IF(Table3[[#This Row],[Placement Fee & Variables]]>0,0,1) -> 0 | K18: =Table3[[#This Row],[Joining Date]]+180 -> 46045 | L18: =IF(AND(M18="", K18<=TODAY()), "Claimable", "") | M18: 46042 | N18: =IF(Table3[[#This Row],[6M Stat]]="Claimable",1,0) -> 0 | O18: =Table3[[#This Row],[Joining Date]]+365 -> 46230 | Q18: =IF(AND(P18="", O18<=TODAY()), "Claimable", "") -> Claimable | R18: =IF(Table3[[#This Row],[12 M Stat]]="Claimable",1,0) -> 1 | S18: =Table3[[#This Row],[Placement claim Highlight]]+Table3[[#This Row],[Highlight rule 6M]]+Table3[[#This Row],[Highlight rule 12 M]] -> 1 | T18: =SUM(Table3[[#This Row],[Placement Fee]:[Salary]]) -> 330 | V18: =IF(Table1[[#This Row],[MoL]]="Yes",55,0) -> 55 | W18: =IF(Table1[[#This Row],[Long MoL +3 Years]]="Yes",137.5,0) -> 0 | X18: =IF(Table1[[#This Row],[Gender]]="Female",137.5,0) -> 137.5 | Y18: =IF(Table1[[#This Row],[Education]]="Bachelors +",55,0) -> 55 | Z18: =IF(Table1[[#This Row],[Salary]]>=600,82.5,0) -> 82.5
A19: =Table1[[#This Row],[SL No.]] -> 18 | B19: =Table1[[#This Row],[Case manager]] -> Meaad | C19: =Table1[[#This Row],[Ref No]] -> JCP/25/223039 | D19: =Table1[[#This Row],[Name]] -> SAYED ALI HASHEM E. ALQASSAB | E19: 45956 | F19: =IF(S19>=1,"Claimable","Claimed") -> Claimed | G19: No | I19: 46049 | J19: =IF(Table3[[#This Row],[Placement Fee & Variables]]>0,0,1) -> 0 | K19: =Table3[[#This Row],[Joining Date]]+180 -> 46136 | L19: =IF(AND(M19="", K19<=TODAY()), "Claimable", "") | M19: 46216 | N19: =IF(Table3[[#This Row],[6M Stat]]="Claimable",1,0) -> 0 | O19: =Table3[[#This Row],[Joining Date]]+365 -> 46321 | Q19: =IF(AND(P19="", O19<=TODAY()), "Claimable", "") | R19: =IF(Table3[[#This Row],[12 M Stat]]="Claimable",1,0) -> 0 | S19: =Table3[[#This Row],[Placement claim Highlight]]+Table3[[#This Row],[Highlight rule 6M]]+Table3[[#This Row],[Highlight rule 12 M]] -> 0 | T19: =SUM(Table3[[#This Row],[Placement Fee]:[Salary]]) -> 55 | V19: =IF(Table1[[#This Row],[MoL]]="Yes",55,0) -> 55 | W19: =IF(Table1[[#This Row],[Long MoL +3 Years]]="Yes",137.5,0) -> 0 | X19: =IF(Table1[[#This Row],[Gender]]="Female",137.5,0) -> 0 | Y19: =IF(Table1[[#This Row],[Education]]="Bachelors +",55,0) -> 0 | Z19: =IF(Table1[[#This Row],[Salary]]>=600,82.5,0) -> 0
A20: =Table1[[#This Row],[SL No.]] -> 19 | B20: =Table1[[#This Row],[Case manager]] -> Malak | C20: =Table1[[#This Row],[Ref No]] -> JCP/25/233228 | D20: =Table1[[#This Row],[Name]] -> SYED HAMID NAZIR HUSSAIN SHAH PIRZAMAN SHAH | E20: ='Placements 26'!F20 -> 46054 | F20: Claimed | G20: No | I20: 46054 | J20: =IF(Table3[[#This Row],[Placement Fee & Variables]]>0,0,1) -> 0 | K20: =Table3[[#This Row],[Joining Date]]+180 -> 46234 | L20: =IF(AND(M20="", K20<=TODAY()), "Claimable", "") -> Claimable | N20: =IF(Table3[[#This Row],[6M Stat]]="Claimable",1,0) -> 1 | O20: =Table3[[#This Row],[Joining Date]]+365 -> 46419 | Q20: =IF(AND(P20="", O20<=TODAY()), "Claimable", "") | R20: =IF(Table3[[#This Row],[12 M Stat]]="Claimable",1,0) -> 0 | S20: =Table3[[#This Row],[Placement claim Highlight]]+Table3[[#This Row],[Highlight rule 6M]]+Table3[[#This Row],[Highlight rule 12 M]] -> 1 | T20: =SUM(Table3[[#This Row],[Placement Fee]:[Salary]]) -> 55 | V20: =IF(Table1[[#This Row],[MoL]]="Yes",55,0) -> 55 | W20: =IF(Table1[[#This Row],[Long MoL +3 Years]]="Yes",137.5,0) -> 0 | X20: =IF(Table1[[#This Row],[Gender]]="Female",137.5,0) -> 0 | Y20: =IF(Table1[[#This Row],[Education]]="Bachelors +",55,0) -> 0 | Z20: =IF(Table1[[#This Row],[Salary]]>=600,82.5,0) -> 0
A21: =Table1[[#This Row],[SL No.]] -> 20 | B21: =Table1[[#This Row],[Case manager]] -> Dina | C21: =Table1[[#This Row],[Ref No]] -> JCP/25/233782 | D21: =Table1[[#This Row],[Name]] -> FATEMA JAAFAR MOHAMED FARHAN | E21: ='Placements 26'!F21 -> 45939 | F21: =IF(S21>=1,"Claimable","Claimed") -> Claimable | G21: No | I21: 46051 | J21: =IF(Table3[[#This Row],[Placement Fee & Variables]]>0,0,1) -> 0 | K21: =Table3[[#This Row],[Joining Date]]+180 -> 46119 | L21: =IF(AND(M21="", K21<=TODAY()), "Claimable", "") | M21: 46202 | N21: =IF(Table3[[#This Row],[6M Stat]]="Claimable",1,0) -> 0 | O21: =Table3[[#This Row],[Joining Date]]+365 -> 46304 | Q21: =IF(AND(P21="", O21<=TODAY()), "Claimable", "") -> Claimable | R21: =IF(Table3[[#This Row],[12 M Stat]]="Claimable",1,0) -> 1 | S21: =Table3[[#This Row],[Placement claim Highlight]]+Table3[[#This Row],[Highlight rule 6M]]+Table3[[#This Row],[Highlight rule 12 M]] -> 1 | T21: =SUM(Table3[[#This Row],[Placement Fee]:[Salary]]) -> 192.5 | V21: =IF(Table1[[#This Row],[MoL]]="Yes",55,0) -> 55 | W21: =IF(Table1[[#This Row],[Long MoL +3 Years]]="Yes",137.5,0) -> 0 | X21: =IF(Table1[[#This Row],[Gender]]="Female",137.5,0) -> 137.5 | Y21: =IF(Table1[[#This Row],[Education]]="Bachelors +",55,0) -> 0 | Z21: =IF(Table1[[#This Row],[Salary]]>=600,82.5,0) -> 0
A22: =Table1[[#This Row],[SL No.]] -> 21 | B22: =Table1[[#This Row],[Case manager]] -> Zainab Mattar | C22: =Table1[[#This Row],[Ref No]] -> JCP/25/262810 | D22: =Table1[[#This Row],[Name]] -> GHASSAN ABDULLA MAHDI MAHDI | E22: ='Placements 26'!F22 -> 46040 | F22: =IF(S22>=1,"Claimable","Claimed") -> Claimable | G22: No | J22: =IF(Table3[[#This Row],[Placement Fee & Variables]]>0,0,1) -> 1 | K22: =Table3[[#This Row],[Joining Date]]+180 -> 46220 | L22: =IF(AND(M22="", K22<=TODAY()), "Claimable", "") -> Claimable | N22: =IF(Table3[[#This Row],[6M Stat]]="Claimable",1,0) -> 1 | O22: =Table3[[#This Row],[Joining Date]]+365 -> 46405 | Q22: =IF(AND(P22="", O22<=TODAY()), "Claimable", "") | R22: =IF(Table3[[#This Row],[12 M Stat]]="Claimable",1,0) -> 0 | S22: =Table3[[#This Row],[Placement claim Highlight]]+Table3[[#This Row],[Highlight rule 6M]]+Table3[[#This Row],[Highlight rule 12 M]] -> 2 | T22: =SUM(Table3[[#This Row],[Placement Fee]:[Salary]]) -> 330 | V22: =IF(Table1[[#This Row],[MoL]]="Yes",55,0) -> 55 | W22: =IF(Table1[[#This Row],[Long MoL +3 Years]]="Yes",137.5,0) -> 137.5 | X22: =IF(Table1[[#This Row],[Gender]]="Female",137.5,0) -> 0 | Y22: =IF(Table1[[#This Row],[Education]]="Bachelors +",55,0) -> 55 | Z22: =IF(Table1[[#This Row],[Salary]]>=600,82.5,0) -> 82.5
A23: =Table1[[#This Row],[SL No.]] -> 22 | B23: =Table1[[#This Row],[Case manager]] -> Husain | C23: =Table1[[#This Row],[Ref No]] -> JCP/26/283826 | D23: =Table1[[#This Row],[Name]] -> Ali Husain Seroor | E23: ='Placements 26'!F23 -> 46050 | F23: =IF(S23>=1,"Claimable","Claimed") -> Claimable | G23: No | I23: 46055 | J23: =IF(Table3[[#This Row],[Placement Fee & Variables]]>0,0,1) -> 0 | K23: =Table3[[#This Row],[Joining Date]]+180 -> 46230 | L23: =IF(AND(M23="", K23<=TODAY()), "Claimable", "") -> Claimable | N23: =IF(Table3[[#This Row],[6M Stat]]="Claimable",1,0) -> 1 | O23: =Table3[[#This Row],[Joining Date]]+365 -> 46415 | Q23: =IF(AND(P23="", O23<=TODAY()), "Claimable", "") | R23: =IF(Table3[[#This Row],[12 M Stat]]="Claimable",1,0) -> 0 | S23: =Table3[[#This Row],[Placement claim Highlight]]+Table3[[#This Row],[Highlight rule 6M]]+Table3[[#This Row],[Highlight rule 12 M]] -> 1 | T23: =SUM(Table3[[#This Row],[Placement Fee]:[Salary]]) -> 192.5 | V23: =IF(Table1[[#This Row],[MoL]]="Yes",55,0) -> 55 | W23: =IF(Table1[[#This Row],[Long MoL +3 Years]]="Yes",137.5,0) -> 137.5 | X23: =IF(Table1[[#This Row],[Gender]]="Female",137.5,0) -> 0 | Y23: =IF(Table1[[#This Row],[Education]]="Bachelors +",55,0) -> 0 | Z23: =IF(Table1[[#This Row],[Salary]]>=600,82.5,0) -> 0
A24: =Table1[[#This Row],[SL No.]] -> 23 | B24: =Table1[[#This Row],[Case manager]] -> Husain | C24: =Table1[[#This Row],[Ref No]] -> JCP/25/171059 | D24: =Table1[[#This Row],[Name]] -> ZAINAB NASER MOHAMED MAHMOOD ALALWAANI | E24: ='Placements 26'!F24 -> 46055 | F24: =IF(S24>=1,"Claimable","Claimed") -> Claimed | G24: No | H24: this payment is done for 12 months | I24: 45700 | J24: =IF(Table3[[#This Row],[Placement Fee & Variables]]>0,0,1) -> 0 | K24: =Table3[[#This Row],[Joining Date]]+180 -> 46235 | L24: =IF(AND(M24="", K24<=TODAY()), "Claimable", "") | M24: 45873 | N24: =IF(Table3[[#This Row],[6M Stat]]="Claimable",1,0) -> 0 | O24: =Table3[[#This Row],[Joining Date]]+365 -> 46420 | P24: 46055 | Q24: =IF(AND(P24="", O24<=TODAY()), "Claimable", "") | R24: =IF(Table3[[#This Row],[12 M Stat]]="Claimable",1,0) -> 0 | S24: =Table3[[#This Row],[Placement claim Highlight]]+Table3[[#This Row],[Highlight rule 6M]]+Table3[[#This Row],[Highlight rule 12 M]] -> 0 | T24: =SUM(Table3[[#This Row],[Placement Fee]:[Salary]]) -> 137.5 | V24: =IF(Table1[[#This Row],[MoL]]="Yes",55,0) -> 0 | W24: =IF(Table1[[#This Row],[Long MoL +3 Years]]="Yes",137.5,0) -> 0 | X24: =IF(Table1[[#This Row],[Gender]]="Female",137.5,0) -> 137.5 | Y24: =IF(Table1[[#This Row],[Education]]="Bachelors +",55,0) -> 0 | Z24: =IF(Table1[[#This Row],[Salary]]>=600,82.5,0) -> 0
A25: =Table1[[#This Row],[SL No.]] -> 24 | B25: =Table1[[#This Row],[Case manager]] -> Husain | C25: =Table1[[#This Row],[Ref No]] -> JCP/25/171458 | D25: =Table1[[#This Row],[Name]] -> HUSAIN MUSTAFA ALI ALMAJED | E25: ='Placements 26'!F25 -> 46055 | F25: =IF(S25>=1,"Claimable","Claimed") -> Claimed | G25: No | H25: this payment is done for 12 months | I25: 45700 | J25: =IF(Table3[[#This Row],[Placement Fee & Variables]]>0,0,1) -> 0 | K25: =Table3[[#This Row],[Joining Date]]+180 -> 46235 | L25: =IF(AND(M25="", K25<=TODAY()), "Claimable", "") | M25: 45873 | N25: =IF(Table3[[#This Row],[6M Stat]]="Claimable",1,0) -> 0 | O25: =Table3[[#This Row],[Joining Date]]+365 -> 46420 | P25: 46055 | Q25: =IF(AND(P25="", O25<=TODAY()), "Claimable", "") | R25: =IF(Table3[[#This Row],[12 M Stat]]="Claimable",1,0) -> 0 | S25: =Table3[[#This Row],[Placement claim Highlight]]+Table3[[#This Row],[Highlight rule 6M]]+Table3[[#This Row],[Highlight rule 12 M]] -> 0 | T25: =SUM(Table3[[#This Row],[Placement Fee]:[Salary]]) -> 55 | V25: =IF(Table1[[#This Row],[MoL]]="Yes",55,0) -> 55 | W25: =IF(Table1[[#This Row],[Long MoL +3 Years]]="Yes",137.5,0) -> 0 | X25: =IF(Table1[[#This Row],[Gender]]="Female",137.5,0) -> 0 | Y25: =IF(Table1[[#This Row],[Education]]="Bachelors +",55,0) -> 0 | Z25: =IF(Table1[[#This Row],[Salary]]>=600,82.5,0) -> 0
A26: =Table1[[#This Row],[SL No.]] -> 25 | B26: =Table1[[#This Row],[Case manager]] -> Meaad | C26: =Table1[[#This Row],[Ref No]] -> JCP/25/223860 | D26: =Table1[[#This Row],[Name]] -> duaa ahmedhisham t bintin | E26: ='Placements 26'!F26 -> 46050 | F26: =IF(S26>=1,"Claimable","Claimed") -> Claimable | G26: Yes | H26: She resigned before registering her | J26: =IF(Table3[[#This Row],[Placement Fee & Variables]]>0,0,1) -> 1 | K26: =Table3[[#This Row],[Joining Date]]+180 -> 46230 | L26: =IF(AND(M26="", K26<=TODAY()), "Claimable", "") -> Claimable | N26: =IF(Table3[[#This Row],[6M Stat]]="Claimable",1,0) -> 1 | O26: =Table3[[#This Row],[Joining Date]]+365 -> 46415 | Q26: =IF(AND(P26="", O26<=TODAY()), "Claimable", "") | R26: =IF(Table3[[#This Row],[12 M Stat]]="Claimable",1,0) -> 0 | S26: =Table3[[#This Row],[Placement claim Highlight]]+Table3[[#This Row],[Highlight rule 6M]]+Table3[[#This Row],[Highlight rule 12 M]] -> 2 | T26: =SUM(Table3[[#This Row],[Placement Fee]:[Salary]]) -> 192.5 | V26: =IF(Table1[[#This Row],[MoL]]="Yes",55,0) -> 0 | W26: =IF(Table1[[#This Row],[Long MoL +3 Years]]="Yes",137.5,0) -> 0 | X26: =IF(Table1[[#This Row],[Gender]]="Female",137.5,0) -> 137.5 | Y26: =IF(Table1[[#This Row],[Education]]="Bachelors +",55,0) -> 55 | Z26: =IF(Table1[[#This Row],[Salary]]>=600,82.5,0) -> 0
A27: =Table1[[#This Row],[SL No.]] -> 26 | B27: =Table1[[#This Row],[Case manager]] -> Meaad | C27: =Table1[[#This Row],[Ref No]] -> JCP/25/258736 | D27: =Table1[[#This Row],[Name]] -> Hasan Abdulnabi Tarada | E27: ='Placements 26'!F27 -> 46047 | F27: =IF(S27>=1,"Claimable","Claimed") -> Claimable | G27: Yes | H27: Candidate resigned before being registerein SIO | I27: Candidate resigned before being registerein SIO | J27: =IF(Table3[[#This Row],[Placement Fee & Variables]]>0,0,1) -> 0 | K27: =Table3[[#This Row],[Joining Date]]+180 -> 46227 | L27: =IF(AND(M27="", K27<=TODAY()), "Claimable", "") -> Claimable | N27: =IF(Table3[[#This Row],[6M Stat]]="Claimable",1,0) -> 1 | O27: =Table3[[#This Row],[Joining Date]]+365 -> 46412 | P27: Candidate resigned before being registerein SIO | Q27: =IF(AND(P27="", O27<=TODAY()), "Claimable", "") | R27: =IF(Table3[[#This Row],[12 M Stat]]="Claimable",1,0) -> 0 | S27: =Table3[[#This Row],[Placement claim Highlight]]+Table3[[#This Row],[Highlight rule 6M]]+Table3[[#This Row],[Highlight rule 12 M]] -> 1 | T27: =SUM(Table3[[#This Row],[Placement Fee]:[Salary]]) -> 82.5 | V27: =IF(Table1[[#This Row],[MoL]]="Yes",55,0) -> 0 | W27: =IF(Table1[[#This Row],[Long MoL +3 Years]]="Yes",137.5,0) -> 0 | X27: =IF(Table1[[#This Row],[Gender]]="Female",137.5,0) -> 0 | Y27: =IF(Table1[[#This Row],[Education]]="Bachelors +",55,0) -> 0 | Z27: =IF(Table1[[#This Row],[Salary]]>=600,82.5,0) -> 82.5
A28: =Table1[[#This Row],[SL No.]] -> 27 | B28: =Table1[[#This Row],[Case manager]] -> Zainab Mattar | C28: =Table1[[#This Row],[Ref No]] -> JCP/24/120499 | D28: =Table1[[#This Row],[Name]] -> MUSTAFA ABDULHAMEED QA HUSAIN | E28: ='Placements 26'!F28 -> 46033 | F28: =IF(S28>=1,"Claimable","Claimed") -> Claimable | G28: No | J28: =IF(Table3[[#This Row],[Placement Fee & Variables]]>0,0,1) -> 1 | K28: =Table3[[#This Row],[Joining Date]]+180 -> 46213 | L28: =IF(AND(M28="", K28<=TODAY()), "Claimable", "") -> Claimable | N28: =IF(Table3[[#This Row],[6M Stat]]="Claimable",1,0) -> 1 | O28: =Table3[[#This Row],[Joining Date]]+365 -> 46398 | Q28: =IF(AND(P28="", O28<=TODAY()), "Claimable", "") | R28: =IF(Table3[[#This Row],[12 M Stat]]="Claimable",1,0) -> 0 | S28: =Table3[[#This Row],[Placement claim Highlight]]+Table3[[#This Row],[Highlight rule 6M]]+Table3[[#This Row],[Highlight rule 12 M]] -> 2 | T28: =SUM(Table3[[#This Row],[Placement Fee]:[Salary]]) -> 110 | V28: =IF(Table1[[#This Row],[MoL]]="Yes",55,0) -> 55 | W28: =IF(Table1[[#This Row],[Long MoL +3 Years]]="Yes",137.5,0) -> 0 | X28: =IF(Table1[[#This Row],[Gender]]="Female",137.5,0) -> 0 | Y28: =IF(Table1[[#This Row],[Education]]="Bachelors +",55,0) -> 55 | Z28: =IF(Table1[[#This Row],[Salary]]>=600,82.5,0) -> 0
A29: =Table1[[#This Row],[SL No.]] -> 28 | B29: =Table1[[#This Row],[Case manager]] -> Zainab Almaroom | C29: =Table1[[#This Row],[Ref No]] -> JCP/25/262077 | D29: =Table1[[#This Row],[Name]] -> MAHMOOD JAAFAR ABDULLA JASIM MOHAMED | E29: ='Placements 26'!F29 -> 46028 | F29: =IF(S29>=1,"Claimable","Claimed") -> Claimed | G29: No | I29: 46056 | J29: =IF(Table3[[#This Row],[Placement Fee & Variables]]>0,0,1) -> 0 | K29: =Table3[[#This Row],[Joining Date]]+180 -> 46208 | L29: =IF(AND(M29="", K29<=TODAY()), "Claimable", "") | M29: 46245 | N29: =IF(Table3[[#This Row],[6M Stat]]="Claimable",1,0) -> 0 | O29: =Table3[[#This Row],[Joining Date]]+365 -> 46393 | Q29: =IF(AND(P29="", O29<=TODAY()), "Claimable", "") | R29: =IF(Table3[[#This Row],[12 M Stat]]="Claimable",1,0) -> 0 | S29: =Table3[[#This Row],[Placement claim Highlight]]+Table3[[#This Row],[Highlight rule 6M]]+Table3[[#This Row],[Highlight rule 12 M]] -> 0 | T29: =SUM(Table3[[#This Row],[Placement Fee]:[Salary]]) -> 55 | V29: =IF(Table1[[#This Row],[MoL]]="Yes",55,0) -> 0 | W29: =IF(Table1[[#This Row],[Long MoL +3 Years]]="Yes",137.5,0) -> 0 | X29: =IF(Table1[[#This Row],[Gender]]="Female",137.5,0) -> 0 | Y29: =IF(Table1[[#This Row],[Education]]="Bachelors +",55,0) -> 55 | Z29: =IF(Table1[[#This Row],[Salary]]>=600,82.5,0) -> 0
A30: =Table1[[#This Row],[SL No.]] -> 29 | B30: =Table1[[#This Row],[Case manager]] -> Husain | C30: =Table1[[#This Row],[Ref No]] -> JCP/25/170479 | D30: =Table1[[#This Row],[Name]] -> Ali hasan Alaswami | E30: ='Placements 26'!F30 -> 45692 | F30: =IF(S30>=1,"Claimable","Claimed") -> Claimed | G30: No | H30: this payment is done for 12 months | I30: 45697 | J30: =IF(Table3[[#This Row],[Placement Fee & Variables]]>0,0,1) -> 0 | K30: =Table3[[#This Row],[Joining Date]]+180 -> 45872 | L30: =IF(AND(M30="", K30<=TODAY()), "Claimable", "") | M30: 45873 | N30: =IF(Table3[[#This Row],[6M Stat]]="Claimable",1,0) -> 0 | O30: =Table3[[#This Row],[Joining Date]]+365 -> 46057 | P30: 46057 | Q30: =IF(AND(P30="", O30<=TODAY()), "Claimable", "") | R30: =IF(Table3[[#This Row],[12 M Stat]]="Claimable",1,0) -> 0 | S30: =Table3[[#This Row],[Placement claim Highlight]]+Table3[[#This Row],[Highlight rule 6M]]+Table3[[#This Row],[Highlight rule 12 M]] -> 0 | T30: =SUM(Table3[[#This Row],[Placement Fee]:[Salary]]) -> 192.5 | V30: =IF(Table1[[#This Row],[MoL]]="Yes",55,0) -> 55 | W30: =IF(Table1[[#This Row],[Long MoL +3 Years]]="Yes",137.5,0) -> 137.5 | X30: =IF(Table1[[#This Row],[Gender]]="Female",137.5,0) -> 0 | Y30: =IF(Table1[[#This Row],[Education]]="Bachelors +",55,0) -> 0 | Z30: =IF(Table1[[#This Row],[Salary]]>=600,82.5,0) -> 0
A31: =Table1[[#This Row],[SL No.]] -> 30 | B31: =Table1[[#This Row],[Case manager]] -> Husain | C31: =Table1[[#This Row],[Ref No]] -> JCP/25/213845 | D31: =Table1[[#This Row],[Name]] -> Sara Jamal Ahmed | E31: ='Placements 26'!F31 -> 45874 | F31: =IF(S31>=1,"Claimable","Claimed") -> Claimable | G31: No | H31: this payment is done for 6 months | I31: 45874 | J31: =IF(Table3[[#This Row],[Placement Fee & Variables]]>0,0,1) -> 0 | K31: =Table3[[#This Row],[Joining Date]]+180 -> 46054 | L31: =IF(AND(M31="", K31<=TODAY()), "Claimable", "") | M31: 46058 | N31: =IF(Table3[[#This Row],[6M Stat]]="Claimable",1,0) -> 0 | O31: =Table3[[#This Row],[Joining Date]]+365 -> 46239 | Q31: =IF(AND(P31="", O31<=TODAY()), "Claimable", "") -> Claimable | R31: =IF(Table3[[#This Row],[12 M Stat]]="Claimable",1,0) -> 1 | S31: =Table3[[#This Row],[Placement claim Highlight]]+Table3[[#This Row],[Highlight rule 6M]]+Table3[[#This Row],[Highlight rule 12 M]] -> 1 | T31: =SUM(Table3[[#This Row],[Placement Fee]:[Salary]]) -> 192.5 | V31: =IF(Table1[[#This Row],[MoL]]="Yes",55,0) -> 0 | W31: =IF(Table1[[#This Row],[Long MoL +3 Years]]="Yes",137.5,0) -> 0 | X31: =IF(Table1[[#This Row],[Gender]]="Female",137.5,0) -> 137.5 | Y31: =IF(Table1[[#This Row],[Education]]="Bachelors +",55,0) -> 55 | Z31: =IF(Table1[[#This Row],[Salary]]>=600,82.5,0) -> 0
A32: =Table1[[#This Row],[SL No.]] -> 31 | B32: =Table1[[#This Row],[Case manager]] -> Husain | C32: =Table1[[#This Row],[Ref No]] -> JCP/26/283681 | D32: =Table1[[#This Row],[Name]] -> Shooq Muneer Maaroof | E32: ='Placements 26'!F32 -> 46057 | F32: =IF(S32>=1,"Claimable","Claimed") -> Claimable | G32: No | I32: 46061 | J32: =IF(Table3[[#This Row],[Placement Fee & Variables]]>0,0,1) -> 0 | K32: =Table3[[#This Row],[Joining Date]]+180 -> 46237 | L32: =IF(AND(M32="", K32<=TODAY()), "Claimable", "") -> Claimable | N32: =IF(Table3[[#This Row],[6M Stat]]="Claimable",1,0) -> 1 | O32: =Table3[[#This Row],[Joining Date]]+365 -> 46422 | Q32: =IF(AND(P32="", O32<=TODAY()), "Claimable", "") | R32: =IF(Table3[[#This Row],[12 M Stat]]="Claimable",1,0) -> 0 | S32: =Table3[[#This Row],[Placement claim Highlight]]+Table3[[#This Row],[Highlight rule 6M]]+Table3[[#This Row],[Highlight rule 12 M]] -> 1 | T32: =SUM(Table3[[#This Row],[Placement Fee]:[Salary]]) -> 385 | V32: =IF(Table1[[#This Row],[MoL]]="Yes",55,0) -> 55 | W32: =IF(Table1[[#This Row],[Long MoL +3 Years]]="Yes",137.5,0) -> 137.5 | X32: =IF(Table1[[#This Row],[Gender]]="Female",137.5,0) -> 137.5 | Y32: =IF(Table1[[#This Row],[Education]]="Bachelors +",55,0) -> 55 | Z32: =IF(Table1[[#This Row],[Salary]]>=600,82.5,0) -> 0
A33: =Table1[[#This Row],[SL No.]] -> 32 | B33: =Table1[[#This Row],[Case manager]] -> Husain | C33: =Table1[[#This Row],[Ref No]] -> JCP/25/170060 | D33: =Table1[[#This Row],[Name]] -> SALMAN ADEL OUN JASIM | E33: ='Placements 26'!F33 -> 45697 | F33: =IF(S33>=1,"Claimable","Claimed") -> Claimed | G33: No | H33: this payment is done for 12 months | I33: 45697 | J33: =IF(Table3[[#This Row],[Placement Fee & Variables]]>0,0,1) -> 0 | K33: =Table3[[#This Row],[Joining Date]]+180 -> 45877 | L33: =IF(AND(M33="", K33<=TODAY()), "Claimable", "") | M33: 45879 | N33: =IF(Table3[[#This Row],[6M Stat]]="Claimable",1,0) -> 0 | O33: =Table3[[#This Row],[Joining Date]]+365 -> 46062 | P33: 46062 | Q33: =IF(AND(P33="", O33<=TODAY()), "Claimable", "") | R33: =IF(Table3[[#This Row],[12 M Stat]]="Claimable",1,0) -> 0 | S33: =Table3[[#This Row],[Placement claim Highlight]]+Table3[[#This Row],[Highlight rule 6M]]+Table3[[#This Row],[Highlight rule 12 M]] -> 0 | T33: =SUM(Table3[[#This Row],[Placement Fee]:[Salary]]) -> 55 | V33: =IF(Table1[[#This Row],[MoL]]="Yes",55,0) -> 55 | W33: =IF(Table1[[#This Row],[Long MoL +3 Years]]="Yes",137.5,0) -> 0 | X33: =IF(Table1[[#This Row],[Gender]]="Female",137.5,0) -> 0 | Y33: =IF(Table1[[#This Row],[Education]]="Bachelors +",55,0) -> 0 | Z33: =IF(Table1[[#This Row],[Salary]]>=600,82.5,0) -> 0
A34: =Table1[[#This Row],[SL No.]] -> 33 | B34: =Table1[[#This Row],[Case manager]] -> Khalifa | C34: =Table1[[#This Row],[Ref No]] -> JCP/26/271188 | D34: =Table1[[#This Row],[Name]] -> AMINA AYMAN S. NAJEM | E34: ='Placements 26'!F34 -> 46041 | F34: =IF(S34>=1,"Claimable","Claimed") -> Claimable | G34: No | I34: 46063 | J34: =IF(Table3[[#This Row],[Placement Fee & Variables]]>0,0,1) -> 0 | K34: =Table3[[#This Row],[Joining Date]]+180 -> 46221 | L34: =IF(AND(M34="", K34<=TODAY()), "Claimable", "") -> Claimable | N34: =IF(Table3[[#This Row],[6M Stat]]="Claimable",1,0) -> 1 | O34: =Table3[[#This Row],[Joining Date]]+365 -> 46406 | Q34: =IF(AND(P34="", O34<=TODAY()), "Claimable", "") | R34: =IF(Table3[[#This Row],[12 M Stat]]="Claimable",1,0) -> 0 | S34: =Table3[[#This Row],[Placement claim Highlight]]+Table3[[#This Row],[Highlight rule 6M]]+Table3[[#This Row],[Highlight rule 12 M]] -> 1 | T34: =SUM(Table3[[#This Row],[Placement Fee]:[Salary]]) -> 330 | V34: =IF(Table1[[#This Row],[MoL]]="Yes",55,0) -> 55 | W34: =IF(Table1[[#This Row],[Long MoL +3 Years]]="Yes",137.5,0) -> 0 | X34: =IF(Table1[[#This Row],[Gender]]="Female",137.5,0) -> 137.5 | Y34: =IF(Table1[[#This Row],[Education]]="Bachelors +",55,0) -> 55 | Z34: =IF(Table1[[#This Row],[Salary]]>=600,82.5,0) -> 82.5
A35: =Table1[[#This Row],[SL No.]] -> 34 | B35: =Table1[[#This Row],[Case manager]] -> Zainab Almaroom | C35: =Table1[[#This Row],[Ref No]] -> JCP/25/229821 | D35: =Table1[[#This Row],[Name]] -> BAYAN ADEL J. ALARAYEDH | E35: ='Placements 26'!F35 -> 46041 | F35: =IF(S35>=1,"Claimable","Claimed") -> Claimed | G35: No | I35: 46063 | J35: =IF(Table3[[#This Row],[Placement Fee & Variables]]>0,0,1) -> 0 | K35: =Table3[[#This Row],[Joining Date]]+180 -> 46221 | L35: =IF(AND(M35="", K35<=TODAY()), "Claimable", "") | M35: 46245 | N35: =IF(Table3[[#This Row],[6M Stat]]="Claimable",1,0) -> 0 | O35: =Table3[[#This Row],[Joining Date]]+365 -> 46406 | Q35: =IF(AND(P35="", O35<=TODAY()), "Claimable", "") | R35: =IF(Table3[[#This Row],[12 M Stat]]="Claimable",1,0) -> 0 | S35: =Table3[[#This Row],[Placement claim Highlight]]+Table3[[#This Row],[Highlight rule 6M]]+Table3[[#This Row],[Highlight rule 12 M]] -> 0 | T35: =SUM(Table3[[#This Row],[Placement Fee]:[Salary]]) -> 330 | V35: =IF(Table1[[#This Row],[MoL]]="Yes",55,0) -> 55 | W35: =IF(Table1[[#This Row],[Long MoL +3 Years]]="Yes",137.5,0) -> 0 | X35: =IF(Table1[[#This Row],[Gender]]="Female",137.5,0) -> 137.5 | Y35: =IF(Table1[[#This Row],[Education]]="Bachelors +",55,0) -> 55 | Z35: =IF(Table1[[#This Row],[Salary]]>=600,82.5,0) -> 82.5
A36: =Table1[[#This Row],[SL No.]] -> 35 | B36: =Table1[[#This Row],[Case manager]] -> Husain | C36: =Table1[[#This Row],[Ref No]] -> JCP/25/208891 | D36: =Table1[[#This Row],[Name]] -> SAYED JAAFAR EBRAHIM JAAFAR NEMAA | E36: ='Placements 26'!F36 -> 46061 | F36: =IF(S36>=1,"Claimable","Claimed") -> Claimable | G36: No | I36: 46078 | J36: =IF(Table3[[#This Row],[Placement Fee & Variables]]>0,0,1) -> 0 | K36: =Table3[[#This Row],[Joining Date]]+180 -> 46241 | L36: =IF(AND(M36="", K36<=TODAY()), "Claimable", "") -> Claimable | N36: =IF(Table3[[#This Row],[6M Stat]]="Claimable",1,0) -> 1 | O36: =Table3[[#This Row],[Joining Date]]+365 -> 46426 | Q36: =IF(AND(P36="", O36<=TODAY()), "Claimable", "") | R36: =IF(Table3[[#This Row],[12 M Stat]]="Claimable",1,0) -> 0 | S36: =Table3[[#This Row],[Placement claim Highlight]]+Table3[[#This Row],[Highlight rule 6M]]+Table3[[#This Row],[Highlight rule 12 M]] -> 1 | T36: =SUM(Table3[[#This Row],[Placement Fee]:[Salary]]) -> 55 | V36: =IF(Table1[[#This Row],[MoL]]="Yes",55,0) -> 0 | W36: =IF(Table1[[#This Row],[Long MoL +3 Years]]="Yes",137.5,0) -> 0 | X36: =IF(Table1[[#This Row],[Gender]]="Female",137.5,0) -> 0 | Y36: =IF(Table1[[#This Row],[Education]]="Bachelors +",55,0) -> 55 | Z36: =IF(Table1[[#This Row],[Salary]]>=600,82.5,0) -> 0
A37: =Table1[[#This Row],[SL No.]] -> 36 | B37: =Table1[[#This Row],[Case manager]] -> Husain | C37: =Table1[[#This Row],[Ref No]] -> JCP/25/169005 | D37: =Table1[[#This Row],[Name]] -> YASER SALMAN EBRAHIM MAHDI | E37: ='Placements 26'!F37 -> 46070 | F37: =IF(S37>=1,"Claimable","Claimed") -> Claimed | G37: No | H37: this payment is done for 12 months | I37: 45713 | J37: =IF(Table3[[#This Row],[Placement Fee & Variables]]>0,0,1) -> 0 | K37: =Table3[[#This Row],[Joining Date]]+180 -> 46250 | L37: =IF(AND(M37="", K37<=TODAY()), "Claimable", "") | M37: 45890 | N37: =IF(Table3[[#This Row],[6M Stat]]="Claimable",1,0) -> 0 | O37: =Table3[[#This Row],[Joining Date]]+365 -> 46435 | P37: 46070 | Q37: =IF(AND(P37="", O37<=TODAY()), "Claimable", "") | R37: =IF(Table3[[#This Row],[12 M Stat]]="Claimable",1,0) -> 0 | S37: =Table3[[#This Row],[Placement claim Highlight]]+Table3[[#This Row],[Highlight rule 6M]]+Table3[[#This Row],[Highlight rule 12 M]] -> 0 | T37: =SUM(Table3[[#This Row],[Placement Fee]:[Salary]]) -> 55 | V37: =IF(Table1[[#This Row],[MoL]]="Yes",55,0) -> 55 | W37: =IF(Table1[[#This Row],[Long MoL +3 Years]]="Yes",137.5,0) -> 0 | X37: =IF(Table1[[#This Row],[Gender]]="Female",137.5,0) -> 0 | Y37: =IF(Table1[[#This Row],[Education]]="Bachelors +",55,0) -> 0 | Z37: =IF(Table1[[#This Row],[Salary]]>=600,82.5,0) -> 0
A38: =Table1[[#This Row],[SL No.]] -> 37 | B38: =Table1[[#This Row],[Case manager]] -> Meaad | C38: =Table1[[#This Row],[Ref No]] -> JCP/26/284939 | D38: =Table1[[#This Row],[Name]] -> Mariam Samir Ali | E38: ='Placements 26'!F38 -> 46062 | F38: =IF(S38>=1,"Claimable","Claimed") -> Claimable | G38: Yes | H38: Not registered in SIO | J38: =IF(Table3[[#This Row],[Placement Fee & Variables]]>0,0,1) -> 1 | K38: =Table3[[#This Row],[Joining Date]]+180 -> 46242 | L38: =IF(AND(M38="", K38<=TODAY()), "Claimable", "") -> Claimable | N38: =IF(Table3[[#This Row],[6M Stat]]="Claimable",1,0) -> 1 | O38: =Table3[[#This Row],[Joining Date]]+365 -> 46427 | Q38: =IF(AND(P38="", O38<=TODAY()), "Claimable", "") | R38: =IF(Table3[[#This Row],[12 M Stat]]="Claimable",1,0) -> 0 | S38: =Table3[[#This Row],[Placement claim Highlight]]+Table3[[#This Row],[Highlight rule 6M]]+Table3[[#This Row],[Highlight rule 12 M]] -> 2 | T38: =SUM(Table3[[#This Row],[Placement Fee]:[Salary]]) -> 82.5 | V38: =IF(Table1[[#This Row],[MoL]]="Yes",55,0) -> 0 | W38: =IF(Table1[[#This Row],[Long MoL +3 Years]]="Yes",137.5,0) -> 0 | X38: =IF(Table1[[#This Row],[Gender]]="Female",137.5,0) -> 0 | Y38: =IF(Table1[[#This Row],[Education]]="Bachelors +",55,0) -> 0 | Z38: =IF(Table1[[#This Row],[Salary]]>=600,82.5,0) -> 82.5
A39: =Table1[[#This Row],[SL No.]] -> 38 | B39: =Table1[[#This Row],[Case manager]] -> Zainab Mattar | C39: =Table1[[#This Row],[Ref No]] -> JCP/26/269393 | D39: =Table1[[#This Row],[Name]] -> FATEMA HASAN JASIM HASAN AHMED | E39: ='Placements 26'!F39 -> 46075 | F39: =IF(S39>=1,"Claimable","Claimed") -> Claimable | G39: No | J39: =IF(Table3[[#This Row],[Placement Fee & Variables]]>0,0,1) -> 1 | K39: =Table3[[#This Row],[Joining Date]]+180 -> 46255 | L39: =IF(AND(M39="", K39<=TODAY()), "Claimable", "") -> Claimable | N39: =IF(Table3[[#This Row],[6M Stat]]="Claimable",1,0) -> 1 | O39: =Table3[[#This Row],[Joining Date]]+365 -> 46440 | Q39: =IF(AND(P39="", O39<=TODAY()), "Claimable", "") | R39: =IF(Table3[[#This Row],[12 M Stat]]="Claimable",1,0) -> 0 | S39: =Table3[[#This Row],[Placement claim Highlight]]+Table3[[#This Row],[Highlight rule 6M]]+Table3[[#This Row],[Highlight rule 12 M]] -> 2 | T39: =SUM(Table3[[#This Row],[Placement Fee]:[Salary]]) -> 247.5 | V39: =IF(Table1[[#This Row],[MoL]]="Yes",55,0) -> 55 | W39: =IF(Table1[[#This Row],[Long MoL +3 Years]]="Yes",137.5,0) -> 0 | X39: =IF(Table1[[#This Row],[Gender]]="Female",137.5,0) -> 137.5 | Y39: =IF(Table1[[#This Row],[Education]]="Bachelors +",55,0) -> 55 | Z39: =IF(Table1[[#This Row],[Salary]]>=600,82.5,0) -> 0
A40: =Table1[[#This Row],[SL No.]] -> 39 | B40: =Table1[[#This Row],[Case manager]] -> Mahdi | C40: =Table1[[#This Row],[Ref No]] -> JCP/25/181038 | D40: =Table1[[#This Row],[Name]] -> Hessa al doserri | E40: ='Placements 26'!F40 -> 46071 | F40: =IF(S40>=1,"Claimable","Claimed") -> Claimable | G40: No | J40: =IF(Table3[[#This Row],[Placement Fee & Variables]]>0,0,1) -> 1 | K40: =Table3[[#This Row],[Joining Date]]+180 -> 46251 | L40: =IF(AND(M40="", K40<=TODAY()), "Claimable", "") -> Claimable | N40: =IF(Table3[[#This Row],[6M Stat]]="Claimable",1,0) -> 1 | O40: =Table3[[#This Row],[Joining Date]]+365 -> 46436 | Q40: =IF(AND(P40="", O40<=TODAY()), "Claimable", "") | R40: =IF(Table3[[#This Row],[12 M Stat]]="Claimable",1,0) -> 0 | S40: =Table3[[#This Row],[Placement claim Highlight]]+Table3[[#This Row],[Highlight rule 6M]]+Table3[[#This Row],[Highlight rule 12 M]] -> 2 | T40: =SUM(Table3[[#This Row],[Placement Fee]:[Salary]]) -> 330 | V40: =IF(Table1[[#This Row],[MoL]]="Yes",55,0) -> 55 | W40: =IF(Table1[[#This Row],[Long MoL +3 Years]]="Yes",137.5,0) -> 0 | X40: =IF(Table1[[#This Row],[Gender]]="Female",137.5,0) -> 137.5 | Y40: =IF(Table1[[#This Row],[Education]]="Bachelors +",55,0) -> 55 | Z40: =IF(Table1[[#This Row],[Salary]]>=600,82.5,0) -> 82.5
A41: =Table1[[#This Row],[SL No.]] -> 40 | B41: =Table1[[#This Row],[Case manager]] -> Meaad | C41: =Table1[[#This Row],[Ref No]] -> JCP/26/284947 | D41: =Table1[[#This Row],[Name]] -> MARYAM MOHAMED A. ALMUQAHWI | E41: ='Placements 26'!F41 -> 46061 | F41: =IF(S41>=1,"Claimable","Claimed") -> Claimable | G41: Yes | I41: 46140 | J41: =IF(Table3[[#This Row],[Placement Fee & Variables]]>0,0,1) -> 0 | K41: =Table3[[#This Row],[Joining Date]]+180 -> 46241 | L41: =IF(AND(M41="", K41<=TODAY()), "Claimable", "") -> Claimable | N41: =IF(Table3[[#This Row],[6M Stat]]="Claimable",1,0) -> 1 | O41: =Table3[[#This Row],[Joining Date]]+365 -> 46426 | Q41: =IF(AND(P41="", O41<=TODAY()), "Claimable", "") | R41: =IF(Table3[[#This Row],[12 M Stat]]="Claimable",1,0) -> 0 | S41: =Table3[[#This Row],[Placement claim Highlight]]+Table3[[#This Row],[Highlight rule 6M]]+Table3[[#This Row],[Highlight rule 12 M]] -> 1 | T41: =SUM(Table3[[#This Row],[Placement Fee]:[Salary]]) -> 0 | V41: =IF(Table1[[#This Row],[MoL]]="Yes",55,0) -> 0 | W41: =IF(Table1[[#This Row],[Long MoL +3 Years]]="Yes",137.5,0) -> 0 | X41: =IF(Table1[[#This Row],[Gender]]="Female",137.5,0) -> 0 | Y41: =IF(Table1[[#This Row],[Education]]="Bachelors +",55,0) -> 0 | Z41: =IF(Table1[[#This Row],[Salary]]>=600,82.5,0) -> 0
A42: =Table1[[#This Row],[SL No.]] -> 41 | B42: =Table1[[#This Row],[Case manager]] -> Meaad | C42: =Table1[[#This Row],[Ref No]] -> JCP/26/286460 | D42: =Table1[[#This Row],[Name]] -> Sharifa Abdulrazzaq Hasan | E42: ='Placements 26'!F42 -> 46071 | F42: =IF(S42>=1,"Claimable","Claimed") -> Claimed | G42: Yes | I42: 46076 | J42: =IF(Table3[[#This Row],[Placement Fee & Variables]]>0,0,1) -> 0 | K42: =Table3[[#This Row],[Joining Date]]+180 -> 46251 | L42: =IF(AND(M42="", K42<=TODAY()), "Claimable", "") | M42: 46252 | N42: =IF(Table3[[#This Row],[6M Stat]]="Claimable",1,0) -> 0 | O42: =Table3[[#This Row],[Joining Date]]+365 -> 46436 | Q42: =IF(AND(P42="", O42<=TODAY()), "Claimable", "") | R42: =IF(Table3[[#This Row],[12 M Stat]]="Claimable",1,0) -> 0 | S42: =Table3[[#This Row],[Placement claim Highlight]]+Table3[[#This Row],[Highlight rule 6M]]+Table3[[#This Row],[Highlight rule 12 M]] -> 0 | T42: =SUM(Table3[[#This Row],[Placement Fee]:[Salary]]) -> 330 | V42: =IF(Table1[[#This Row],[MoL]]="Yes",55,0) -> 55 | W42: =IF(Table1[[#This Row],[Long MoL +3 Years]]="Yes",137.5,0) -> 0 | X42: =IF(Table1[[#This Row],[Gender]]="Female",137.5,0) -> 137.5 | Y42: =IF(Table1[[#This Row],[Education]]="Bachelors +",55,0) -> 55 | Z42: =IF(Table1[[#This Row],[Salary]]>=600,82.5,0) -> 82.5
A43: =Table1[[#This Row],[SL No.]] -> 42 | B43: =Table1[[#This Row],[Case manager]] -> Husain | C43: =Table1[[#This Row],[Ref No]] -> JCP/25/213261 | D43: =Table1[[#This Row],[Name]] -> AMMAR SALEH HASAN AHMED ALI | E43: ='Placements 26'!F43 -> 45893 | F43: =IF(S43>=1,"Claimable","Claimed") -> Claimable | G43: No | H43: this payment is done for 6months | I43: 45921 | J43: =IF(Table3[[#This Row],[Placement Fee & Variables]]>0,0,1) -> 0 | K43: =Table3[[#This Row],[Joining Date]]+180 -> 46073 | L43: =IF(AND(M43="", K43<=TODAY()), "Claimable", "") | M43: 46077 | N43: =IF(Table3[[#This Row],[6M Stat]]="Claimable",1,0) -> 0 | O43: =Table3[[#This Row],[Joining Date]]+365 -> 46258 | Q43: =IF(AND(P43="", O43<=TODAY()), "Claimable", "") -> Claimable | R43: =IF(Table3[[#This Row],[12 M Stat]]="Claimable",1,0) -> 1 | S43: =Table3[[#This Row],[Placement claim Highlight]]+Table3[[#This Row],[Highlight rule 6M]]+Table3[[#This Row],[Highlight rule 12 M]] -> 1 | T43: =SUM(Table3[[#This Row],[Placement Fee]:[Salary]]) -> 55 | V43: =IF(Table1[[#This Row],[MoL]]="Yes",55,0) -> 55 | W43: =IF(Table1[[#This Row],[Long MoL +3 Years]]="Yes",137.5,0) -> 0 | X43: =IF(Table1[[#This Row],[Gender]]="Female",137.5,0) -> 0 | Y43: =IF(Table1[[#This Row],[Education]]="Bachelors +",55,0) -> 0 | Z43: =IF(Table1[[#This Row],[Salary]]>=600,82.5,0) -> 0
A44: =Table1[[#This Row],[SL No.]] -> 43 | B44: =Table1[[#This Row],[Case manager]] -> Husain | C44: =Table1[[#This Row],[Ref No]] -> JCP/25/217089 | D44: =Table1[[#This Row],[Name]] -> ALI HUSAIN ABDULLA KAD FARDAN | E44: ='Placements 26'!F44 -> 45886 | F44: =IF(S44>=1,"Claimable","Claimed") -> Claimable | G44: No | H44: this payment is done for 6months | I44: 45889 | J44: =IF(Table3[[#This Row],[Placement Fee & Variables]]>0,0,1) -> 0 | K44: =Table3[[#This Row],[Joining Date]]+180 -> 46066 | L44: =IF(AND(M44="", K44<=TODAY()), "Claimable", "") | M44: 46079 | N44: =IF(Table3[[#This Row],[6M Stat]]="Claimable",1,0) -> 0 | O44: =Table3[[#This Row],[Joining Date]]+365 -> 46251 | Q44: =IF(AND(P44="", O44<=TODAY()), "Claimable", "") -> Claimable | R44: =IF(Table3[[#This Row],[12 M Stat]]="Claimable",1,0) -> 1 | S44: =Table3[[#This Row],[Placement claim Highlight]]+Table3[[#This Row],[Highlight rule 6M]]+Table3[[#This Row],[Highlight rule 12 M]] -> 1 | T44: =SUM(Table3[[#This Row],[Placement Fee]:[Salary]]) -> 55 | V44: =IF(Table1[[#This Row],[MoL]]="Yes",55,0) -> 55 | W44: =IF(Table1[[#This Row],[Long MoL +3 Years]]="Yes",137.5,0) -> 0 | X44: =IF(Table1[[#This Row],[Gender]]="Female",137.5,0) -> 0 | Y44: =IF(Table1[[#This Row],[Education]]="Bachelors +",55,0) -> 0 | Z44: =IF(Table1[[#This Row],[Salary]]>=600,82.5,0) -> 0
A45: =Table1[[#This Row],[SL No.]] -> 44 | B45: =Table1[[#This Row],[Case manager]] -> Meaad | C45: =Table1[[#This Row],[Ref No]] -> JCP/26/286051 | D45: =Table1[[#This Row],[Name]] -> Fatima Mukhtar | E45: ='Placements 26'!F45 -> 46068 | F45: =IF(S45>=1,"Claimable","Claimed") -> Claimed | G45: Yes | I45: 46128 | J45: =IF(Table3[[#This Row],[Placement Fee & Variables]]>0,0,1) -> 0 | K45: =Table3[[#This Row],[Joining Date]]+180 -> 46248 | L45: =IF(AND(M45="", K45<=TODAY()), "Claimable", "") | M45: 46252 | N45: =IF(Table3[[#This Row],[6M Stat]]="Claimable",1,0) -> 0 | O45: =Table3[[#This Row],[Joining Date]]+365 -> 46433 | Q45: =IF(AND(P45="", O45<=TODAY()), "Claimable", "") | R45: =IF(Table3[[#This Row],[12 M Stat]]="Claimable",1,0) -> 0 | S45: =Table3[[#This Row],[Placement claim Highlight]]+Table3[[#This Row],[Highlight rule 6M]]+Table3[[#This Row],[Highlight rule 12 M]] -> 0 | T45: =SUM(Table3[[#This Row],[Placement Fee]:[Salary]]) -> 192.5 | V45: =IF(Table1[[#This Row],[MoL]]="Yes",55,0) -> 0 | W45: =IF(Table1[[#This Row],[Long MoL +3 Years]]="Yes",137.5,0) -> 0 | X45: =IF(Table1[[#This Row],[Gender]]="Female",137.5,0) -> 137.5 | Y45: =IF(Table1[[#This Row],[Education]]="Bachelors +",55,0) -> 55 | Z45: =IF(Table1[[#This Row],[Salary]]>=600,82.5,0) -> 0
A46: =Table1[[#This Row],[SL No.]] -> 45 | B46: =Table1[[#This Row],[Case manager]] -> Meaad | C46: =Table1[[#This Row],[Ref No]] -> JCP/26/286053 | D46: =Table1[[#This Row],[Name]] -> MARYAM A.JALIL ABDULLA HASAN ABDULLA SARHAN | E46: ='Placements 26'!F46 -> 46068 | F46: =IF(S46>=1,"Claimable","Claimed") -> Claimable | G46: No | H46: Not registered in SIO | J46: =IF(Table3[[#This Row],[Placement Fee & Variables]]>0,0,1) -> 1 | K46: =Table3[[#This Row],[Joining Date]]+180 -> 46248 | L46: =IF(AND(M46="", K46<=TODAY()), "Claimable", "") -> Claimable | N46: =IF(Table3[[#This Row],[6M Stat]]="Claimable",1,0) -> 1 | O46: =Table3[[#This Row],[Joining Date]]+365 -> 46433 | Q46: =IF(AND(P46="", O46<=TODAY()), "Claimable", "") | R46: =IF(Table3[[#This Row],[12 M Stat]]="Claimable",1,0) -> 0 | S46: =Table3[[#This Row],[Placement claim Highlight]]+Table3[[#This Row],[Highlight rule 6M]]+Table3[[#This Row],[Highlight rule 12 M]] -> 2 | T46: =SUM(Table3[[#This Row],[Placement Fee]:[Salary]]) -> 192.5 | V46: =IF(Table1[[#This Row],[MoL]]="Yes",55,0) -> 0 | W46: =IF(Table1[[#This Row],[Long MoL +3 Years]]="Yes",137.5,0) -> 0 | X46: =IF(Table1[[#This Row],[Gender]]="Female",137.5,0) -> 137.5 | Y46: =IF(Table1[[#This Row],[Education]]="Bachelors +",55,0) -> 55 | Z46: =IF(Table1[[#This Row],[Salary]]>=600,82.5,0) -> 0
A47: =Table1[[#This Row],[SL No.]] -> 46 | B47: =Table1[[#This Row],[Case manager]] -> Meaad | C47: =Table1[[#This Row],[Ref No]] -> JCP/26/286885 | D47: =Table1[[#This Row],[Name]] -> Naba Zuhair AlElaiwat | E47: ='Placements 26'!F47 -> 46076 | F47: =IF(S47>=1,"Claimable","Claimed") -> Claimed | G47: Yes | I47: 46133 | J47: =IF(Table3[[#This Row],[Placement Fee & Variables]]>0,0,1) -> 0 | K47: =Table3[[#This Row],[Joining Date]]+180 -> 46256 | L47: =IF(AND(M47="", K47<=TODAY()), "Claimable", "") | M47: 46245 | N47: =IF(Table3[[#This Row],[6M Stat]]="Claimable",1,0) -> 0 | O47: =Table3[[#This Row],[Joining Date]]+365 -> 46441 | Q47: =IF(AND(P47="", O47<=TODAY()), "Claimable", "") | R47: =IF(Table3[[#This Row],[12 M Stat]]="Claimable",1,0) -> 0 | S47: =Table3[[#This Row],[Placement claim Highlight]]+Table3[[#This Row],[Highlight rule 6M]]+Table3[[#This Row],[Highlight rule 12 M]] -> 0 | T47: =SUM(Table3[[#This Row],[Placement Fee]:[Salary]]) -> 0 | V47: =IF(Table1[[#This Row],[MoL]]="Yes",55,0) -> 0 | W47: =IF(Table1[[#This Row],[Long MoL +3 Years]]="Yes",137.5,0) -> 0 | X47: =IF(Table1[[#This Row],[Gender]]="Female",137.5,0) -> 0 | Y47: =IF(Table1[[#This Row],[Education]]="Bachelors +",55,0) -> 0 | Z47: =IF(Table1[[#This Row],[Salary]]>=600,82.5,0) -> 0
A48: =Table1[[#This Row],[SL No.]] -> 47 | B48: =Table1[[#This Row],[Case manager]] -> Husain | C48: =Table1[[#This Row],[Ref No]] -> JCP/25/171258 | D48: =Table1[[#This Row],[Name]] -> Noora Faqir | E48: ='Placements 26'!F48 -> 45721 | F48: =IF(S48>=1,"Claimable","Claimed") -> Claimed | G48: No | H48: this payment is done for 12 months | I48: 45722 | J48: =IF(Table3[[#This Row],[Placement Fee & Variables]]>0,0,1) -> 0 | K48: =Table3[[#This Row],[Joining Date]]+180 -> 45901 | L48: =IF(AND(M48="", K48<=TODAY()), "Claimable", "") | M48: 45907 | N48: =IF(Table3[[#This Row],[6M Stat]]="Claimable",1,0) -> 0 | O48: =Table3[[#This Row],[Joining Date]]+365 -> 46086 | P48: 46086 | Q48: =IF(AND(P48="", O48<=TODAY()), "Claimable", "") | R48: =IF(Table3[[#This Row],[12 M Stat]]="Claimable",1,0) -> 0 | S48: =Table3[[#This Row],[Placement claim Highlight]]+Table3[[#This Row],[Highlight rule 6M]]+Table3[[#This Row],[Highlight rule 12 M]] -> 0 | T48: =SUM(Table3[[#This Row],[Placement Fee]:[Salary]]) -> 137.5 | V48: =IF(Table1[[#This Row],[MoL]]="Yes",55,0) -> 0 | W48: =IF(Table1[[#This Row],[Long MoL +3 Years]]="Yes",137.5,0) -> 0 | X48: =IF(Table1[[#This Row],[Gender]]="Female",137.5,0) -> 137.5 | Y48: =IF(Table1[[#This Row],[Education]]="Bachelors +",55,0) -> 0 | Z48: =IF(Table1[[#This Row],[Salary]]>=600,82.5,0) -> 0
A49: =Table1[[#This Row],[SL No.]] -> 48 | B49: =Table1[[#This Row],[Case manager]] -> Meaad | C49: =Table1[[#This Row],[Ref No]] -> JCP/26/286809 | D49: =Table1[[#This Row],[Name]] -> Ameera Husain Hamad | E49: ='Placements 26'!F49 -> 46082 | F49: =IF(S49>=1,"Claimable","Claimed") -> Claimable | G49: No | I49: 45724 | J49: =IF(Table3[[#This Row],[Placement Fee & Variables]]>0,0,1) -> 0 | K49: =Table3[[#This Row],[Joining Date]]+180 -> 46262 | L49: =IF(AND(M49="", K49<=TODAY()), "Claimable", "") -> Claimable | N49: =IF(Table3[[#This Row],[6M Stat]]="Claimable",1,0) -> 1 | O49: =Table3[[#This Row],[Joining Date]]+365 -> 46447 | Q49: =IF(AND(P49="", O49<=TODAY()), "Claimable", "") | R49: =IF(Table3[[#This Row],[12 M Stat]]="Claimable",1,0) -> 0 | S49: =Table3[[#This Row],[Placement claim Highlight]]+Table3[[#This Row],[Highlight rule 6M]]+Table3[[#This Row],[Highlight rule 12 M]] -> 1 | T49: =SUM(Table3[[#This Row],[Placement Fee]:[Salary]]) -> 275 | V49: =IF(Table1[[#This Row],[MoL]]="Yes",55,0) -> 0 | W49: =IF(Table1[[#This Row],[Long MoL +3 Years]]="Yes",137.5,0) -> 0 | X49: =IF(Table1[[#This Row],[Gender]]="Female",137.5,0) -> 137.5 | Y49: =IF(Table1[[#This Row],[Education]]="Bachelors +",55,0) -> 55 | Z49: =IF(Table1[[#This Row],[Salary]]>=600,82.5,0) -> 82.5
A50: =Table1[[#This Row],[SL No.]] -> 49 | B50: =Table1[[#This Row],[Case manager]] -> Husain | C50: =Table1[[#This Row],[Ref No]] -> JCP/25/153757 | D50: =Table1[[#This Row],[Name]] -> Sayed Moosa Mahdi Alawi Mohsen Ahmed | E50: ='Placements 26'!F50 -> 45725 | F50: =IF(S50>=1,"Claimable","Claimed") -> Claimed | G50: No | H50: this payment is done for 12 months | I50: 45736 | J50: =IF(Table3[[#This Row],[Placement Fee & Variables]]>0,0,1) -> 0 | K50: =Table3[[#This Row],[Joining Date]]+180 -> 45905 | L50: =IF(AND(M50="", K50<=TODAY()), "Claimable", "") | M50: 45909 | N50: =IF(Table3[[#This Row],[6M Stat]]="Claimable",1,0) -> 0 | O50: =Table3[[#This Row],[Joining Date]]+365 -> 46090 | P50: 46090 | Q50: =IF(AND(P50="", O50<=TODAY()), "Claimable", "") | R50: =IF(Table3[[#This Row],[12 M Stat]]="Claimable",1,0) -> 0 | S50: =Table3[[#This Row],[Placement claim Highlight]]+Table3[[#This Row],[Highlight rule 6M]]+Table3[[#This Row],[Highlight rule 12 M]] -> 0 | T50: =SUM(Table3[[#This Row],[Placement Fee]:[Salary]]) -> 0 | V50: =IF(Table1[[#This Row],[MoL]]="Yes",55,0) -> 0 | W50: =IF(Table1[[#This Row],[Long MoL +3 Years]]="Yes",137.5,0) -> 0 | X50: =IF(Table1[[#This Row],[Gender]]="Female",137.5,0) -> 0 | Y50: =IF(Table1[[#This Row],[Education]]="Bachelors +",55,0) -> 0 | Z50: =IF(Table1[[#This Row],[Salary]]>=600,82.5,0) -> 0
A51: =Table1[[#This Row],[SL No.]] -> 50 | B51: =Table1[[#This Row],[Case manager]] -> Husain | C51: =Table1[[#This Row],[Ref No]] -> JCP/24/096845 | D51: =Table1[[#This Row],[Name]] -> KARAR HUSAM ALI YATEEM | E51: ='Placements 26'!F51 -> 45911 | F51: =IF(S51>=1,"Claimable","Claimed") -> Claimable | G51: No | H51: this payment is done for 12 months | I51: 45931 | J51: =IF(Table3[[#This Row],[Placement Fee & Variables]]>0,0,1) -> 0 | K51: =Table3[[#This Row],[Joining Date]]+180 -> 46091 | L51: =IF(AND(M51="", K51<=TODAY()), "Claimable", "") | M51: 46093 | N51: =IF(Table3[[#This Row],[6M Stat]]="Claimable",1,0) -> 0 | O51: =Table3[[#This Row],[Joining Date]]+365 -> 46276 | Q51: =IF(AND(P51="", O51<=TODAY()), "Claimable", "") -> Claimable | R51: =IF(Table3[[#This Row],[12 M Stat]]="Claimable",1,0) -> 1 | S51: =Table3[[#This Row],[Placement claim Highlight]]+Table3[[#This Row],[Highlight rule 6M]]+Table3[[#This Row],[Highlight rule 12 M]] -> 1 | T51: =SUM(Table3[[#This Row],[Placement Fee]:[Salary]]) -> 192.5 | V51: =IF(Table1[[#This Row],[MoL]]="Yes",55,0) -> 55 | W51: =IF(Table1[[#This Row],[Long MoL +3 Years]]="Yes",137.5,0) -> 137.5 | X51: =IF(Table1[[#This Row],[Gender]]="Female",137.5,0) -> 0 | Y51: =IF(Table1[[#This Row],[Education]]="Bachelors +",55,0) -> 0 | Z51: =IF(Table1[[#This Row],[Salary]]>=600,82.5,0) -> 0
A52: =Table1[[#This Row],[SL No.]] -> 51 | B52: =Table1[[#This Row],[Case manager]] -> Husain | C52: =Table1[[#This Row],[Ref No]] -> JCP/25/225850 | D52: =Table1[[#This Row],[Name]] -> HASAN FADHEL HASAN ISMAEEL ALI | E52: ='Placements 26'!F52 -> 45914 | F52: =IF(S52>=1,"Claimable","Claimed") -> Claimable | G52: No | H52: this payment is done for 6months | I52: 45915 | J52: =IF(Table3[[#This Row],[Placement Fee & Variables]]>0,0,1) -> 0 | K52: =Table3[[#This Row],[Joining Date]]+180 -> 46094 | L52: =IF(AND(M52="", K52<=TODAY()), "Claimable", "") | M52: 46096 | N52: =IF(Table3[[#This Row],[6M Stat]]="Claimable",1,0) -> 0 | O52: =Table3[[#This Row],[Joining Date]]+365 -> 46279 | Q52: =IF(AND(P52="", O52<=TODAY()), "Claimable", "") -> Claimable | R52: =IF(Table3[[#This Row],[12 M Stat]]="Claimable",1,0) -> 1 | S52: =Table3[[#This Row],[Placement claim Highlight]]+Table3[[#This Row],[Highlight rule 6M]]+Table3[[#This Row],[Highlight rule 12 M]] -> 1 | T52: =SUM(Table3[[#This Row],[Placement Fee]:[Salary]]) -> 55 | V52: =IF(Table1[[#This Row],[MoL]]="Yes",55,0) -> 0 | W52: =IF(Table1[[#This Row],[Long MoL +3 Years]]="Yes",137.5,0) -> 0 | X52: =IF(Table1[[#This Row],[Gender]]="Female",137.5,0) -> 0 | Y52: =IF(Table1[[#This Row],[Education]]="Bachelors +",55,0) -> 55 | Z52: =IF(Table1[[#This Row],[Salary]]>=600,82.5,0) -> 0
A53: =Table1[[#This Row],[SL No.]] -> 52 | B53: =Table1[[#This Row],[Case manager]] -> Husain | C53: =Table1[[#This Row],[Ref No]] -> JCP/25/173504 | D53: =Table1[[#This Row],[Name]] -> Shuaib hasan Rustam | E53: ='Placements 26'!F53 -> 45739 | F53: =IF(S53>=1,"Claimable","Claimed") -> Claimed | G53: No | H53: this payment is done for 12 months | I53: 45740 | J53: =IF(Table3[[#This Row],[Placement Fee & Variables]]>0,0,1) -> 0 | K53: =Table3[[#This Row],[Joining Date]]+180 -> 45919 | L53: =IF(AND(M53="", K53<=TODAY()), "Claimable", "") | M53: 45923 | N53: =IF(Table3[[#This Row],[6M Stat]]="Claimable",1,0) -> 0 | O53: =Table3[[#This Row],[Joining Date]]+365 -> 46104 | P53: 46112 | Q53: =IF(AND(P53="", O53<=TODAY()), "Claimable", "") | R53: =IF(Table3[[#This Row],[12 M Stat]]="Claimable",1,0) -> 0 | S53: =Table3[[#This Row],[Placement claim Highlight]]+Table3[[#This Row],[Highlight rule 6M]]+Table3[[#This Row],[Highlight rule 12 M]] -> 0 | T53: =SUM(Table3[[#This Row],[Placement Fee]:[Salary]]) -> 192.5 | V53: =IF(Table1[[#This Row],[MoL]]="Yes",55,0) -> 55 | W53: =IF(Table1[[#This Row],[Long MoL +3 Years]]="Yes",137.5,0) -> 137.5 | X53: =IF(Table1[[#This Row],[Gender]]="Female",137.5,0) -> 0 | Y53: =IF(Table1[[#This Row],[Education]]="Bachelors +",55,0) -> 0 | Z53: =IF(Table1[[#This Row],[Salary]]>=600,82.5,0) -> 0
A54: =Table1[[#This Row],[SL No.]] -> 53 | B54: =Table1[[#This Row],[Case manager]] -> Husain | C54: =Table1[[#This Row],[Ref No]] -> JCP/25/217425 | D54: =Table1[[#This Row],[Name]] -> ALI SALMAN HASAN ALI | E54: ='Placements 26'!F54 -> 45922 | F54: =IF(S54>=1,"Claimable","Claimed") -> Claimable | G54: No | H54: this payment is done for 6 months | I54: 45922 | J54: =IF(Table3[[#This Row],[Placement Fee & Variables]]>0,0,1) -> 0 | K54: =Table3[[#This Row],[Joining Date]]+180 -> 46102 | L54: =IF(AND(M54="", K54<=TODAY()), "Claimable", "") | M54: 46112 | N54: =IF(Table3[[#This Row],[6M Stat]]="Claimable",1,0) -> 0 | O54: =Table3[[#This Row],[Joining Date]]+365 -> 46287 | Q54: =IF(AND(P54="", O54<=TODAY()), "Claimable", "") -> Claimable | R54: =IF(Table3[[#This Row],[12 M Stat]]="Claimable",1,0) -> 1 | S54: =Table3[[#This Row],[Placement claim Highlight]]+Table3[[#This Row],[Highlight rule 6M]]+Table3[[#This Row],[Highlight rule 12 M]] -> 1 | T54: =SUM(Table3[[#This Row],[Placement Fee]:[Salary]]) -> 192.5 | V54: =IF(Table1[[#This Row],[MoL]]="Yes",55,0) -> 55 | W54: =IF(Table1[[#This Row],[Long MoL +3 Years]]="Yes",137.5,0) -> 137.5 | X54: =IF(Table1[[#This Row],[Gender]]="Female",137.5,0) -> 0 | Y54: =IF(Table1[[#This Row],[Education]]="Bachelors +",55,0) -> 0 | Z54: =IF(Table1[[#This Row],[Salary]]>=600,82.5,0) -> 0
A55: =Table1[[#This Row],[SL No.]] -> 54 | B55: =Table1[[#This Row],[Case manager]] -> Husain | C55: =Table1[[#This Row],[Ref No]] -> JCP/24/047875 | D55: =Table1[[#This Row],[Name]] -> AMMAR SAYED YASER SAEED MOHAMED | E55: ='Placements 26'!F55 -> 45922 | F55: =IF(S55>=1,"Claimable","Claimed") -> Claimable | G55: No | H55: this payment is done for 6 months | I55: 45922 | J55: =IF(Table3[[#This Row],[Placement Fee & Variables]]>0,0,1) -> 0 | K55: =Table3[[#This Row],[Joining Date]]+180 -> 46102 | L55: =IF(AND(M55="", K55<=TODAY()), "Claimable", "") | M55: 46112 | N55: =IF(Table3[[#This Row],[6M Stat]]="Claimable",1,0) -> 0 | O55: =Table3[[#This Row],[Joining Date]]+365 -> 46287 | Q55: =IF(AND(P55="", O55<=TODAY()), "Claimable", "") -> Claimable | R55: =IF(Table3[[#This Row],[12 M Stat]]="Claimable",1,0) -> 1 | S55: =Table3[[#This Row],[Placement claim Highlight]]+Table3[[#This Row],[Highlight rule 6M]]+Table3[[#This Row],[Highlight rule 12 M]] -> 1 | T55: =SUM(Table3[[#This Row],[Placement Fee]:[Salary]]) -> 330 | V55: =IF(Table1[[#This Row],[MoL]]="Yes",55,0) -> 55 | W55: =IF(Table1[[#This Row],[Long MoL +3 Years]]="Yes",137.5,0) -> 137.5 | X55: =IF(Table1[[#This Row],[Gender]]="Female",137.5,0) -> 0 | Y55: =IF(Table1[[#This Row],[Education]]="Bachelors +",55,0) -> 55 | Z55: =IF(Table1[[#This Row],[Salary]]>=600,82.5,0) -> 82.5
A56: =Table1[[#This Row],[SL No.]] -> 55 | B56: =Table1[[#This Row],[Case manager]] -> Meaad | C56: =Table1[[#This Row],[Ref No]] -> JCP/25/229307 | D56: =Table1[[#This Row],[Name]] -> Bader Abdulnabi Ebrahim | E56: ='Placements 26'!F56 -> 45921 | F56: =IF(S56>=1,"Claimable","Claimed") -> Claimable | G56: No | H56: this payment is done for 6 months | I56: 45924 | J56: =IF(Table3[[#This Row],[Placement Fee & Variables]]>0,0,1) -> 0 | K56: =Table3[[#This Row],[Joining Date]]+180 -> 46101 | L56: =IF(AND(M56="", K56<=TODAY()), "Claimable", "") | M56: 46092 | N56: =IF(Table3[[#This Row],[6M Stat]]="Claimable",1,0) -> 0 | O56: =Table3[[#This Row],[Joining Date]]+365 -> 46286 | Q56: =IF(AND(P56="", O56<=TODAY()), "Claimable", "") -> Claimable | R56: =IF(Table3[[#This Row],[12 M Stat]]="Claimable",1,0) -> 1 | S56: =Table3[[#This Row],[Placement claim Highlight]]+Table3[[#This Row],[Highlight rule 6M]]+Table3[[#This Row],[Highlight rule 12 M]] -> 1 | T56: =SUM(Table3[[#This Row],[Placement Fee]:[Salary]]) -> 247.5 | V56: =IF(Table1[[#This Row],[MoL]]="Yes",55,0) -> 55 | W56: =IF(Table1[[#This Row],[Long MoL +3 Years]]="Yes",137.5,0) -> 137.5 | X56: =IF(Table1[[#This Row],[Gender]]="Female",137.5,0) -> 0 | Y56: =IF(Table1[[#This Row],[Education]]="Bachelors +",55,0) -> 55 | Z56: =IF(Table1[[#This Row],[Salary]]>=600,82.5,0) -> 0
A57: =Table1[[#This Row],[SL No.]] -> 56 | B57: =Table1[[#This Row],[Case manager]] -> Meaad | C57: =Table1[[#This Row],[Ref No]] -> JCP/25/174221 | D57: =Table1[[#This Row],[Name]] -> فاطمه حسن الليث | E57: ='Placements 26'!F57 -> 45921 | F57: =IF(S57>=1,"Claimable","Claimed") -> Claimed | G57: No | I57: 45924 | J57: =IF(Table3[[#This Row],[Placement Fee & Variables]]>0,0,1) -> 0 | K57: =Table3[[#This Row],[Joining Date]]+180 -> 46101 | L57: =IF(AND(M57="", K57<=TODAY()), "Claimable", "") | M57: 46092 | N57: =IF(Table3[[#This Row],[6M Stat]]="Claimable",1,0) -> 0 | O57: =Table3[[#This Row],[Joining Date]]+365 -> 46286 | P57: 46286 | Q57: =IF(AND(P57="", O57<=TODAY()), "Claimable", "") | R57: =IF(Table3[[#This Row],[12 M Stat]]="Claimable",1,0) -> 0 | S57: =Table3[[#This Row],[Placement claim Highlight]]+Table3[[#This Row],[Highlight rule 6M]]+Table3[[#This Row],[Highlight rule 12 M]] -> 0 | T57: =SUM(Table3[[#This Row],[Placement Fee]:[Salary]]) -> 192.5 | V57: =IF(Table1[[#This Row],[MoL]]="Yes",55,0) -> 0 | W57: =IF(Table1[[#This Row],[Long MoL +3 Years]]="Yes",137.5,0) -> 0 | X57: =IF(Table1[[#This Row],[Gender]]="Female",137.5,0) -> 137.5 | Y57: =IF(Table1[[#This Row],[Education]]="Bachelors +",55,0) -> 55 | Z57: =IF(Table1[[#This Row],[Salary]]>=600,82.5,0) -> 0
A58: =Table1[[#This Row],[SL No.]] -> 57 | B58: =Table1[[#This Row],[Case manager]] -> Husain | C58: =Table1[[#This Row],[Ref No]] -> JCP/25/180485 | D58: =Table1[[#This Row],[Name]] -> ساره ساتر | E58: ='Placements 26'!F58 -> 45740 | F58: =IF(S58>=1,"Claimable","Claimed") -> Claimed | G58: No | H58: this payment is done for 6 months | I58: 45743 | J58: =IF(Table3[[#This Row],[Placement Fee & Variables]]>0,0,1) -> 0 | K58: =Table3[[#This Row],[Joining Date]]+180 -> 45920 | L58: =IF(AND(M58="", K58<=TODAY()), "Claimable", "") | M58: 45924 | N58: =IF(Table3[[#This Row],[6M Stat]]="Claimable",1,0) -> 0 | O58: =Table3[[#This Row],[Joining Date]]+365 -> 46105 | P58: 46112 | Q58: =IF(AND(P58="", O58<=TODAY()), "Claimable", "") | R58: =IF(Table3[[#This Row],[12 M Stat]]="Claimable",1,0) -> 0 | S58: =Table3[[#This Row],[Placement claim Highlight]]+Table3[[#This Row],[Highlight rule 6M]]+Table3[[#This Row],[Highlight rule 12 M]] -> 0 | T58: =SUM(Table3[[#This Row],[Placement Fee]:[Salary]]) -> 385 | V58: =IF(Table1[[#This Row],[MoL]]="Yes",55,0) -> 55 | W58: =IF(Table1[[#This Row],[Long MoL +3 Years]]="Yes",137.5,0) -> 137.5 | X58: =IF(Table1[[#This Row],[Gender]]="Female",137.5,0) -> 137.5 | Y58: =IF(Table1[[#This Row],[Education]]="Bachelors +",55,0) -> 55 | Z58: =IF(Table1[[#This Row],[Salary]]>=600,82.5,0) -> 0
A59: =Table1[[#This Row],[SL No.]] -> 58 | C59: =Table1[[#This Row],[Ref No]] -> JCP/25/194119 | D59: =Table1[[#This Row],[Name]] -> MAHDI MOHAMED MAHDI ALI | E59: ='Placements 26'!F59 -> 45792 | F59: =IF(S59>=1,"Claimable","Claimed") -> Claimable | G59: No | H59: this payment is done for 6 months | I59: 45792 | J59: =IF(Table3[[#This Row],[Placement Fee & Variables]]>0,0,1) -> 0 | K59: =Table3[[#This Row],[Joining Date]]+180 -> 45972 | L59: =IF(AND(M59="", K59<=TODAY()), "Claimable", "") | M59: 45998 | N59: =IF(Table3[[#This Row],[6M Stat]]="Claimable",1,0) -> 0 | O59: =Table3[[#This Row],[Joining Date]]+365 -> 46157 | Q59: =IF(AND(P59="", O59<=TODAY()), "Claimable", "") -> Claimable | R59: =IF(Table3[[#This Row],[12 M Stat]]="Claimable",1,0) -> 1 | S59: =Table3[[#This Row],[Placement claim Highlight]]+Table3[[#This Row],[Highlight rule 6M]]+Table3[[#This Row],[Highlight rule 12 M]] -> 1 | T59: =SUM(Table3[[#This Row],[Placement Fee]:[Salary]]) -> 0 | V59: =IF(Table1[[#This Row],[MoL]]="Yes",55,0) -> 0 | W59: =IF(Table1[[#This Row],[Long MoL +3 Years]]="Yes",137.5,0) -> 0 | X59: =IF(Table1[[#This Row],[Gender]]="Female",137.5,0) -> 0 | Y59: =IF(Table1[[#This Row],[Education]]="Bachelors +",55,0) -> 0 | Z59: =IF(Table1[[#This Row],[Salary]]>=600,82.5,0) -> 0
A60: =Table1[[#This Row],[SL No.]] -> 59 | B60: =Table1[[#This Row],[Case manager]] -> Malak | C60: =Table1[[#This Row],[Ref No]] -> JCP/25/178761 | D60: =Table1[[#This Row],[Name]] -> MAJED MOHAMED ALI MOHSEN ZABAR | E60: ='Placements 26'!F60 -> 45922 | F60: =IF(S60>=1,"Claimable","Claimed") -> Claimable | G60: No | H60: this payment is done for 6 months | I60: 45728 | J60: =IF(Table3[[#This Row],[Placement Fee & Variables]]>0,0,1) -> 0 | K60: =Table3[[#This Row],[Joining Date]]+180 -> 46102 | L60: =IF(AND(M60="", K60<=TODAY()), "Claimable", "") | M60: 46112 | N60: =IF(Table3[[#This Row],[6M Stat]]="Claimable",1,0) -> 0 | O60: =Table3[[#This Row],[Joining Date]]+365 -> 46287 | Q60: =IF(AND(P60="", O60<=TODAY()), "Claimable", "") -> Claimable | R60: =IF(Table3[[#This Row],[12 M Stat]]="Claimable",1,0) -> 1 | S60: =Table3[[#This Row],[Placement claim Highlight]]+Table3[[#This Row],[Highlight rule 6M]]+Table3[[#This Row],[Highlight rule 12 M]] -> 1 | T60: =SUM(Table3[[#This Row],[Placement Fee]:[Salary]]) -> 137.5 | V60: =IF(Table1[[#This Row],[MoL]]="Yes",55,0) -> 55 | W60: =IF(Table1[[#This Row],[Long MoL +3 Years]]="Yes",137.5,0) -> 0 | X60: =IF(Table1[[#This Row],[Gender]]="Female",137.5,0) -> 0 | Y60: =IF(Table1[[#This Row],[Education]]="Bachelors +",55,0) -> 0 | Z60: =IF(Table1[[#This Row],[Salary]]>=600,82.5,0) -> 82.5
A61: =Table1[[#This Row],[SL No.]] -> 60 | B61: =Table1[[#This Row],[Case manager]] -> Zainab Mattar | C61: =Table1[[#This Row],[Ref No]] -> JCP/25/231016 | D61: =Table1[[#This Row],[Name]] -> No Placement Recorded | E61: ='Placements 26'!F61 -> 45668 | F61: =IF(S61>=1,"Claimable","Claimed") -> Claimable | G61: No | J61: =IF(Table3[[#This Row],[Placement Fee & Variables]]>0,0,1) -> 1 | K61: =Table3[[#This Row],[Joining Date]]+180 -> 45848 | L61: =IF(AND(M61="", K61<=TODAY()), "Claimable", "") -> Claimable | N61: =IF(Table3[[#This Row],[6M Stat]]="Claimable",1,0) -> 1 | O61: =Table3[[#This Row],[Joining Date]]+365 -> 46033 | Q61: =IF(AND(P61="", O61<=TODAY()), "Claimable", "") -> Claimable | R61: =IF(Table3[[#This Row],[12 M Stat]]="Claimable",1,0) -> 1 | S61: =Table3[[#This Row],[Placement claim Highlight]]+Table3[[#This Row],[Highlight rule 6M]]+Table3[[#This Row],[Highlight rule 12 M]] -> 3 | T61: =SUM(Table3[[#This Row],[Placement Fee]:[Salary]]) -> 0 | V61: =IF(Table1[[#This Row],[MoL]]="Yes",55,0) -> 0 | W61: =IF(Table1[[#This Row],[Long MoL +3 Years]]="Yes",137.5,0) -> 0 | X61: =IF(Table1[[#This Row],[Gender]]="Female",137.5,0) -> 0 | Y61: =IF(Table1[[#This Row],[Education]]="Bachelors +",55,0) -> 0 | Z61: =IF(Table1[[#This Row],[Salary]]>=600,82.5,0) -> 0
A62: =Table1[[#This Row],[SL No.]] -> 61 | B62: =Table1[[#This Row],[Case manager]] -> Meaad | C62: =Table1[[#This Row],[Ref No]] -> JCP/25/190585 | D62: =Table1[[#This Row],[Name]] -> ZAINAB MOHAMED GHULOOM ALI | E62: ='Placements 26'!F62 -> 45811 | F62: =IF(S62>=1,"Claimable","Claimed") -> Claimed | G62: No | H62: this payment is done for 6 months | I62: 46176 | J62: =IF(Table3[[#This Row],[Placement Fee & Variables]]>0,0,1) -> 0 | K62: =Table3[[#This Row],[Joining Date]]+180 -> 45991 | L62: =IF(AND(M62="", K62<=TODAY()), "Claimable", "") | M62: 45998 | N62: =IF(Table3[[#This Row],[6M Stat]]="Claimable",1,0) -> 0 | O62: =Table3[[#This Row],[Joining Date]]+365 -> 46176 | P62: 46245 | Q62: =IF(AND(P62="", O62<=TODAY()), "Claimable", "") | R62: =IF(Table3[[#This Row],[12 M Stat]]="Claimable",1,0) -> 0 | S62: =Table3[[#This Row],[Placement claim Highlight]]+Table3[[#This Row],[Highlight rule 6M]]+Table3[[#This Row],[Highlight rule 12 M]] -> 0 | T62: =SUM(Table3[[#This Row],[Placement Fee]:[Salary]]) -> 247.5 | V62: =IF(Table1[[#This Row],[MoL]]="Yes",55,0) -> 55 | W62: =IF(Table1[[#This Row],[Long MoL +3 Years]]="Yes",137.5,0) -> 0 | X62: =IF(Table1[[#This Row],[Gender]]="Female",137.5,0) -> 137.5 | Y62: =IF(Table1[[#This Row],[Education]]="Bachelors +",55,0) -> 55 | Z62: =IF(Table1[[#This Row],[Salary]]>=600,82.5,0) -> 0
A63: =Table1[[#This Row],[SL No.]] -> 62 | B63: =Table1[[#This Row],[Case manager]] -> Husain | C63: =Table1[[#This Row],[Ref No]] -> JCP/26/288742 | D63: =Table1[[#This Row],[Name]] -> SAKINA ALI | E63: ='Placements 26'!F63 -> 46095 | F63: =IF(S63>=1,"Claimable","Claimed") -> Claimable | G63: No | I63: 46129 | J63: =IF(Table3[[#This Row],[Placement Fee & Variables]]>0,0,1) -> 0 | K63: =Table3[[#This Row],[Joining Date]]+180 -> 46275 | L63: =IF(AND(M63="", K63<=TODAY()), "Claimable", "") -> Claimable | N63: =IF(Table3[[#This Row],[6M Stat]]="Claimable",1,0) -> 1 | O63: =Table3[[#This Row],[Joining Date]]+365 -> 46460 | Q63: =IF(AND(P63="", O63<=TODAY()), "Claimable", "") | R63: =IF(Table3[[#This Row],[12 M Stat]]="Claimable",1,0) -> 0 | S63: =Table3[[#This Row],[Placement claim Highlight]]+Table3[[#This Row],[Highlight rule 6M]]+Table3[[#This Row],[Highlight rule 12 M]] -> 1 | T63: =SUM(Table3[[#This Row],[Placement Fee]:[Salary]]) -> 137.5 | V63: =IF(Table1[[#This Row],[MoL]]="Yes",55,0) -> 0 | W63: =IF(Table1[[#This Row],[Long MoL +3 Years]]="Yes",137.5,0) -> 0 | X63: =IF(Table1[[#This Row],[Gender]]="Female",137.5,0) -> 137.5 | Y63: =IF(Table1[[#This Row],[Education]]="Bachelors +",55,0) -> 0 | Z63: =IF(Table1[[#This Row],[Salary]]>=600,82.5,0) -> 0
A64: =Table1[[#This Row],[SL No.]] -> 63 | B64: =Table1[[#This Row],[Case manager]] -> Husain | C64: =Table1[[#This Row],[Ref No]] -> JCP/26/288724 | D64: =Table1[[#This Row],[Name]] -> السيد جعفر ناصر | E64: ='Placements 26'!F64 -> 46095 | F64: =IF(S64>=1,"Claimable","Claimed") -> Claimable | G64: No | I64: 46129 | J64: =IF(Table3[[#This Row],[Placement Fee & Variables]]>0,0,1) -> 0 | K64: =Table3[[#This Row],[Joining Date]]+180 -> 46275 | L64: =IF(AND(M64="", K64<=TODAY()), "Claimable", "") -> Claimable | N64: =IF(Table3[[#This Row],[6M Stat]]="Claimable",1,0) -> 1 | O64: =Table3[[#This Row],[Joining Date]]+365 -> 46460 | Q64: =IF(AND(P64="", O64<=TODAY()), "Claimable", "") | R64: =IF(Table3[[#This Row],[12 M Stat]]="Claimable",1,0) -> 0 | S64: =Table3[[#This Row],[Placement claim Highlight]]+Table3[[#This Row],[Highlight rule 6M]]+Table3[[#This Row],[Highlight rule 12 M]] -> 1 | T64: =SUM(Table3[[#This Row],[Placement Fee]:[Salary]]) -> 0 | V64: =IF(Table1[[#This Row],[MoL]]="Yes",55,0) -> 0 | W64: =IF(Table1[[#This Row],[Long MoL +3 Years]]="Yes",137.5,0) -> 0 | X64: =IF(Table1[[#This Row],[Gender]]="Female",137.5,0) -> 0 | Y64: =IF(Table1[[#This Row],[Education]]="Bachelors +",55,0) -> 0 | Z64: =IF(Table1[[#This Row],[Salary]]>=600,82.5,0) -> 0
A65: =Table1[[#This Row],[SL No.]] -> 64 | B65: =Table1[[#This Row],[Case manager]] -> Meaad | C65: =Table1[[#This Row],[Ref No]] -> JCP/25/195286 | D65: =Table1[[#This Row],[Name]] -> HASAN AQEEL ALI HASAN ALJESHI | E65: ='Placements 26'!F65 -> 45819 | F65: =IF(S65>=1,"Claimable","Claimed") -> Claimed | G65: Yes | H65: this payment is done for 6 months | I65: 45819 | J65: =IF(Table3[[#This Row],[Placement Fee & Variables]]>0,0,1) -> 0 | K65: =Table3[[#This Row],[Joining Date]]+180 -> 45999 | L65: =IF(AND(M65="", K65<=TODAY()), "Claimable", "") | M65: 45998 | N65: =IF(Table3[[#This Row],[6M Stat]]="Claimable",1,0) -> 0 | O65: =Table3[[#This Row],[Joining Date]]+365 -> 46184 | P65: 46245 | Q65: =IF(AND(P65="", O65<=TODAY()), "Claimable", "") | R65: =IF(Table3[[#This Row],[12 M Stat]]="Claimable",1,0) -> 0 | S65: =Table3[[#This Row],[Placement claim Highlight]]+Table3[[#This Row],[Highlight rule 6M]]+Table3[[#This Row],[Highlight rule 12 M]] -> 0 | T65: =SUM(Table3[[#This Row],[Placement Fee]:[Salary]]) -> 55 | V65: =IF(Table1[[#This Row],[MoL]]="Yes",55,0) -> 55 | W65: =IF(Table1[[#This Row],[Long MoL +3 Years]]="Yes",137.5,0) -> 0 | X65: =IF(Table1[[#This Row],[Gender]]="Female",137.5,0) -> 0 | Y65: =IF(Table1[[#This Row],[Education]]="Bachelors +",55,0) -> 0 | Z65: =IF(Table1[[#This Row],[Salary]]>=600,82.5,0) -> 0
A66: =Table1[[#This Row],[SL No.]] -> 65 | B66: =Table1[[#This Row],[Case manager]] -> Dina | C66: =Table1[[#This Row],[Ref No]] -> JCP/24/094062 | D66: =Table1[[#This Row],[Name]] -> sayed ali noordeen ali | E66: ='Placements 26'!F66 -> 46012 | F66: =IF(S66>=1,"Claimable","Claimed") -> Claimed | G66: No | I66: 46127 | J66: =IF(Table3[[#This Row],[Placement Fee & Variables]]>0,0,1) -> 0 | K66: =Table3[[#This Row],[Joining Date]]+180 -> 46192 | L66: =IF(AND(M66="", K66<=TODAY()), "Claimable", "") | M66: 46202 | N66: =IF(Table3[[#This Row],[6M Stat]]="Claimable",1,0) -> 0 | O66: =Table3[[#This Row],[Joining Date]]+365 -> 46377 | Q66: =IF(AND(P66="", O66<=TODAY()), "Claimable", "") | R66: =IF(Table3[[#This Row],[12 M Stat]]="Claimable",1,0) -> 0 | S66: =Table3[[#This Row],[Placement claim Highlight]]+Table3[[#This Row],[Highlight rule 6M]]+Table3[[#This Row],[Highlight rule 12 M]] -> 0 | T66: =SUM(Table3[[#This Row],[Placement Fee]:[Salary]]) -> 275 | V66: =IF(Table1[[#This Row],[MoL]]="Yes",55,0) -> 55 | W66: =IF(Table1[[#This Row],[Long MoL +3 Years]]="Yes",137.5,0) -> 137.5 | X66: =IF(Table1[[#This Row],[Gender]]="Female",137.5,0) -> 0 | Y66: =IF(Table1[[#This Row],[Education]]="Bachelors +",55,0) -> 0 | Z66: =IF(Table1[[#This Row],[Salary]]>=600,82.5,0) -> 82.5
A67: =Table1[[#This Row],[SL No.]] -> 66 | B67: Zainab Mattar | C67: =Table1[[#This Row],[Ref No]] -> JCP/26/283470 | D67: =Table1[[#This Row],[Name]] -> ALI HUSAIN SAEED ABDULWAHAB ALRADHI | E67: ='Placements 26'!F67 -> 46047 | F67: =IF(S67>=1,"Claimable","Claimed") -> Claimable | G67: No | I67: 46127 | J67: =IF(Table3[[#This Row],[Placement Fee & Variables]]>0,0,1) -> 0 | K67: =Table3[[#This Row],[Joining Date]]+180 -> 46227 | L67: =IF(AND(M67="", K67<=TODAY()), "Claimable", "") -> Claimable | N67: =IF(Table3[[#This Row],[6M Stat]]="Claimable",1,0) -> 1 | O67: =Table3[[#This Row],[Joining Date]]+365 -> 46412 | Q67: =IF(AND(P67="", O67<=TODAY()), "Claimable", "") | R67: =IF(Table3[[#This Row],[12 M Stat]]="Claimable",1,0) -> 0 | S67: =Table3[[#This Row],[Placement claim Highlight]]+Table3[[#This Row],[Highlight rule 6M]]+Table3[[#This Row],[Highlight rule 12 M]] -> 1 | T67: =SUM(Table3[[#This Row],[Placement Fee]:[Salary]]) -> 330 | V67: =IF(Table1[[#This Row],[MoL]]="Yes",55,0) -> 55 | W67: =IF(Table1[[#This Row],[Long MoL +3 Years]]="Yes",137.5,0) -> 137.5 | X67: =IF(Table1[[#This Row],[Gender]]="Female",137.5,0) -> 0 | Y67: =IF(Table1[[#This Row],[Education]]="Bachelors +",55,0) -> 55 | Z67: =IF(Table1[[#This Row],[Salary]]>=600,82.5,0) -> 82.5
A68: =Table1[[#This Row],[SL No.]] -> 67 | B68: Zainab Mattar | C68: =Table1[[#This Row],[Ref No]] -> JCP/26/283404 | D68: =Table1[[#This Row],[Name]] -> Kadhem Ahmed Kadhem | E68: ='Placements 26'!F68 -> 46047 | F68: =IF(S68>=1,"Claimable","Claimed") -> Claimable | G68: No | I68: 46127 | J68: =IF(Table3[[#This Row],[Placement Fee & Variables]]>0,0,1) -> 0 | K68: =Table3[[#This Row],[Joining Date]]+180 -> 46227 | L68: =IF(AND(M68="", K68<=TODAY()), "Claimable", "") -> Claimable | N68: =IF(Table3[[#This Row],[6M Stat]]="Claimable",1,0) -> 1 | O68: =Table3[[#This Row],[Joining Date]]+365 -> 46412 | Q68: =IF(AND(P68="", O68<=TODAY()), "Claimable", "") | R68: =IF(Table3[[#This Row],[12 M Stat]]="Claimable",1,0) -> 0 | S68: =Table3[[#This Row],[Placement claim Highlight]]+Table3[[#This Row],[Highlight rule 6M]]+Table3[[#This Row],[Highlight rule 12 M]] -> 1 | T68: =SUM(Table3[[#This Row],[Placement Fee]:[Salary]]) -> 275 | V68: =IF(Table1[[#This Row],[MoL]]="Yes",55,0) -> 55 | W68: =IF(Table1[[#This Row],[Long MoL +3 Years]]="Yes",137.5,0) -> 137.5 | X68: =IF(Table1[[#This Row],[Gender]]="Female",137.5,0) -> 0 | Y68: =IF(Table1[[#This Row],[Education]]="Bachelors +",55,0) -> 0 | Z68: =IF(Table1[[#This Row],[Salary]]>=600,82.5,0) -> 82.5
A69: =Table1[[#This Row],[SL No.]] -> 68 | B69: Malak | C69: =Table1[[#This Row],[Ref No]] -> JCP/26/283447 | D69: =Table1[[#This Row],[Name]] -> ALI ABDULREDHA AHMED KHORRAMI | E69: ='Placements 26'!F69 -> 46047 | F69: =IF(S69>=1,"Claimable","Claimed") -> Claimable | G69: No | I69: 46127 | J69: =IF(Table3[[#This Row],[Placement Fee & Variables]]>0,0,1) -> 0 | K69: =Table3[[#This Row],[Joining Date]]+180 -> 46227 | L69: =IF(AND(M69="", K69<=TODAY()), "Claimable", "") -> Claimable | N69: =IF(Table3[[#This Row],[6M Stat]]="Claimable",1,0) -> 1 | O69: =Table3[[#This Row],[Joining Date]]+365 -> 46412 | Q69: =IF(AND(P69="", O69<=TODAY()), "Claimable", "") | R69: =IF(Table3[[#This Row],[12 M Stat]]="Claimable",1,0) -> 0 | S69: =Table3[[#This Row],[Placement claim Highlight]]+Table3[[#This Row],[Highlight rule 6M]]+Table3[[#This Row],[Highlight rule 12 M]] -> 1 | T69: =SUM(Table3[[#This Row],[Placement Fee]:[Salary]]) -> 330 | V69: =IF(Table1[[#This Row],[MoL]]="Yes",55,0) -> 55 | W69: =IF(Table1[[#This Row],[Long MoL +3 Years]]="Yes",137.5,0) -> 137.5 | X69: =IF(Table1[[#This Row],[Gender]]="Female",137.5,0) -> 0 | Y69: =IF(Table1[[#This Row],[Education]]="Bachelors +",55,0) -> 55 | Z69: =IF(Table1[[#This Row],[Salary]]>=600,82.5,0) -> 82.5
A70: =Table1[[#This Row],[SL No.]] -> 69 | B70: Zainab Mattar | C70: =Table1[[#This Row],[Ref No]] -> JCP/26/283488 | D70: =Table1[[#This Row],[Name]] -> Ali maki Abbas | E70: ='Placements 26'!F70 -> 46047 | F70: =IF(S70>=1,"Claimable","Claimed") -> Claimable | G70: No | I70: 46127 | J70: =IF(Table3[[#This Row],[Placement Fee & Variables]]>0,0,1) -> 0 | K70: =Table3[[#This Row],[Joining Date]]+180 -> 46227 | L70: =IF(AND(M70="", K70<=TODAY()), "Claimable", "") -> Claimable | N70: =IF(Table3[[#This Row],[6M Stat]]="Claimable",1,0) -> 1 | O70: =Table3[[#This Row],[Joining Date]]+365 -> 46412 | Q70: =IF(AND(P70="", O70<=TODAY()), "Claimable", "") | R70: =IF(Table3[[#This Row],[12 M Stat]]="Claimable",1,0) -> 0 | S70: =Table3[[#This Row],[Placement claim Highlight]]+Table3[[#This Row],[Highlight rule 6M]]+Table3[[#This Row],[Highlight rule 12 M]] -> 1 | T70: =SUM(Table3[[#This Row],[Placement Fee]:[Salary]]) -> 137.5 | V70: =IF(Table1[[#This Row],[MoL]]="Yes",55,0) -> 55 | W70: =IF(Table1[[#This Row],[Long MoL +3 Years]]="Yes",137.5,0) -> 0 | X70: =IF(Table1[[#This Row],[Gender]]="Female",137.5,0) -> 0 | Y70: =IF(Table1[[#This Row],[Education]]="Bachelors +",55,0) -> 0 | Z70: =IF(Table1[[#This Row],[Salary]]>=600,82.5,0) -> 82.5
A71: =Table1[[#This Row],[SL No.]] -> 70 | B71: =Table1[[#This Row],[Case manager]] -> Zainab Mattar | C71: =Table1[[#This Row],[Ref No]] -> 26/288849 | D71: =Table1[[#This Row],[Name]] -> FATEMA JASIM AHMED SALEH | E71: ='Placements 26'!F71 -> 46113 | F71: =IF(S71>=1,"Claimable","Claimed") -> Claimable | G71: Yes | H71: Application not approved by Tamkeen | J71: =IF(Table3[[#This Row],[Placement Fee & Variables]]>0,0,1) -> 1 | K71: =Table3[[#This Row],[Joining Date]]+180 -> 46293 | L71: =IF(AND(M71="", K71<=TODAY()), "Claimable", "") -> Claimable | N71: =IF(Table3[[#This Row],[6M Stat]]="Claimable",1,0) -> 1 | O71: =Table3[[#This Row],[Joining Date]]+365 -> 46478 | Q71: =IF(AND(P71="", O71<=TODAY()), "Claimable", "") | R71: =IF(Table3[[#This Row],[12 M Stat]]="Claimable",1,0) -> 0 | S71: =Table3[[#This Row],[Placement claim Highlight]]+Table3[[#This Row],[Highlight rule 6M]]+Table3[[#This Row],[Highlight rule 12 M]] -> 2 | T71: =SUM(Table3[[#This Row],[Placement Fee]:[Salary]]) -> 192.5 | V71: =IF(Table1[[#This Row],[MoL]]="Yes",55,0) -> 0 | W71: =IF(Table1[[#This Row],[Long MoL +3 Years]]="Yes",137.5,0) -> 0 | X71: =IF(Table1[[#This Row],[Gender]]="Female",137.5,0) -> 137.5 | Y71: =IF(Table1[[#This Row],[Education]]="Bachelors +",55,0) -> 55 | Z71: =IF(Table1[[#This Row],[Salary]]>=600,82.5,0) -> 0
A72: =Table1[[#This Row],[SL No.]] -> 71 | B72: =Table1[[#This Row],[Case manager]] -> Meaad | C72: =Table1[[#This Row],[Ref No]] -> 26/289712 | D72: =Table1[[#This Row],[Name]] -> Maryam Abbas Ahmed Ebrahim Abdulla Almeftah | E72: ='Placements 26'!F72 -> 46111 | F72: =IF(S72>=1,"Claimable","Claimed") -> Claimable | G72: Yes | I72: 46133 | J72: =IF(Table3[[#This Row],[Placement Fee & Variables]]>0,0,1) -> 0 | K72: =Table3[[#This Row],[Joining Date]]+180 -> 46291 | L72: =IF(AND(M72="", K72<=TODAY()), "Claimable", "") -> Claimable | N72: =IF(Table3[[#This Row],[6M Stat]]="Claimable",1,0) -> 1 | O72: =Table3[[#This Row],[Joining Date]]+365 -> 46476 | Q72: =IF(AND(P72="", O72<=TODAY()), "Claimable", "") | R72: =IF(Table3[[#This Row],[12 M Stat]]="Claimable",1,0) -> 0 | S72: =Table3[[#This Row],[Placement claim Highlight]]+Table3[[#This Row],[Highlight rule 6M]]+Table3[[#This Row],[Highlight rule 12 M]] -> 1 | T72: =SUM(Table3[[#This Row],[Placement Fee]:[Salary]]) -> 192.5 | V72: =IF(Table1[[#This Row],[MoL]]="Yes",55,0) -> 0 | W72: =IF(Table1[[#This Row],[Long MoL +3 Years]]="Yes",137.5,0) -> 0 | X72: =IF(Table1[[#This Row],[Gender]]="Female",137.5,0) -> 137.5 | Y72: =IF(Table1[[#This Row],[Education]]="Bachelors +",55,0) -> 55 | Z72: =IF(Table1[[#This Row],[Salary]]>=600,82.5,0) -> 0
A73: =Table1[[#This Row],[SL No.]] -> 72 | B73: =Table1[[#This Row],[Case manager]] -> Husain | C73: =Table1[[#This Row],[Ref No]] -> JCP/24/145750 | D73: =Table1[[#This Row],[Name]] -> MOHAMED AHMED ALI AHMED HUSAIN | E73: ='Placements 26'!F73 -> 46106 | F73: =IF(S73>=1,"Claimable","Claimed") -> Claimable | G73: No | I73: 46130 | J73: =IF(Table3[[#This Row],[Placement Fee & Variables]]>0,0,1) -> 0 | K73: =Table3[[#This Row],[Joining Date]]+180 -> 46286 | L73: =IF(AND(M73="", K73<=TODAY()), "Claimable", "") -> Claimable | N73: =IF(Table3[[#This Row],[6M Stat]]="Claimable",1,0) -> 1 | O73: =Table3[[#This Row],[Joining Date]]+365 -> 46471 | Q73: =IF(AND(P73="", O73<=TODAY()), "Claimable", "") | R73: =IF(Table3[[#This Row],[12 M Stat]]="Claimable",1,0) -> 0 | S73: =Table3[[#This Row],[Placement claim Highlight]]+Table3[[#This Row],[Highlight rule 6M]]+Table3[[#This Row],[Highlight rule 12 M]] -> 1 | T73: =SUM(Table3[[#This Row],[Placement Fee]:[Salary]]) -> 55 | V73: =IF(Table1[[#This Row],[MoL]]="Yes",55,0) -> 55 | W73: =IF(Table1[[#This Row],[Long MoL +3 Years]]="Yes",137.5,0) -> 0 | X73: =IF(Table1[[#This Row],[Gender]]="Female",137.5,0) -> 0 | Y73: =IF(Table1[[#This Row],[Education]]="Bachelors +",55,0) -> 0 | Z73: =IF(Table1[[#This Row],[Salary]]>=600,82.5,0) -> 0
A74: =Table1[[#This Row],[SL No.]] -> 73 | B74: =Table1[[#This Row],[Case manager]] -> Zainab Mattar | C74: =Table1[[#This Row],[Ref No]] -> JCP/25/217083 | D74: =Table1[[#This Row],[Name]] -> REEMA ARSALAN JASIM ARAYEDH | E74: ='Placements 26'!F74 -> 46117 | F74: =IF(S74>=1,"Claimable","Claimed") -> Claimable | G74: No | H74: SIO not registered yet | J74: =IF(Table3[[#This Row],[Placement Fee & Variables]]>0,0,1) -> 1 | K74: =Table3[[#This Row],[Joining Date]]+180 -> 46297 | L74: =IF(AND(M74="", K74<=TODAY()), "Claimable", "") -> Claimable | N74: =IF(Table3[[#This Row],[6M Stat]]="Claimable",1,0) -> 1 | O74: =Table3[[#This Row],[Joining Date]]+365 -> 46482 | Q74: =IF(AND(P74="", O74<=TODAY()), "Claimable", "") | R74: =IF(Table3[[#This Row],[12 M Stat]]="Claimable",1,0) -> 0 | S74: =Table3[[#This Row],[Placement claim Highlight]]+Table3[[#This Row],[Highlight rule 6M]]+Table3[[#This Row],[Highlight rule 12 M]] -> 2 | T74: =SUM(Table3[[#This Row],[Placement Fee]:[Salary]]) -> 192.5 | V74: =IF(Table1[[#This Row],[MoL]]="Yes",55,0) -> 0 | W74: =IF(Table1[[#This Row],[Long MoL +3 Years]]="Yes",137.5,0) -> 0 | X74: =IF(Table1[[#This Row],[Gender]]="Female",137.5,0) -> 137.5 | Y74: =IF(Table1[[#This Row],[Education]]="Bachelors +",55,0) -> 55 | Z74: =IF(Table1[[#This Row],[Salary]]>=600,82.5,0) -> 0
A75: =Table1[[#This Row],[SL No.]] -> 74 | B75: =Table1[[#This Row],[Case manager]] -> Husain | C75: =Table1[[#This Row],[Ref No]] -> 24/049470 | D75: =Table1[[#This Row],[Name]] -> HASAN MAHDI NASER ALKHABBAZ | E75: ='Placements 26'!F75 -> 46099 | F75: =IF(S75>=1,"Claimable","Claimed") -> Claimable | G75: Yes | I75: 46130 | J75: =IF(Table3[[#This Row],[Placement Fee & Variables]]>0,0,1) -> 0 | K75: =Table3[[#This Row],[Joining Date]]+180 -> 46279 | L75: =IF(AND(M75="", K75<=TODAY()), "Claimable", "") -> Claimable | N75: =IF(Table3[[#This Row],[6M Stat]]="Claimable",1,0) -> 1 | O75: =Table3[[#This Row],[Joining Date]]+365 -> 46464 | Q75: =IF(AND(P75="", O75<=TODAY()), "Claimable", "") | R75: =IF(Table3[[#This Row],[12 M Stat]]="Claimable",1,0) -> 0 | S75: =Table3[[#This Row],[Placement claim Highlight]]+Table3[[#This Row],[Highlight rule 6M]]+Table3[[#This Row],[Highlight rule 12 M]] -> 1 | T75: =SUM(Table3[[#This Row],[Placement Fee]:[Salary]]) -> 55 | V75: =IF(Table1[[#This Row],[MoL]]="Yes",55,0) -> 55 | W75: =IF(Table1[[#This Row],[Long MoL +3 Years]]="Yes",137.5,0) -> 0 | X75: =IF(Table1[[#This Row],[Gender]]="Female",137.5,0) -> 0 | Y75: =IF(Table1[[#This Row],[Education]]="Bachelors +",55,0) -> 0 | Z75: =IF(Table1[[#This Row],[Salary]]>=600,82.5,0) -> 0
A76: =Table1[[#This Row],[SL No.]] -> 75 | B76: =Table1[[#This Row],[Case manager]] -> Meaad | C76: =Table1[[#This Row],[Ref No]] -> 26/289720 | D76: =Table1[[#This Row],[Name]] -> ALI MAHROOS | E76: ='Placements 26'!F76 -> 46113 | F76: =IF(S76>=1,"Claimable","Claimed") -> Claimable | G76: Yes | I76: 46133 | J76: =IF(Table3[[#This Row],[Placement Fee & Variables]]>0,0,1) -> 0 | K76: =Table3[[#This Row],[Joining Date]]+180 -> 46293 | L76: =IF(AND(M76="", K76<=TODAY()), "Claimable", "") -> Claimable | N76: =IF(Table3[[#This Row],[6M Stat]]="Claimable",1,0) -> 1 | O76: =Table3[[#This Row],[Joining Date]]+365 -> 46478 | Q76: =IF(AND(P76="", O76<=TODAY()), "Claimable", "") | R76: =IF(Table3[[#This Row],[12 M Stat]]="Claimable",1,0) -> 0 | S76: =Table3[[#This Row],[Placement claim Highlight]]+Table3[[#This Row],[Highlight rule 6M]]+Table3[[#This Row],[Highlight rule 12 M]] -> 1 | T76: =SUM(Table3[[#This Row],[Placement Fee]:[Salary]]) -> 0 | V76: =IF(Table1[[#This Row],[MoL]]="Yes",55,0) -> 0 | W76: =IF(Table1[[#This Row],[Long MoL +3 Years]]="Yes",137.5,0) -> 0 | X76: =IF(Table1[[#This Row],[Gender]]="Female",137.5,0) -> 0 | Y76: =IF(Table1[[#This Row],[Education]]="Bachelors +",55,0) -> 0 | Z76: =IF(Table1[[#This Row],[Salary]]>=600,82.5,0) -> 0
A77: =Table1[[#This Row],[SL No.]] -> 76 | B77: =Table1[[#This Row],[Case manager]] -> Meaad | C77: =Table1[[#This Row],[Ref No]] -> 26/288557 | D77: =Table1[[#This Row],[Name]] -> KAWTHAR HUSAIN MAKI A DEKHEEL | E77: ='Placements 26'!F77 -> 46113 | F77: =IF(S77>=1,"Claimable","Claimed") -> Claimable | G77: No | I77: 46140 | J77: =IF(Table3[[#This Row],[Placement Fee & Variables]]>0,0,1) -> 0 | K77: =Table3[[#This Row],[Joining Date]]+180 -> 46293 | L77: =IF(AND(M77="", K77<=TODAY()), "Claimable", "") -> Claimable | N77: =IF(Table3[[#This Row],[6M Stat]]="Claimable",1,0) -> 1 | O77: =Table3[[#This Row],[Joining Date]]+365 -> 46478 | Q77: =IF(AND(P77="", O77<=TODAY()), "Claimable", "") | R77: =IF(Table3[[#This Row],[12 M Stat]]="Claimable",1,0) -> 0 | S77: =Table3[[#This Row],[Placement claim Highlight]]+Table3[[#This Row],[Highlight rule 6M]]+Table3[[#This Row],[Highlight rule 12 M]] -> 1 | T77: =SUM(Table3[[#This Row],[Placement Fee]:[Salary]]) -> 192.5 | V77: =IF(Table1[[#This Row],[MoL]]="Yes",55,0) -> 0 | W77: =IF(Table1[[#This Row],[Long MoL +3 Years]]="Yes",137.5,0) -> 0 | X77: =IF(Table1[[#This Row],[Gender]]="Female",137.5,0) -> 137.5 | Y77: =IF(Table1[[#This Row],[Education]]="Bachelors +",55,0) -> 55 | Z77: =IF(Table1[[#This Row],[Salary]]>=600,82.5,0) -> 0
A78: =Table1[[#This Row],[SL No.]] -> 77 | B78: =Table1[[#This Row],[Case manager]] -> Zainab Almaroom | C78: =Table1[[#This Row],[Ref No]] -> JCP/25/264921 | D78: =Table1[[#This Row],[Name]] -> Maryam Akbar Murad | E78: ='Placements 26'!F78 -> 46104 | F78: =IF(S78>=1,"Claimable","Claimed") -> Claimed | G78: No | I78: 14-3-26 | J78: =IF(Table3[[#This Row],[Placement Fee & Variables]]>0,0,1) -> 0 | K78: =Table3[[#This Row],[Joining Date]]+180 -> 46284 | L78: =IF(AND(M78="", K78<=TODAY()), "Claimable", "") | M78: 14-9-26 | N78: =IF(Table3[[#This Row],[6M Stat]]="Claimable",1,0) -> 0 | O78: =Table3[[#This Row],[Joining Date]]+365 -> 46469 | Q78: =IF(AND(P78="", O78<=TODAY()), "Claimable", "") | R78: =IF(Table3[[#This Row],[12 M Stat]]="Claimable",1,0) -> 0 | S78: =Table3[[#This Row],[Placement claim Highlight]]+Table3[[#This Row],[Highlight rule 6M]]+Table3[[#This Row],[Highlight rule 12 M]] -> 0 | T78: =SUM(Table3[[#This Row],[Placement Fee]:[Salary]]) -> 275 | V78: =IF(Table1[[#This Row],[MoL]]="Yes",55,0) -> 0 | W78: =IF(Table1[[#This Row],[Long MoL +3 Years]]="Yes",137.5,0) -> 0 | X78: =IF(Table1[[#This Row],[Gender]]="Female",137.5,0) -> 137.5 | Y78: =IF(Table1[[#This Row],[Education]]="Bachelors +",55,0) -> 55 | Z78: =IF(Table1[[#This Row],[Salary]]>=600,82.5,0) -> 82.5
A79: =Table1[[#This Row],[SL No.]] -> 78 | B79: Zainab Mattar | C79: =Table1[[#This Row],[Ref No]] -> JCP/25/180026 | D79: =Table1[[#This Row],[Name]] -> Yusuf Ebrahim Yusuf Ahmed Fulad | E79: ='Placements 26'!F79 -> 46061 | F79: =IF(S79>=1,"Claimable","Claimed") -> Claimed | G79: Yes | H79: Application canceled | I79: Application canceled | J79: =IF(Table3[[#This Row],[Placement Fee & Variables]]>0,0,1) -> 0 | K79: =Table3[[#This Row],[Joining Date]]+180 -> 46241 | L79: =IF(AND(M79="", K79<=TODAY()), "Claimable", "") | M79: Application canceled | N79: =IF(Table3[[#This Row],[6M Stat]]="Claimable",1,0) -> 0 | O79: =Table3[[#This Row],[Joining Date]]+365 -> 46426 | P79: Application canceled | Q79: =IF(AND(P79="", O79<=TODAY()), "Claimable", "") | R79: =IF(Table3[[#This Row],[12 M Stat]]="Claimable",1,0) -> 0 | S79: =Table3[[#This Row],[Placement claim Highlight]]+Table3[[#This Row],[Highlight rule 6M]]+Table3[[#This Row],[Highlight rule 12 M]] -> 0 | T79: =SUM(Table3[[#This Row],[Placement Fee]:[Salary]]) -> 0 | V79: =IF(Table1[[#This Row],[MoL]]="Yes",55,0) -> 0 | W79: =IF(Table1[[#This Row],[Long MoL +3 Years]]="Yes",137.5,0) -> 0 | X79: =IF(Table1[[#This Row],[Gender]]="Female",137.5,0) -> 0 | Y79: =IF(Table1[[#This Row],[Education]]="Bachelors +",55,0) -> 0 | Z79: =IF(Table1[[#This Row],[Salary]]>=600,82.5,0) -> 0
A80: =Table1[[#This Row],[SL No.]] -> 79 | B80: =Table1[[#This Row],[Case manager]] -> Dina | C80: =Table1[[#This Row],[Ref No]] -> JCP/26/285439 | D80: =Table1[[#This Row],[Name]] -> Sayed Mohammed ALI Albahraini | E80: ='Placements 26'!F80 -> 46061 | F80: =IF(S80>=1,"Claimable","Claimed") -> Claimed | G80: No | H80: Candidate left | I80: 46127 | J80: =IF(Table3[[#This Row],[Placement Fee & Variables]]>0,0,1) -> 0 | K80: =Table3[[#This Row],[Joining Date]]+180 -> 46241 | L80: =IF(AND(M80="", K80<=TODAY()), "Claimable", "") | M80: Candidate left | N80: =IF(Table3[[#This Row],[6M Stat]]="Claimable",1,0) -> 0 | O80: =Table3[[#This Row],[Joining Date]]+365 -> 46426 | P80: Candidate left | Q80: =IF(AND(P80="", O80<=TODAY()), "Claimable", "") | R80: =IF(Table3[[#This Row],[12 M Stat]]="Claimable",1,0) -> 0 | S80: =Table3[[#This Row],[Placement claim Highlight]]+Table3[[#This Row],[Highlight rule 6M]]+Table3[[#This Row],[Highlight rule 12 M]] -> 0 | T80: =SUM(Table3[[#This Row],[Placement Fee]:[Salary]]) -> 55 | V80: =IF(Table1[[#This Row],[MoL]]="Yes",55,0) -> 55 | W80: =IF(Table1[[#This Row],[Long MoL +3 Years]]="Yes",137.5,0) -> 0 | X80: =IF(Table1[[#This Row],[Gender]]="Female",137.5,0) -> 0 | Y80: =IF(Table1[[#This Row],[Education]]="Bachelors +",55,0) -> 0 | Z80: =IF(Table1[[#This Row],[Salary]]>=600,82.5,0) -> 0
A81: =Table1[[#This Row],[SL No.]] -> 80 | B81: =Table1[[#This Row],[Case manager]] -> Dina | C81: =Table1[[#This Row],[Ref No]] -> JCP/24/145581 | D81: =Table1[[#This Row],[Name]] -> JASIM MOHAMED SALEH SALEH | E81: ='Placements 26'!F81 -> 46054 | F81: =IF(S81>=1,"Claimable","Claimed") -> Claimable | G81: Yes | H81: not able to claim as joining date after approval date | J81: =IF(Table3[[#This Row],[Placement Fee & Variables]]>0,0,1) -> 1 | K81: =Table3[[#This Row],[Joining Date]]+180 -> 46234 | L81: =IF(AND(M81="", K81<=TODAY()), "Claimable", "") -> Claimable | N81: =IF(Table3[[#This Row],[6M Stat]]="Claimable",1,0) -> 1 | O81: =Table3[[#This Row],[Joining Date]]+365 -> 46419 | Q81: =IF(AND(P81="", O81<=TODAY()), "Claimable", "") | R81: =IF(Table3[[#This Row],[12 M Stat]]="Claimable",1,0) -> 0 | S81: =Table3[[#This Row],[Placement claim Highlight]]+Table3[[#This Row],[Highlight rule 6M]]+Table3[[#This Row],[Highlight rule 12 M]] -> 2 | T81: =SUM(Table3[[#This Row],[Placement Fee]:[Salary]]) -> 0 | V81: =IF(Table1[[#This Row],[MoL]]="Yes",55,0) -> 0 | W81: =IF(Table1[[#This Row],[Long MoL +3 Years]]="Yes",137.5,0) -> 0 | X81: =IF(Table1[[#This Row],[Gender]]="Female",137.5,0) -> 0 | Y81: =IF(Table1[[#This Row],[Education]]="Bachelors +",55,0) -> 0 | Z81: =IF(Table1[[#This Row],[Salary]]>=600,82.5,0) -> 0
A82: =Table1[[#This Row],[SL No.]] -> 81 | B82: =Table1[[#This Row],[Case manager]] -> Dina | C82: =Table1[[#This Row],[Ref No]] -> JCP/25/223037 | D82: =Table1[[#This Row],[Name]] -> JAAFAR KADHEM HUSAIN HABIB KADHEM ALJABOORI | E82: ='Placements 26'!F82 -> 46061 | F82: =IF(S82>=1,"Claimable","Claimed") -> Claimable | G82: No | H82: Candidate left | I82: 46160 | J82: =IF(Table3[[#This Row],[Placement Fee & Variables]]>0,0,1) -> 0 | K82: =Table3[[#This Row],[Joining Date]]+180 -> 46241 | L82: =IF(AND(M82="", K82<=TODAY()), "Claimable", "") -> Claimable | N82: =IF(Table3[[#This Row],[6M Stat]]="Claimable",1,0) -> 1 | O82: =Table3[[#This Row],[Joining Date]]+365 -> 46426 | Q82: =IF(AND(P82="", O82<=TODAY()), "Claimable", "") | R82: =IF(Table3[[#This Row],[12 M Stat]]="Claimable",1,0) -> 0 | S82: =Table3[[#This Row],[Placement claim Highlight]]+Table3[[#This Row],[Highlight rule 6M]]+Table3[[#This Row],[Highlight rule 12 M]] -> 1 | T82: =SUM(Table3[[#This Row],[Placement Fee]:[Salary]]) -> 55 | V82: =IF(Table1[[#This Row],[MoL]]="Yes",55,0) -> 55 | W82: =IF(Table1[[#This Row],[Long MoL +3 Years]]="Yes",137.5,0) -> 0 | X82: =IF(Table1[[#This Row],[Gender]]="Female",137.5,0) -> 0 | Y82: =IF(Table1[[#This Row],[Education]]="Bachelors +",55,0) -> 0 | Z82: =IF(Table1[[#This Row],[Salary]]>=600,82.5,0) -> 0
A83: =Table1[[#This Row],[SL No.]] -> 82 | B83: =Table1[[#This Row],[Case manager]] -> Malak | C83: =Table1[[#This Row],[Ref No]] -> JCP/26/286008 | D83: =Table1[[#This Row],[Name]] -> Husain Hasan Ali | E83: ='Placements 26'!F83 -> 46068 | F83: =IF(S83>=1,"Claimable","Claimed") -> Claimable | G83: Yes | H83: need to be transfered to our center | J83: =IF(Table3[[#This Row],[Placement Fee & Variables]]>0,0,1) -> 1 | K83: =Table3[[#This Row],[Joining Date]]+180 -> 46248 | L83: =IF(AND(M83="", K83<=TODAY()), "Claimable", "") -> Claimable | N83: =IF(Table3[[#This Row],[6M Stat]]="Claimable",1,0) -> 1 | O83: =Table3[[#This Row],[Joining Date]]+365 -> 46433 | Q83: =IF(AND(P83="", O83<=TODAY()), "Claimable", "") | R83: =IF(Table3[[#This Row],[12 M Stat]]="Claimable",1,0) -> 0 | S83: =Table3[[#This Row],[Placement claim Highlight]]+Table3[[#This Row],[Highlight rule 6M]]+Table3[[#This Row],[Highlight rule 12 M]] -> 2 | T83: =SUM(Table3[[#This Row],[Placement Fee]:[Salary]]) -> 0 | V83: =IF(Table1[[#This Row],[MoL]]="Yes",55,0) -> 0 | W83: =IF(Table1[[#This Row],[Long MoL +3 Years]]="Yes",137.5,0) -> 0 | X83: =IF(Table1[[#This Row],[Gender]]="Female",137.5,0) -> 0 | Y83: =IF(Table1[[#This Row],[Education]]="Bachelors +",55,0) -> 0 | Z83: =IF(Table1[[#This Row],[Salary]]>=600,82.5,0) -> 0
A84: =Table1[[#This Row],[SL No.]] -> 83 | B84: Zainab Mattar | C84: =Table1[[#This Row],[Ref No]] -> JCP/26/283442 | D84: =Table1[[#This Row],[Name]] -> HUSAIN EBRAHIM JASIM EBRAHIM | E84: ='Placements 26'!F84 -> 46068 | F84: =IF(S84>=1,"Claimable","Claimed") -> Claimable | G84: No | I84: 46127 | J84: =IF(Table3[[#This Row],[Placement Fee & Variables]]>0,0,1) -> 0 | K84: =Table3[[#This Row],[Joining Date]]+180 -> 46248 | L84: =IF(AND(M84="", K84<=TODAY()), "Claimable", "") -> Claimable | N84: =IF(Table3[[#This Row],[6M Stat]]="Claimable",1,0) -> 1 | O84: =Table3[[#This Row],[Joining Date]]+365 -> 46433 | Q84: =IF(AND(P84="", O84<=TODAY()), "Claimable", "") | R84: =IF(Table3[[#This Row],[12 M Stat]]="Claimable",1,0) -> 0 | S84: =Table3[[#This Row],[Placement claim Highlight]]+Table3[[#This Row],[Highlight rule 6M]]+Table3[[#This Row],[Highlight rule 12 M]] -> 1 | T84: =SUM(Table3[[#This Row],[Placement Fee]:[Salary]]) -> 0 | V84: =IF(Table1[[#This Row],[MoL]]="Yes",55,0) -> 0 | W84: =IF(Table1[[#This Row],[Long MoL +3 Years]]="Yes",137.5,0) -> 0 | X84: =IF(Table1[[#This Row],[Gender]]="Female",137.5,0) -> 0 | Y84: =IF(Table1[[#This Row],[Education]]="Bachelors +",55,0) -> 0 | Z84: =IF(Table1[[#This Row],[Salary]]>=600,82.5,0) -> 0
A85: =Table1[[#This Row],[SL No.]] -> 84 | B85: Zainab Mattar | C85: =Table1[[#This Row],[Ref No]] -> JCP/25/263373 | D85: =Table1[[#This Row],[Name]] -> hasan husain ebrahim | E85: ='Placements 26'!F85 -> 46075 | F85: =IF(S85>=1,"Claimable","Claimed") -> Claimable | G85: No | I85: 46160 | J85: =IF(Table3[[#This Row],[Placement Fee & Variables]]>0,0,1) -> 0 | K85: =Table3[[#This Row],[Joining Date]]+180 -> 46255 | L85: =IF(AND(M85="", K85<=TODAY()), "Claimable", "") -> Claimable | N85: =IF(Table3[[#This Row],[6M Stat]]="Claimable",1,0) -> 1 | O85: =Table3[[#This Row],[Joining Date]]+365 -> 46440 | Q85: =IF(AND(P85="", O85<=TODAY()), "Claimable", "") | R85: =IF(Table3[[#This Row],[12 M Stat]]="Claimable",1,0) -> 0 | S85: =Table3[[#This Row],[Placement claim Highlight]]+Table3[[#This Row],[Highlight rule 6M]]+Table3[[#This Row],[Highlight rule 12 M]] -> 1 | T85: =SUM(Table3[[#This Row],[Placement Fee]:[Salary]]) -> 0 | V85: =IF(Table1[[#This Row],[MoL]]="Yes",55,0) -> 0 | W85: =IF(Table1[[#This Row],[Long MoL +3 Years]]="Yes",137.5,0) -> 0 | X85: =IF(Table1[[#This Row],[Gender]]="Female",137.5,0) -> 0 | Y85: =IF(Table1[[#This Row],[Education]]="Bachelors +",55,0) -> 0 | Z85: =IF(Table1[[#This Row],[Salary]]>=600,82.5,0) -> 0
A86: =Table1[[#This Row],[SL No.]] -> 85 | B86: Zainab Mattar | C86: =Table1[[#This Row],[Ref No]] -> JCP/26/285998 | D86: =Table1[[#This Row],[Name]] -> HASAN ABDULZAHRA ASHO DHABAAN | E86: ='Placements 26'!F86 -> 46068 | F86: =IF(S86>=1,"Claimable","Claimed") -> Claimable | G86: No | I86: 46160 | J86: =IF(Table3[[#This Row],[Placement Fee & Variables]]>0,0,1) -> 0 | K86: =Table3[[#This Row],[Joining Date]]+180 -> 46248 | L86: =IF(AND(M86="", K86<=TODAY()), "Claimable", "") -> Claimable | N86: =IF(Table3[[#This Row],[6M Stat]]="Claimable",1,0) -> 1 | O86: =Table3[[#This Row],[Joining Date]]+365 -> 46433 | Q86: =IF(AND(P86="", O86<=TODAY()), "Claimable", "") | R86: =IF(Table3[[#This Row],[12 M Stat]]="Claimable",1,0) -> 0 | S86: =Table3[[#This Row],[Placement claim Highlight]]+Table3[[#This Row],[Highlight rule 6M]]+Table3[[#This Row],[Highlight rule 12 M]] -> 1 | T86: =SUM(Table3[[#This Row],[Placement Fee]:[Salary]]) -> 0 | V86: =IF(Table1[[#This Row],[MoL]]="Yes",55,0) -> 0 | W86: =IF(Table1[[#This Row],[Long MoL +3 Years]]="Yes",137.5,0) -> 0 | X86: =IF(Table1[[#This Row],[Gender]]="Female",137.5,0) -> 0 | Y86: =IF(Table1[[#This Row],[Education]]="Bachelors +",55,0) -> 0 | Z86: =IF(Table1[[#This Row],[Salary]]>=600,82.5,0) -> 0
A87: =Table1[[#This Row],[SL No.]] -> 86 | B87: =Table1[[#This Row],[Case manager]] -> Dina | C87: =Table1[[#This Row],[Ref No]] -> JCP/25/264214 | D87: =Table1[[#This Row],[Name]] -> FOZAN KHAN MANZOOR Ali MUZAFFAR | E87: ='Placements 26'!F87 -> 46068 | F87: =IF(S87>=1,"Claimable","Claimed") -> Claimable | G87: No | I87: 46160 | J87: =IF(Table3[[#This Row],[Placement Fee & Variables]]>0,0,1) -> 0 | K87: =Table3[[#This Row],[Joining Date]]+180 -> 46248 | L87: =IF(AND(M87="", K87<=TODAY()), "Claimable", "") -> Claimable | N87: =IF(Table3[[#This Row],[6M Stat]]="Claimable",1,0) -> 1 | O87: =Table3[[#This Row],[Joining Date]]+365 -> 46433 | Q87: =IF(AND(P87="", O87<=TODAY()), "Claimable", "") | R87: =IF(Table3[[#This Row],[12 M Stat]]="Claimable",1,0) -> 0 | S87: =Table3[[#This Row],[Placement claim Highlight]]+Table3[[#This Row],[Highlight rule 6M]]+Table3[[#This Row],[Highlight rule 12 M]] -> 1 | T87: =SUM(Table3[[#This Row],[Placement Fee]:[Salary]]) -> 82.5 | V87: =IF(Table1[[#This Row],[MoL]]="Yes",55,0) -> 0 | W87: =IF(Table1[[#This Row],[Long MoL +3 Years]]="Yes",137.5,0) -> 0 | X87: =IF(Table1[[#This Row],[Gender]]="Female",137.5,0) -> 0 | Y87: =IF(Table1[[#This Row],[Education]]="Bachelors +",55,0) -> 0 | Z87: =IF(Table1[[#This Row],[Salary]]>=600,82.5,0) -> 82.5
A88: =Table1[[#This Row],[SL No.]] -> 87 | B88: Zainab Mattar | C88: =Table1[[#This Row],[Ref No]] -> JCP/25/190581 | D88: =Table1[[#This Row],[Name]] -> faisal ahmed ahmed shah gul salam hashmi | E88: ='Placements 26'!F88 -> 46054 | F88: =IF(S88>=1,"Claimable","Claimed") -> Claimable | G88: No | I88: 46128 | J88: =IF(Table3[[#This Row],[Placement Fee & Variables]]>0,0,1) -> 0 | K88: =Table3[[#This Row],[Joining Date]]+180 -> 46234 | L88: =IF(AND(M88="", K88<=TODAY()), "Claimable", "") -> Claimable | N88: =IF(Table3[[#This Row],[6M Stat]]="Claimable",1,0) -> 1 | O88: =Table3[[#This Row],[Joining Date]]+365 -> 46419 | Q88: =IF(AND(P88="", O88<=TODAY()), "Claimable", "") | R88: =IF(Table3[[#This Row],[12 M Stat]]="Claimable",1,0) -> 0 | S88: =Table3[[#This Row],[Placement claim Highlight]]+Table3[[#This Row],[Highlight rule 6M]]+Table3[[#This Row],[Highlight rule 12 M]] -> 1 | T88: =SUM(Table3[[#This Row],[Placement Fee]:[Salary]]) -> 247.5 | V88: =IF(Table1[[#This Row],[MoL]]="Yes",55,0) -> 55 | W88: =IF(Table1[[#This Row],[Long MoL +3 Years]]="Yes",137.5,0) -> 137.5 | X88: =IF(Table1[[#This Row],[Gender]]="Female",137.5,0) -> 0 | Y88: =IF(Table1[[#This Row],[Education]]="Bachelors +",55,0) -> 55 | Z88: =IF(Table1[[#This Row],[Salary]]>=600,82.5,0) -> 0
A89: =Table1[[#This Row],[SL No.]] -> 88 | B89: =Table1[[#This Row],[Case manager]] -> Dina | C89: =Table1[[#This Row],[Ref No]] -> JCP/25/198356 | D89: =Table1[[#This Row],[Name]] -> Faisal Ghulam Mohd | E89: ='Placements 26'!F89 -> 46098 | F89: =IF(S89>=1,"Claimable","Claimed") -> Claimable | G89: Yes | H89: not able to claim as joining date after approval date | J89: =IF(Table3[[#This Row],[Placement Fee & Variables]]>0,0,1) -> 1 | K89: =Table3[[#This Row],[Joining Date]]+180 -> 46278 | L89: =IF(AND(M89="", K89<=TODAY()), "Claimable", "") -> Claimable | N89: =IF(Table3[[#This Row],[6M Stat]]="Claimable",1,0) -> 1 | O89: =Table3[[#This Row],[Joining Date]]+365 -> 46463 | Q89: =IF(AND(P89="", O89<=TODAY()), "Claimable", "") | R89: =IF(Table3[[#This Row],[12 M Stat]]="Claimable",1,0) -> 0 | S89: =Table3[[#This Row],[Placement claim Highlight]]+Table3[[#This Row],[Highlight rule 6M]]+Table3[[#This Row],[Highlight rule 12 M]] -> 2 | T89: =SUM(Table3[[#This Row],[Placement Fee]:[Salary]]) -> 0 | V89: =IF(Table1[[#This Row],[MoL]]="Yes",55,0) -> 0 | W89: =IF(Table1[[#This Row],[Long MoL +3 Years]]="Yes",137.5,0) -> 0 | X89: =IF(Table1[[#This Row],[Gender]]="Female",137.5,0) -> 0 | Y89: =IF(Table1[[#This Row],[Education]]="Bachelors +",55,0) -> 0 | Z89: =IF(Table1[[#This Row],[Salary]]>=600,82.5,0) -> 0
A90: =Table1[[#This Row],[SL No.]] -> 89 | B90: =Table1[[#This Row],[Case manager]] -> Malak | C90: =Table1[[#This Row],[Ref No]] -> JCP/25/167732 | D90: =Table1[[#This Row],[Name]] -> BASEL SHAKER ALI MANSOOR ALI | E90: ='Placements 26'!F90 -> 46061 | F90: =IF(S90>=1,"Claimable","Claimed") -> Claimable | G90: No | I90: 46153 | J90: =IF(Table3[[#This Row],[Placement Fee & Variables]]>0,0,1) -> 0 | K90: =Table3[[#This Row],[Joining Date]]+180 -> 46241 | L90: =IF(AND(M90="", K90<=TODAY()), "Claimable", "") -> Claimable | N90: =IF(Table3[[#This Row],[6M Stat]]="Claimable",1,0) -> 1 | O90: =Table3[[#This Row],[Joining Date]]+365 -> 46426 | Q90: =IF(AND(P90="", O90<=TODAY()), "Claimable", "") | R90: =IF(Table3[[#This Row],[12 M Stat]]="Claimable",1,0) -> 0 | S90: =Table3[[#This Row],[Placement claim Highlight]]+Table3[[#This Row],[Highlight rule 6M]]+Table3[[#This Row],[Highlight rule 12 M]] -> 1 | T90: =SUM(Table3[[#This Row],[Placement Fee]:[Salary]]) -> 0 | V90: =IF(Table1[[#This Row],[MoL]]="Yes",55,0) -> 0 | W90: =IF(Table1[[#This Row],[Long MoL +3 Years]]="Yes",137.5,0) -> 0 | X90: =IF(Table1[[#This Row],[Gender]]="Female",137.5,0) -> 0 | Y90: =IF(Table1[[#This Row],[Education]]="Bachelors +",55,0) -> 0 | Z90: =IF(Table1[[#This Row],[Salary]]>=600,82.5,0) -> 0
A91: =Table1[[#This Row],[SL No.]] -> 90 | B91: =Table1[[#This Row],[Case manager]] -> Meaad | C91: =Table1[[#This Row],[Ref No]] -> 26/270825 | D91: =Table1[[#This Row],[Name]] -> Ali Mohsin Abdali | E91: ='Placements 26'!F91 -> 46061 | F91: =IF(S91>=1,"Claimable","Claimed") -> Claimable | G91: Yes | H91: Application pending individual | J91: =IF(Table3[[#This Row],[Placement Fee & Variables]]>0,0,1) -> 1 | K91: =Table3[[#This Row],[Joining Date]]+180 -> 46241 | L91: =IF(AND(M91="", K91<=TODAY()), "Claimable", "") -> Claimable | N91: =IF(Table3[[#This Row],[6M Stat]]="Claimable",1,0) -> 1 | O91: =Table3[[#This Row],[Joining Date]]+365 -> 46426 | Q91: =IF(AND(P91="", O91<=TODAY()), "Claimable", "") | R91: =IF(Table3[[#This Row],[12 M Stat]]="Claimable",1,0) -> 0 | S91: =Table3[[#This Row],[Placement claim Highlight]]+Table3[[#This Row],[Highlight rule 6M]]+Table3[[#This Row],[Highlight rule 12 M]] -> 2 | T91: =SUM(Table3[[#This Row],[Placement Fee]:[Salary]]) -> 0 | V91: =IF(Table1[[#This Row],[MoL]]="Yes",55,0) -> 0 | W91: =IF(Table1[[#This Row],[Long MoL +3 Years]]="Yes",137.5,0) -> 0 | X91: =IF(Table1[[#This Row],[Gender]]="Female",137.5,0) -> 0 | Y91: =IF(Table1[[#This Row],[Education]]="Bachelors +",55,0) -> 0 | Z91: =IF(Table1[[#This Row],[Salary]]>=600,82.5,0) -> 0
A92: =Table1[[#This Row],[SL No.]] -> 91 | B92: =Table1[[#This Row],[Case manager]] -> Dina | C92: =Table1[[#This Row],[Ref No]] -> JCP/26/285421 | D92: =Table1[[#This Row],[Name]] -> ali abbas abdali | E92: ='Placements 26'!F92 -> 46061 | F92: =IF(S92>=1,"Claimable","Claimed") -> Claimable | G92: No | H92: candidate left | I92: 46128 | J92: =IF(Table3[[#This Row],[Placement Fee & Variables]]>0,0,1) -> 0 | K92: =Table3[[#This Row],[Joining Date]]+180 -> 46241 | L92: =IF(AND(M92="", K92<=TODAY()), "Claimable", "") -> Claimable | N92: =IF(Table3[[#This Row],[6M Stat]]="Claimable",1,0) -> 1 | O92: =Table3[[#This Row],[Joining Date]]+365 -> 46426 | Q92: =IF(AND(P92="", O92<=TODAY()), "Claimable", "") | R92: =IF(Table3[[#This Row],[12 M Stat]]="Claimable",1,0) -> 0 | S92: =Table3[[#This Row],[Placement claim Highlight]]+Table3[[#This Row],[Highlight rule 6M]]+Table3[[#This Row],[Highlight rule 12 M]] -> 1 | T92: =SUM(Table3[[#This Row],[Placement Fee]:[Salary]]) -> 0 | V92: =IF(Table1[[#This Row],[MoL]]="Yes",55,0) -> 0 | W92: =IF(Table1[[#This Row],[Long MoL +3 Years]]="Yes",137.5,0) -> 0 | X92: =IF(Table1[[#This Row],[Gender]]="Female",137.5,0) -> 0 | Y92: =IF(Table1[[#This Row],[Education]]="Bachelors +",55,0) -> 0 | Z92: =IF(Table1[[#This Row],[Salary]]>=600,82.5,0) -> 0
A93: =Table1[[#This Row],[SL No.]] -> 92 | B93: =Table1[[#This Row],[Case manager]] -> Malak | C93: =Table1[[#This Row],[Ref No]] -> JCP/25/261707 | D93: =Table1[[#This Row],[Name]] -> Abdulla Hussain Abdulla | E93: ='Placements 26'!F93 -> 46061 | F93: =IF(S93>=1,"Claimable","Claimed") -> Claimable | G93: No | I93: 46128 | J93: =IF(Table3[[#This Row],[Placement Fee & Variables]]>0,0,1) -> 0 | K93: =Table3[[#This Row],[Joining Date]]+180 -> 46241 | L93: =IF(AND(M93="", K93<=TODAY()), "Claimable", "") -> Claimable | N93: =IF(Table3[[#This Row],[6M Stat]]="Claimable",1,0) -> 1 | O93: =Table3[[#This Row],[Joining Date]]+365 -> 46426 | Q93: =IF(AND(P93="", O93<=TODAY()), "Claimable", "") | R93: =IF(Table3[[#This Row],[12 M Stat]]="Claimable",1,0) -> 0 | S93: =Table3[[#This Row],[Placement claim Highlight]]+Table3[[#This Row],[Highlight rule 6M]]+Table3[[#This Row],[Highlight rule 12 M]] -> 1 | T93: =SUM(Table3[[#This Row],[Placement Fee]:[Salary]]) -> 0 | V93: =IF(Table1[[#This Row],[MoL]]="Yes",55,0) -> 0 | W93: =IF(Table1[[#This Row],[Long MoL +3 Years]]="Yes",137.5,0) -> 0 | X93: =IF(Table1[[#This Row],[Gender]]="Female",137.5,0) -> 0 | Y93: =IF(Table1[[#This Row],[Education]]="Bachelors +",55,0) -> 0 | Z93: =IF(Table1[[#This Row],[Salary]]>=600,82.5,0) -> 0
A94: =Table1[[#This Row],[SL No.]] -> 93 | B94: =Table1[[#This Row],[Case manager]] -> Dina | C94: =Table1[[#This Row],[Ref No]] -> 26/283501 | D94: =Table1[[#This Row],[Name]] -> AAMER ALI HASAN ALMUTAWA | E94: ='Placements 26'!F94 -> 46078 | F94: =IF(S94>=1,"Claimable","Claimed") -> Claimable | G94: No | H94: candidate left | I94: 46159 | J94: =IF(Table3[[#This Row],[Placement Fee & Variables]]>0,0,1) -> 0 | K94: =Table3[[#This Row],[Joining Date]]+180 -> 46258 | L94: =IF(AND(M94="", K94<=TODAY()), "Claimable", "") -> Claimable | N94: =IF(Table3[[#This Row],[6M Stat]]="Claimable",1,0) -> 1 | O94: =Table3[[#This Row],[Joining Date]]+365 -> 46443 | Q94: =IF(AND(P94="", O94<=TODAY()), "Claimable", "") | R94: =IF(Table3[[#This Row],[12 M Stat]]="Claimable",1,0) -> 0 | S94: =Table3[[#This Row],[Placement claim Highlight]]+Table3[[#This Row],[Highlight rule 6M]]+Table3[[#This Row],[Highlight rule 12 M]] -> 1 | T94: =SUM(Table3[[#This Row],[Placement Fee]:[Salary]]) -> 82.5 | V94: =IF(Table1[[#This Row],[MoL]]="Yes",55,0) -> 0 | W94: =IF(Table1[[#This Row],[Long MoL +3 Years]]="Yes",137.5,0) -> 0 | X94: =IF(Table1[[#This Row],[Gender]]="Female",137.5,0) -> 0 | Y94: =IF(Table1[[#This Row],[Education]]="Bachelors +",55,0) -> 0 | Z94: =IF(Table1[[#This Row],[Salary]]>=600,82.5,0) -> 82.5
A95: =Table1[[#This Row],[SL No.]] -> 94 | B95: =Table1[[#This Row],[Case manager]] -> Malak | C95: =Table1[[#This Row],[Ref No]] -> JCP/26/283428 | D95: =Table1[[#This Row],[Name]] -> mohammed ashoor hasan | E95: ='Placements 26'!F95 -> 46068 | F95: =IF(S95>=1,"Claimable","Claimed") -> Claimable | G95: No | I95: 46128 | J95: =IF(Table3[[#This Row],[Placement Fee & Variables]]>0,0,1) -> 0 | K95: =Table3[[#This Row],[Joining Date]]+180 -> 46248 | L95: =IF(AND(M95="", K95<=TODAY()), "Claimable", "") -> Claimable | N95: =IF(Table3[[#This Row],[6M Stat]]="Claimable",1,0) -> 1 | O95: =Table3[[#This Row],[Joining Date]]+365 -> 46433 | Q95: =IF(AND(P95="", O95<=TODAY()), "Claimable", "") | R95: =IF(Table3[[#This Row],[12 M Stat]]="Claimable",1,0) -> 0 | S95: =Table3[[#This Row],[Placement claim Highlight]]+Table3[[#This Row],[Highlight rule 6M]]+Table3[[#This Row],[Highlight rule 12 M]] -> 1 | T95: =SUM(Table3[[#This Row],[Placement Fee]:[Salary]]) -> 192.5 | V95: =IF(Table1[[#This Row],[MoL]]="Yes",55,0) -> 55 | W95: =IF(Table1[[#This Row],[Long MoL +3 Years]]="Yes",137.5,0) -> 137.5 | X95: =IF(Table1[[#This Row],[Gender]]="Female",137.5,0) -> 0 | Y95: =IF(Table1[[#This Row],[Education]]="Bachelors +",55,0) -> 0 | Z95: =IF(Table1[[#This Row],[Salary]]>=600,82.5,0) -> 0
A96: =Table1[[#This Row],[SL No.]] -> 95 | B96: =Table1[[#This Row],[Case manager]] -> Dina | C96: =Table1[[#This Row],[Ref No]] -> JCP/26/286399 | D96: =Table1[[#This Row],[Name]] -> HASAN JAAFAR MOHAMED ALAALI | E96: ='Placements 26'!F96 -> 46070 | F96: =IF(S96>=1,"Claimable","Claimed") -> Claimable | G96: No | I96: 46128 | J96: =IF(Table3[[#This Row],[Placement Fee & Variables]]>0,0,1) -> 0 | K96: =Table3[[#This Row],[Joining Date]]+180 -> 46250 | L96: =IF(AND(M96="", K96<=TODAY()), "Claimable", "") -> Claimable | N96: =IF(Table3[[#This Row],[6M Stat]]="Claimable",1,0) -> 1 | O96: =Table3[[#This Row],[Joining Date]]+365 -> 46435 | Q96: =IF(AND(P96="", O96<=TODAY()), "Claimable", "") | R96: =IF(Table3[[#This Row],[12 M Stat]]="Claimable",1,0) -> 0 | S96: =Table3[[#This Row],[Placement claim Highlight]]+Table3[[#This Row],[Highlight rule 6M]]+Table3[[#This Row],[Highlight rule 12 M]] -> 1 | T96: =SUM(Table3[[#This Row],[Placement Fee]:[Salary]]) -> 192.5 | V96: =IF(Table1[[#This Row],[MoL]]="Yes",55,0) -> 55 | W96: =IF(Table1[[#This Row],[Long MoL +3 Years]]="Yes",137.5,0) -> 137.5 | X96: =IF(Table1[[#This Row],[Gender]]="Female",137.5,0) -> 0 | Y96: =IF(Table1[[#This Row],[Education]]="Bachelors +",55,0) -> 0 | Z96: =IF(Table1[[#This Row],[Salary]]>=600,82.5,0) -> 0
A97: =Table1[[#This Row],[SL No.]] -> 96 | B97: =Table1[[#This Row],[Case manager]] -> Meaad | C97: =Table1[[#This Row],[Ref No]] -> JCP/26/285972 | D97: =Table1[[#This Row],[Name]] -> ali hassan abdulla | E97: ='Placements 26'!F97 -> 46124 | F97: =IF(S97>=1,"Claimable","Claimed") -> Claimable | G97: Yes | I97: 46140 | J97: =IF(Table3[[#This Row],[Placement Fee & Variables]]>0,0,1) -> 0 | K97: =Table3[[#This Row],[Joining Date]]+180 -> 46304 | L97: =IF(AND(M97="", K97<=TODAY()), "Claimable", "") -> Claimable | N97: =IF(Table3[[#This Row],[6M Stat]]="Claimable",1,0) -> 1 | O97: =Table3[[#This Row],[Joining Date]]+365 -> 46489 | Q97: =IF(AND(P97="", O97<=TODAY()), "Claimable", "") | R97: =IF(Table3[[#This Row],[12 M Stat]]="Claimable",1,0) -> 0 | S97: =Table3[[#This Row],[Placement claim Highlight]]+Table3[[#This Row],[Highlight rule 6M]]+Table3[[#This Row],[Highlight rule 12 M]] -> 1 | T97: =SUM(Table3[[#This Row],[Placement Fee]:[Salary]]) -> 0 | V97: =IF(Table1[[#This Row],[MoL]]="Yes",55,0) -> 0 | W97: =IF(Table1[[#This Row],[Long MoL +3 Years]]="Yes",137.5,0) -> 0 | X97: =IF(Table1[[#This Row],[Gender]]="Female",137.5,0) -> 0 | Y97: =IF(Table1[[#This Row],[Education]]="Bachelors +",55,0) -> 0 | Z97: =IF(Table1[[#This Row],[Salary]]>=600,82.5,0) -> 0
A98: =Table1[[#This Row],[SL No.]] -> 97 | B98: =Table1[[#This Row],[Case manager]] -> Husain | C98: =Table1[[#This Row],[Ref No]] -> JCP/24/142442 | D98: =Table1[[#This Row],[Name]] -> SAYED ALAA MOOSA MOHAMED FADHEL | E98: ='Placements 26'!F98 -> 45931 | F98: =IF(S98>=1,"Claimable","Claimed") -> Claimable | J98: =IF(Table3[[#This Row],[Placement Fee & Variables]]>0,0,1) -> 1 | K98: =Table3[[#This Row],[Joining Date]]+180 -> 46111 | L98: =IF(AND(M98="", K98<=TODAY()), "Claimable", "") -> Claimable | N98: =IF(Table3[[#This Row],[6M Stat]]="Claimable",1,0) -> 1 | O98: =Table3[[#This Row],[Joining Date]]+365 -> 46296 | Q98: =IF(AND(P98="", O98<=TODAY()), "Claimable", "") -> Claimable | R98: =IF(Table3[[#This Row],[12 M Stat]]="Claimable",1,0) -> 1 | S98: =Table3[[#This Row],[Placement claim Highlight]]+Table3[[#This Row],[Highlight rule 6M]]+Table3[[#This Row],[Highlight rule 12 M]] -> 3 | T98: =SUM(Table3[[#This Row],[Placement Fee]:[Salary]]) -> 55 | V98: =IF(Table1[[#This Row],[MoL]]="Yes",55,0) -> 0 | W98: =IF(Table1[[#This Row],[Long MoL +3 Years]]="Yes",137.5,0) -> 0 | X98: =IF(Table1[[#This Row],[Gender]]="Female",137.5,0) -> 0 | Y98: =IF(Table1[[#This Row],[Education]]="Bachelors +",55,0) -> 55 | Z98: =IF(Table1[[#This Row],[Salary]]>=600,82.5,0) -> 0
A99: =Table1[[#This Row],[SL No.]] -> 98 | B99: =Table1[[#This Row],[Case manager]] -> Husain | C99: =Table1[[#This Row],[Ref No]] -> JCP/25/233173 | D99: =Table1[[#This Row],[Name]] -> KHALIFA EBRAHIM K. SAAD | E99: ='Placements 26'!F99 -> 45935 | F99: =IF(S99>=1,"Claimable","Claimed") -> Claimable | J99: =IF(Table3[[#This Row],[Placement Fee & Variables]]>0,0,1) -> 1 | K99: =Table3[[#This Row],[Joining Date]]+180 -> 46115 | L99: =IF(AND(M99="", K99<=TODAY()), "Claimable", "") -> Claimable | N99: =IF(Table3[[#This Row],[6M Stat]]="Claimable",1,0) -> 1 | O99: =Table3[[#This Row],[Joining Date]]+365 -> 46300 | Q99: =IF(AND(P99="", O99<=TODAY()), "Claimable", "") -> Claimable | R99: =IF(Table3[[#This Row],[12 M Stat]]="Claimable",1,0) -> 1 | S99: =Table3[[#This Row],[Placement claim Highlight]]+Table3[[#This Row],[Highlight rule 6M]]+Table3[[#This Row],[Highlight rule 12 M]] -> 3 | T99: =SUM(Table3[[#This Row],[Placement Fee]:[Salary]]) -> 55 | V99: =IF(Table1[[#This Row],[MoL]]="Yes",55,0) -> 55 | W99: =IF(Table1[[#This Row],[Long MoL +3 Years]]="Yes",137.5,0) -> 0 | X99: =IF(Table1[[#This Row],[Gender]]="Female",137.5,0) -> 0 | Y99: =IF(Table1[[#This Row],[Education]]="Bachelors +",55,0) -> 0 | Z99: =IF(Table1[[#This Row],[Salary]]>=600,82.5,0) -> 0
A100: =Table1[[#This Row],[SL No.]] -> 99 | B100: =Table1[[#This Row],[Case manager]] -> Husain | C100: =Table1[[#This Row],[Ref No]] -> JCP/25/244587 | D100: =Table1[[#This Row],[Name]] -> EBRAHIM NAEEM A. MARHOON | E100: ='Placements 26'!F100 -> 45939 | F100: =IF(S100>=1,"Claimable","Claimed") -> Claimable | J100: =IF(Table3[[#This Row],[Placement Fee & Variables]]>0,0,1) -> 1 | K100: =Table3[[#This Row],[Joining Date]]+180 -> 46119 | L100: =IF(AND(M100="", K100<=TODAY()), "Claimable", "") -> Claimable | N100: =IF(Table3[[#This Row],[6M Stat]]="Claimable",1,0) -> 1 | O100: =Table3[[#This Row],[Joining Date]]+365 -> 46304 | Q100: =IF(AND(P100="", O100<=TODAY()), "Claimable", "") -> Claimable | R100: =IF(Table3[[#This Row],[12 M Stat]]="Claimable",1,0) -> 1 | S100: =Table3[[#This Row],[Placement claim Highlight]]+Table3[[#This Row],[Highlight rule 6M]]+Table3[[#This Row],[Highlight rule 12 M]] -> 3 | T100: =SUM(Table3[[#This Row],[Placement Fee]:[Salary]]) -> 55 | V100: =IF(Table1[[#This Row],[MoL]]="Yes",55,0) -> 55 | W100: =IF(Table1[[#This Row],[Long MoL +3 Years]]="Yes",137.5,0) -> 0 | X100: =IF(Table1[[#This Row],[Gender]]="Female",137.5,0) -> 0 | Y100: =IF(Table1[[#This Row],[Education]]="Bachelors +",55,0) -> 0 | Z100: =IF(Table1[[#This Row],[Salary]]>=600,82.5,0) -> 0
...

Sheet Dropdown
A1: Case Manager | B1: MoL | C1: Gender | D1: Education | E1: Claims | F1: Employement Type
A2: Husain | B2: Yes | C2: Male | D2: High School | E2: Claimed | F2: Full time Direct Employment | G2: 550 | H2: 330 | I2: 330
A3: Dina | B3: No | C3: Female | D3: Diploma | E3: Not Claimed | F3: Insourced to Service Provider | G3: 165 | H3: 165 | I3: 165
A4: Malak | D4: Bachelors + | E4: Partial Claimed | F4: Part time Direct Employment | G4: 275
A5: Zainab Mattar | E5: Disputed | F5: Full time Multi Party Employment
A6: Meaad | E6: Terminated | F6: Pro active Job Seeker
A7: Mahdi
A8: Khalifa
A9: Zainab Almaroom
A10: Ameera
